Workbook

Sheet 购物零售方案123
A1: 2023 | B1: 销售 | C1: 利润 | D1: 参考毛利率 | E1: 销售占比 | F1: 利润占比 | H1: 2024 | I1: 销售 | J1: 利润 | K1: 参考毛利率 | L1: 销售占比 | M1: 利润占比 | N1: 销售同比 | O1: 利润同比 | Q1: 2024实际 | R1: 销售 | S1: 利润 | T1: 参考毛利率 | U1: 销售占比 | V1: 利润占比 | W1: 销售同比 | X1: 利润同比 | Y1: * 方案一： 财务底线预测 | Z1: 2025购物零售 (含本地生活) | AA1: 销售 | AB1: 利润 | AC1: 参考毛利率 | AD1: 销售占比 | AE1: 利润占比 | AF1: 销售同比 | AG1: 利润同比24年实际 | AH1: * 方案二： 控制降幅 | AI1: 2025 | AJ1: 销售 | AK1: 利润 | AL1: 参考毛利率 | AM1: 销售占比 | AN1: 利润占比 （年度权重64开） | AO1: 销售同比 | AP1: 利润同比
A2: 1月 | B2: 2.1462181e+08 | C2: 48124681 | D2: =C2*1.12/B2 -> 0.25113777 | E2: =B2/$B$14 -> 0.11008355 | F2: =C2/$C$14 -> 0.11846536 | H2: 1月 | I2: 1.6722146e+08 | J2: 34006764 | K2: =J2*1.12/I2 -> 0.22776728 | L2: =I2/$I$14 -> 0.12602766 | M2: =J2/$J$14 -> 0.11329782 | N2: =I2/B2-1 -> -0.22085525 | O2: =J2/C2-1 -> -0.29336126 | Q2: 1月 | R2: 1.6722146e+08 | S2: 34006764 | T2: =S2*1.12/R2 -> 0.22776728 | U2: =R2/$R$14 -> 0.12637179 | V2: =S2/$S$14 -> 0.11364594 | W2: =R2/B2-1 -> -0.22085525 | X2: =S2/C2-1 -> -0.29336126 | Z2: 1月 | AA2: =AB2*1.12/AC2 -> 1.0672287e+08 | AB2: 26403676 | AC2: 0.2770926 | AD2: =AA2/$AA$14 -> 0.11479197 | AE2: 0.11557371 | AF2: =AA2/I2-1 -> -0.36178722 | AG2: =AB2/S2-1 -> -0.22357575 | AI2: 1月 | AJ2: =AM2*$AJ$14 -> 1.2144924e+08 | AK2: 27381363 | AL2: 0.2770926 | AM2: 0.12598268 | AN2: 0.11557371 | AO2: =AJ2/R2-1 -> -0.27372213 | AP2: =AK2/S2-1 -> -0.19482596
A3: 2月 | B3: 1.5226345e+08 | C3: 30883670 | D3: =C3*1.12/B3 -> 0.22717014 | E3: =B3/$B$14 -> 0.078098781 | F3: =C3/$C$14 -> 0.076024295 | H3: 2月 | I3: 1.093038e+08 | J3: 23684768 | K3: =J3*1.12/I3 -> 0.24269001 | L3: =I3/$I$14 -> 0.082377599 | M3: =J3/$J$14 -> 0.078908787 | N3: =I3/B3-1 -> -0.28214028 | O3: =J3/C3-1 -> -0.23309736 | Q3: 2月 | R3: 1.093038e+08 | S3: 23684768 | T3: =S3*1.12/R3 -> 0.24269001 | U3: =R3/$R$14 -> 0.082602538 | V3: =S3/$S$14 -> 0.079151245 | W3: =R3/B3-1 -> -0.28214028 | X3: =S3/C3-1 -> -0.23309736 | Z3: 2月 | AA3: =AB3*1.12/AC3 -> 73034628 | AB3: 17651897 | AC3: 0.27069522 | AD3: =AA3/$AA$14 -> 0.078556631 | AE3: 0.077900465 | AF3: =AA3/I3-1 -> -0.33181985 | AG3: =AB3/S3-1 -> -0.25471522 | AI3: 2月 | AJ3: =AM3*$AJ$14 -> 79534596 | AK3: 18305519 | AL3: 0.27069522 | AM3: 0.082503448 | AN3: 0.077900465 | AO3: =AJ3/R3-1 -> -0.27235286 | AP3: =AK3/S3-1 -> -0.22711848
A4: 3月 | B4: 1.6175068e+08 | C4: 33760031 | D4: =C4*1.12/B4 -> 0.23376245 | E4: =B4/$B$14 -> 0.082964959 | F4: =C4/$C$14 -> 0.083104843 | H4: 3月 | I4: 1.1619973e+08 | J4: 25054034 | K4: =J4*1.12/I4 -> 0.24148523 | L4: =I4/$I$14 -> 0.087574766 | M4: =J4/$J$14 -> 0.083470668 | N4: =I4/B4-1 -> -0.28161212 | O4: =J4/C4-1 -> -0.25787883 | Q4: 3月 | R4: 1.1619973e+08 | S4: 25054034 | T4: =S4*1.12/R4 -> 0.24148523 | U4: =R4/$R$14 -> 0.087813896 | V4: =S4/$S$14 -> 0.083727143 | W4: =R4/B4-1 -> -0.28161212 | X4: =S4/C4-1 -> -0.25787883 | Z4: 3月 | AA4: =AB4*1.12/AC4 -> 77033742 | AB4: 18977869 | AC4: 0.27592082 | AD4: =AA4/$AA$14 -> 0.082858109 | AE4: 0.083478223 | AF4: =AA4/I4-1 -> -0.33705747 | AG4: =AB4/S4-1 -> -0.24252241 | AI4: 3月 | AJ4: =AM4*$AJ$14 -> 87237230 | AK4: 19680590 | AL4: 0.27592082 | AM4: 0.090493605 | AN4: 0.083478223 | AO4: =AJ4/R4-1 -> -0.24924755 | AP4: =AK4/S4-1 -> -0.21447419
A5: 4月 | B5: 1.8408006e+08 | C5: 34204404 | D5: =C5*1.12/B5 -> 0.20811017 | E5: =B5/$B$14 -> 0.094418117 | F5: =C5/$C$14 -> 0.084198728 | H5: 4月 | I5: 1.1157144e+08 | J5: 24919117 | K5: =J5*1.12/I5 -> 0.25014834 | L5: =I5/$I$14 -> 0.084086625 | M5: =J5/$J$14 -> 0.083021177 | N5: =I5/B5-1 -> -0.39389718 | O5: =J5/C5-1 -> -0.27146467 | Q5: 4月 | R5: 1.1157144e+08 | S5: 24919117 | T5: =S5*1.12/R5 -> 0.25014834 | U5: =R5/$R$14 -> 0.084316231 | V5: =S5/$S$14 -> 0.083276271 | W5: =R5/B5-1 -> -0.39389718 | X5: =S5/C5-1 -> -0.27146467 | Z5: 4月 | AA5: =AB5*1.12/AC5 -> 74747016 | AB5: 19051014 | AC5: 0.28545803 | AD5: =AA5/$AA$14 -> 0.080398488 | AE5: 0.083645254 | AF5: =AA5/I5-1 -> -0.33005244 | AG5: =AB5/S5-1 -> -0.23548598 | AI5: 4月 | AJ5: =AM5*$AJ$14 -> 76438412 | AK5: 19756444 | AL5: 0.28545803 | AM5: 0.07929169 | AN5: 0.083645254 | AO5: =AJ5/R5-1 -> -0.31489268 | AP5: =AK5/S5-1 -> -0.20717721
A6: 5月 | B6: 1.529621e+08 | C6: 31976609 | D6: =C6*1.12/B6 -> 0.23413514 | E6: =B6/$B$14 -> 0.07845713 | F6: =C6/$C$14 -> 0.078714711 | H6: 5月 | I6: 99069605 | J6: 22040447 | K6: =J6*1.12/I6 -> 0.24917128 | L6: =I6/$I$14 -> 0.074664525 | M6: =J6/$J$14 -> 0.073430525 | N6: =I6/B6-1 -> -0.35232579 | O6: =J6/C6-1 -> -0.31073219 | Q6: 5月 | R6: 99069605 | S6: 22040447 | T6: =S6*1.12/R6 -> 0.24917128 | U6: =R6/$R$14 -> 0.074868402 | V6: =S6/$S$14 -> 0.073656151 | W6: =R6/B6-1 -> -0.35232579 | X6: =S6/C6-1 -> -0.31073219 | Z6: 5月 | AA6: =AB6*1.12/AC6 -> 75825989 | AB6: 17332853 | AC6: 0.25601769 | AD6: =AA6/$AA$14 -> 0.081559041 | AE6: 0.075679575 | AF6: =AA6/I6-1 -> -0.23461904 | AG6: =AB6/S6-1 -> -0.21358888 | AI6: 5月 | AJ6: =AM6*$AJ$14 -> 75827612 | AK6: 17974661 | AL6: 0.25601769 | AM6: 0.07865809 | AN6: 0.075679575 | AO6: =AJ6/R6-1 -> -0.23460266 | AP6: =AK6/S6-1 -> -0.1844693
A7: 6月 | B7: 1.4523334e+08 | C7: 31037674 | D7: =C7*1.12/B7 -> 0.23935409 | E7: =B7/$B$14 -> 0.074492906 | F7: =C7/$C$14 -> 0.076403396 | H7: 6月 | I7: 99516460 | J7: 22879456 | K7: =J7*1.12/I7 -> 0.25749499 | L7: =I7/$I$14 -> 0.0750013 | M7: =J7/$J$14 -> 0.076225787 | N7: =I7/B7-1 -> -0.31478227 | O7: =J7/C7-1 -> -0.2628489 | Q7: 6月 | R7: 99516460 | S7: 22879456 | T7: =S7*1.12/R7 -> 0.25749499 | U7: =R7/$R$14 -> 0.075206097 | V7: =S7/$S$14 -> 0.076460002 | W7: =R7/B7-1 -> -0.31478227 | X7: =S7/C7-1 -> -0.2628489 | Z7: 6月 | AA7: =AB7*1.12/AC7 -> 71544978 | AB7: 17388881 | AC7: 0.27221403 | AD7: =AA7/$AA$14 -> 0.076954351 | AE7: 0.07643736 | AF7: =AA7/I7-1 -> -0.28107392 | AG7: =AB7/S7-1 -> -0.23997838 | AI7: 6月 | AJ7: =AM7*$AJ$14 -> 71670920 | AK7: 18032764 | AL7: 0.27221403 | AM7: 0.074346238 | AN7: 0.07643736 | AO7: =AJ7/R7-1 -> -0.27980838 | AP7: =AK7/S7-1 -> -0.21183596
A8: 7月 | B8: 1.3255032e+08 | C8: 28669117 | D8: =C8*1.12/B8 -> 0.24224318 | E8: =B8/$B$14 -> 0.067987547 | F8: =C8/$C$14 -> 0.070572877 | H8: 7月 | I8: 96727683 | J8: 21936037 | K8: =J8*1.12/I8 -> 0.25399515 | L8: =I8/$I$14 -> 0.072899518 | M8: =J8/$J$14 -> 0.073082671 | N8: =I8/B8-1 -> -0.2702569 | O8: =J8/C8-1 -> -0.23485481 | Q8: 7月 | R8: 96727683 | S8: 21936037 | T8: =S8*1.12/R8 -> 0.25399515 | U8: =R8/$R$14 -> 0.073098576 | V8: =S8/$S$14 -> 0.073307228 | W8: =R8/B8-1 -> -0.2702569 | X8: =S8/C8-1 -> -0.23485481 | Z8: 7月 | AA8: =AB8*1.12/AC8 -> 68837414 | AB8: 16366992 | AC8: 0.26629459 | AD8: =AA8/$AA$14 -> 0.074042073 | AE8: 0.072213487 | AF8: =AA8/I8-1 -> -0.28833802 | AG8: =AB8/S8-1 -> -0.25387655 | AI8: 7月 | AJ8: =AM8*$AJ$14 -> 69915671 | AK8: 16973036 | AL8: 0.26629459 | AM8: 0.07252547 | AN8: 0.072213487 | AO8: =AJ8/R8-1 -> -0.27719067 | AP8: =AK8/S8-1 -> -0.22624876
A9: 8月 | B9: 1.3821707e+08 | C9: 30480858 | D9: =C9*1.12/B9 -> 0.24699236 | E9: =B9/$B$14 -> 0.070894132 | F9: =C9/$C$14 -> 0.07503272 | H9: 8月 | I9: 93524294 | J9: 21669839 | K9: =J9*1.12/I9 -> 0.25950711 | L9: =I9/$I$14 -> 0.070485261 | M9: =J9/$J$14 -> 0.072195797 | N9: =I9/B9-1 -> -0.3233521 | O9: =J9/C9-1 -> -0.2890673 | Q9: 8月 | R9: 93524294 | S9: 21669839 | T9: =S9*1.12/R9 -> 0.25950711 | U9: =R9/$R$14 -> 0.070677727 | V9: =S9/$S$14 -> 0.072417629 | W9: =R9/B9-1 -> -0.3233521 | X9: =S9/C9-1 -> -0.2890673 | Z9: 8月 | AA9: =AB9*1.12/AC9 -> 70401539 | AB9: 16773123 | AC9: 0.2668393 | AD9: =AA9/$AA$14 -> 0.075724459 | AE9: 0.073463665 | AF9: =AA9/I9-1 -> -0.24723795 | AG9: =AB9/S9-1 -> -0.2259692 | AI9: 8月 | AJ9: =AM9*$AJ$14 -> 71215317 | AK9: 17394206 | AL9: 0.2668393 | AM9: 0.073873628 | AN9: 0.073463665 | AO9: =AJ9/R9-1 -> -0.23853671 | AP9: =AK9/S9-1 -> -0.19730804
A10: 9月 | B10: 1.5463191e+08 | C10: 30993082 | D10: =C10*1.12/B10 -> 0.22448312 | E10: =B10/$B$14 -> 0.079313607 | F10: =C10/$C$14 -> 0.076293629 | H10: 9月 | I10: 96919381 | J10: 22210990 | K10: =J10*1.12/I10 -> 0.25667012 | L10: =I10/$I$14 -> 0.073043993 | M10: =J10/$J$14 -> 0.073998712 | N10: =I10/B10-1 -> -0.37322521 | O10: =J10/C10-1 -> -0.28335652 | Q10: 9月 | R10: 96919381 | S10: 22210990 | T10: =S10*1.12/R10 -> 0.25667012 | U10: =R10/$R$14 -> 0.073243445 | V10: =S10/$S$14 -> 0.074226084 | W10: =R10/B10-1 -> -0.37322521 | X10: =S10/C10-1 -> -0.28335652 | Z10: 9月 | AA10: =AB10*1.12/AC10 -> 68489876 | AB10: 17122276 | AC10: 0.27999685 | AD10: =AA10/$AA$14 -> 0.073668259 | AE10: 0.075053102 | AF10: =AA10/I10-1 -> -0.29333147 | AG10: =AB10/S10-1 -> -0.22910794 | AI10: 9月 | AJ10: =AM10*$AJ$14 -> 69054266 | AK10: 17756288 | AL10: 0.27999685 | AM10: 0.071631911 | AN10: 0.075053102 | AO10: =AJ10/R10-1 -> -0.28750818 | AP10: =AK10/S10-1 -> -0.200563
A11: 10月 | B11: 1.4214851e+08 | C11: 30396484 | D11: =C11*1.12/B11 -> 0.23949645 | E11: =B11/$B$14 -> 0.072910636 | F11: =C11/$C$14 -> 0.074825022 | H11: 10月 | I11: 106250450 | J11: 23889521 | K11: =J11*1.12/I11 -> 0.25182259 | L11: =I11/$I$14 -> 0.080076421 | M11: =J11/$J$14 -> 0.079590948 | N11: =I11/B11-1 -> -0.2525391 | O11: =J11/C11-1 -> -0.2140696 | Q11: 10月 | R11: 106250450 | S11: 23889521 | T11: =S11*1.12/R11 -> 0.25182259 | U11: =R11/$R$14 -> 0.080295076 | V11: =S11/$S$14 -> 0.079835502 | W11: =R11/B11-1 -> -0.2525391 | X11: =S11/C11-1 -> -0.2140696 | Z11: 10月 | AA11: =AB11*1.12/AC11 -> 73382319 | AB11: 17593312 | AC11: 0.26851848 | AD11: =AA11/$AA$14 -> 0.07893061 | AE11: 0.07783131 | AF11: =AA11/I11-1 -> -0.3093458 | AG11: =AB11/S11-1 -> -0.26355527 | AI11: 10月 | AJ11: =AM11*$AJ$14 -> 74258175 | AK11: 18244765 | AL11: 0.26851848 | AM11: 0.07703007 | AN11: 0.07783131 | AO11: =AJ11/R11-1 -> -0.30110249 | AP11: =AK11/S11-1 -> -0.23628587
A12: 11月 | B12: 1.9186272e+08 | C12: 38054014 | D12: =C12*1.12/B12 -> 0.22214058 | E12: =B12/$B$14 -> 0.09840999 | F12: =C12/$C$14 -> 0.093675057 | H12: 11月 | I12: 117875870 | J12: 29188984 | K12: =J12*1.12/I12 -> 0.27733973 | L12: =I12/$I$14 -> 0.088838003 | M12: =J12/$J$14 -> 0.097246776 | N12: =I12/B12-1 -> -0.3856239 | O12: =J12/C12-1 -> -0.23295912 | Q12: 11月 | R12: 117875870 | S12: 29188984 | T12: =S12*1.12/R12 -> 0.27733973 | U12: =R12/$R$14 -> 0.089080582 | V12: =S12/$S$14 -> 0.097545581 | W12: =R12/B12-1 -> -0.3856239 | X12: =S12/C12-1 -> -0.23295912 | Z12: 11月 | AA12: =AB12*1.12/AC12 -> 84302979 | AB12: 22076337 | AC12: 0.29329329 | AD12: =AA12/$AA$14 -> 0.090676959 | AE12: 0.095997371 | AF12: =AA12/I12-1 -> -0.28481564 | AG12: =AB12/S12-1 -> -0.24367572 | AI12: 11月 | AJ12: =AM12*$AJ$14 -> 84972736 | AK12: 22893790 | AL12: 0.29329329 | AM12: 0.088144582 | AN12: 0.095997371 | AO12: =AJ12/R12-1 -> -0.27913375 | AP12: =AK12/S12-1 -> -0.21567021
A13: 12月 | B13: 1.793045e+08 | C13: 37653592 | D13: =C13*1.12/B13 -> 0.2351978 | E13: =B13/$B$14 -> 0.091968641 | F13: =C13/$C$14 -> 0.092689367 | G13: * 12月财务底线 | H13: 12月 | I13: =J13*1.12/K13 -> 1.1268296e+08 | J13: 28673788 | K13: 0.285 | L13: =I13/$I$14 -> 0.084924326 | M13: =J13/$J$14 -> 0.095530336 | N13: =I13/B13-1 -> -0.37155532 | O13: =J13/C13-1 -> -0.23848466 | P13: * 12月业务预测 | Q13: 12月 | R13: =S13*1.12/T13 -> 1.0906972e+08 | S13: 27754349 | T13: 0.285 | U13: =R13/$R$14 -> 0.082425641 | V13: =S13/$S$14 -> 0.092751226 | W13: =R13/B13-1 -> -0.39170672 | X13: =S13/C13-1 -> -0.26290304 | Z13: 12月 | AA13: =AB13*1.12/AC13 -> 85383380 | AB13: 21793176 | AC13: 0.28586778 | AD13: =AA13/$AA$14 -> 0.091839047 | AE13: 0.092726482 | AF13: =AA13/I13-1 -> -0.24226891 | AG13: =AB13/S13-1 -> -0.21478336 | AI13: 12月 | AJ13: =AM13*$AJ$14 -> 82441239 | AK13: 22600144 | AL13: 0.28586778 | AM13: 0.08551859 | AN13: 0.092726482 | AO13: =AJ13/R13-1 -> -0.24414183 | AP13: =AK13/S13-1 -> -0.18570801
A14: 合计 | B14: =SUM(B2:B13) -> 1.9496265e+09 | C14: =SUM(C2:C13) -> 4.0623422e+08 | D14: =C14*1.12/B14 -> 0.23336897 | E14: =B14/$B$14 -> 1 | F14: =C14/$C$14 -> 1 | H14: 合计 | I14: =SUM(I2:I13) -> 1.3268631e+09 | J14: =SUM(J2:J13) -> 3.0015374e+08 | K14: =J14*1.12/I14 -> 0.25335861 | L14: =I14/$I$14 -> 1 | M14: =J14/$J$14 -> 1 | N14: =I14/B14-1 -> -0.319427 | O14: =J14/C14-1 -> -0.26113131 | Q14: 合计 | R14: =SUM(R2:R13) -> 1.3232499e+09 | S14: =SUM(S2:S13) -> 2.992343e+08 | T14: =S14*1.12/R14 -> 0.25327221 | U14: =R14/$R$14 -> 1 | V14: =S14/$S$14 -> 1 | W14: =R14/B14-1 -> -0.3212803 | X14: =S14/C14-1 -> -0.26339463 | Z14: 合计 | AA14: =SUM(AA2:AA13) -> 9.2970673e+08 | AB14: =AB15*AE15 -> 2.2853141e+08 | AC14: =AB14*1.12/AA14 -> 0.27530743 | AD14: =AA14/$AA$14 -> 1 | AE14: =AB14/$AB$14 -> 1 | AF14: =AA14/I14-1 -> -0.29931979 | AG14: =AB14/S14-1 -> -0.23627939 | AI14: 合计 | AJ14: =AK14*1.12/AL14 -> 9.6401542e+08 | AK14: =S14*(1-0.208) -> 2.3699357e+08 | AL14: 0.27534082 | AM14: 1 | AN14: 1 | AO14: =AJ14/R14-1 -> -0.27147893 | AP14: =AK14/S14-1 -> -0.208
Q15: 12月实际预测低于底限 | Z15: 报OPG P1利润 | AB15: 2.4497346e+08 | AE15: 0.93288231 | AI15: 计划P1目标 | AK15: 2.5404445e+08 | AN15: =AK14/AK15 -> 0.93288231 | AP15: 同比降幅控制 | AQ15: =AK15/AB15-1 -> 0.037028449
A16: 本页所有口径：购物零售+本地生活 | H16: 底限11月 | J16: 29656000 | Z16: * 25年春节放假期间：1.28-2.4；本页所有口径：购物零售+本地生活 | AK16: 自营旅游折返30万利润 | AL16: =AK15/365 -> 696012.18
H17: 底限12月 | J17: 29167000 | Z17: 注：购物零售2025年利润底限，以2024年度”购物零售+本地生活“占P1比重（ 93.3%）推算；2024年旅行社下“本地生活类”（消费服务不含住宿）利润额364万；
AB18: =AB15/365 -> 671160.16 | AH18: 方案二思路： | AI18: 1. 购物零售24年实际利润同比↓ 26.3%，考虑大屏直播有效时长，2024年导流类/东方荟普通商品/汽车等占比6.2%、电视商品贡献占比88%，时长因素影响5.5个百分点，取 -20.8%作为25年预估降幅；
AI19: 2. 25年分月利润比重按24年权重60%，23年权重40%计算；
Y20: 目标区间上限 | AB20: =AB21/365 -> 738276.18 | AI20: 3. 25年毛利率按 27.5%计；25年分月销售额按毛利率反推；
Z21: 参考：底限↑ 10% | AB21: =AB15*1.1 -> 2.6947081e+08
Z22: 参考：2023年上报OPG版，日均利润额147.8万；目标方案取高，日均170万，年中调整到165万（业务板块间调整），较财务底限上调11.6%-15%；
Z24: 参考：2024年实际 ↓10% | AB24: =S14*0.9 -> 2.6931087e+08
Z25: 参考：2024年目标框定：TV电视商品下降15%、IC电商商品增长10%，购物零售较2023年实际合计下降12%；
Z27: 财务底限目标P1，同比24年实际业绩，降幅24.0%

Sheet 0. 方案
B1: 2026年目标分解初步方案（拟）
B2: 存量整体 = 仅电视端及APP业务（含自营业务）+ 数据库营销 + 私域整体；
B4: 一、目标分解思路
B5: （一）基本规则：
B6: 1.为确保公司整体目标的达成进度，各渠道均参考历史月度比重，避免将目标重心全部分摊到下半年，减少公司风险。
B7: 2.复盘2025年度各渠道目标执行情况
B8: 存量整体、电视商品、数据库营销上半年占比均超50%（51%-55%），私域整体及第三方上半年占比43%、46%。 下半年目标比重过高，易导致滚动目标失效，最终缺口难以统筹完成。因此，在考虑业务趋势或成长性的同时，需重点优化上下半年目标的合理比重。
B9: 3.从存量整体角度，盘点2023-2025近三年的月度趋势，按1:2:3（即：17%：33%：50%）的权重，初步形成整体的月度目标分配，用于校验分渠道目标之和。
B10: 4.按存量整体趋势的客观分配，上半年占比51.4%；依据分渠道规则设定的目标，上半年合计占比51.3%；两种方案比重趋势吻合。
B12: （二）分渠道规则：
B13: 1. 仅电视端及APP业务（含自营业务）：同比下降9%左右，具体降幅与实际完成情况相关。
B14: 考虑业务结构的相似性与可参考性，2026年目标分配主要参考2025各月占比；
... B32: 4. 业务非常规举措版是在以上基础逻辑之上，再加上业务预计实施非常规举措后可额外提升的利润。
B35: 利润目标 | C35: 1月 | D35: 2月 | E35: 3月 | F35: Q1
B36: 存量整体 | C36: 23226681 | D36: 16184643 | E36: 18883028 | F36: 58294352
B37: 仅电视端及APP业务 （含自营业务） | C37: 19601681 | D37: 13951219 | E37: 15859315 | F37: 49412216
B38: 数据库营销 | C38: 2850000 | D38: 1600000 | E38: 2200000 | F38: 6650000
B39: 私域 | C39: 775000 | D39: 633423.97 | E39: 823712.13 | F39: 2232136.1
B42: 基础版 | H42: 业务非常规举措版
B43: 利润金额 | C43: 1月 | D43: 2月 | E43: 3月 | F43: Q1 | H43: 利润金额 | I43: 1月 | J43: 2月 | K43: 3月 | L43: Q1
B44: 存量整体 | C44: 20820547 | D44: 14409561 | E44: 16416014 | F44: 51646122 | H44: 存量整体 | I44: 21655547 | J44: 15169561 | K44: 17491014 | L44: 54316122
B45: 仅电视端及APP业务 （含自营业务） | C45: 17900929 | D45: 12136832 | E45: 13496396 | F45: 43534158 | H45: 仅电视端及APP业务 （含自营业务） | I45: 18435929 | J45: 12896832 | K45: 14571396 | L45: 45904158
B46: 数据库营销 | C46: 2241015.1 | D46: 1659797 | E46: 2241015.1 | F46: 6141827.1 | H46: 数据库营销 | I46: 2541015.1 | J46: 1659797 | K46: 2241015.1 | L46: 6441827.1
B47: 私域 | C47: 678602.73 | D47: 612931.5 | E47: 678602.73 | F47: 1970137 | H47: 私域 | I47: 678602.73 | J47: 612931.5 | K47: 678602.73 | L47: 1970137
B49: 基础版 | H49: 业务非常规举措版
B50: 预测达成率 | C50: 1月 | D50: 2月 | E50: 3月 | F50: Q1 | H50: 预测达成率 | I50: 1月 | J50: 2月 | K50: 3月 | L50: Q1
B51: 存量整体 | C51: 0.89640648 | D51: 0.89032304 | E51: 0.86935287 | F51: 0.88595414 | H51: 存量整体 | I51: 0.93235652 | J51: 0.93728113 | K51: 0.9262823 | L51: 0.93175618
B52: 仅电视端及APP业务 （含自营业务） | C52: 0.91323441 | D52: 0.86994779 | E52: 0.8510075 | F52: 0.8810404 | H52: 仅电视端及APP业务 （含自营业务） | I52: 0.94052799 | J52: 0.92442331 | K52: 0.918791 | L52: 0.92900425
B53: 数据库营销 | C53: 0.78632107 | D53: 1.0373731 | E53: 1.0186432 | F53: 0.92358302 | H53: 数据库营销 | I53: 0.89158423 | J53: 1.0373731 | K53: 1.0186432 | L53: 0.9686958
B54: 私域 | C54: 0.87561643 | D54: 0.96764811 | E54: 0.82383481 | F54: 0.88262403 | H54: 私域 | I54: 0.87561643 | J54: 0.96764811 | K54: 0.82383481 | L54: 0.88262403

Sheet 1. 按目标v0.2
B2: 25年实际 | X2: 25年实际利润 | AT2: 25年实际
B3: 销售金额 | C3: 1月 | D3: 2月 | E3: 3月 | F3: 4月 | G3: 5月 | H3: 6月 | I3: 7月 | J3: 8月 | K3: 9月 | L3: 10月 | M3: 11月 | N3: 12月 | O3: 合计 | P3: H1 | Q3: H2 | R3: Q1 | S3: Q2 | T3: Q3 | U3: Q4 | X3: 利润金额 | Y3: 1月 | Z3: 2月 | AA3: 3月 | AB3: 4月 | AC3: 5月 | AD3: 6月 | AE3: 7月 | AF3: 8月 | AG3: 9月 | AH3: 10月 | AI3: 11月 | AJ3: 12月 | AK3: 合计 | AL3: H1 | AM3: H2 | AN3: Q1 | AO3: Q2 | AP3: Q3 | AQ3: Q4 | AT3: 手动毛利率 | AU3: 1月 | AV3: 2月 | AW3: 3月 | AX3: 4月 | AY3: 5月 | AZ3: 6月 | BA3: 7月 | BB3: 8月 | BC3: 9月 | BD3: 10月 | BE3: 11月 | BF3: 12月e | BG3: 合计 | BH3: H1 | BI3: H2 | BJ3: Q1 | BK3: Q2 | BL3: Q3 | BM3: Q4
A4: 25年口径 | B4: 1电视及APP业务（含自营旅游） | C4: 1.0781329e+08 | D4: 81747623 | E4: 84492124 | F4: 84646543 | G4: 83475150 | H4: 78490927 | I4: 80703402 | J4: 74913585 | K4: 83150977 | L4: 90542776 | M4: 88943142 | N4: 82689520 | O4: =SUM(C4:N4) -> 1.0216091e+09 | P4: =SUM(C4:H4) -> 5.2066566e+08 | Q4: =SUM(I4:N4) -> 5.009434e+08 | R4: =SUM(C4:E4) -> 2.7405304e+08 | S4: =SUM(F4:H4) -> 246612620 | T4: =SUM(I4:K4) -> 238767964 | U4: =SUM(L4:N4) -> 2.6217544e+08 | V4: 0.91806803 | W4: 25年口径 | X4: 1电视及APP业务（含自营旅游） | Y4: 25910624 | Z4: 18677402 | AA4: 20898078 | AB4: 20177139 | AC4: 18790332 | AD4: 19119339 | AE4: 18619342 | AF4: 17665712 | AG4: 17937357 | AH4: 17492227 | AI4: 21609474 | AJ4: 22762989 | AK4: =SUM(Y4:AJ4) -> 2.3966002e+08 | AL4: =SUM(Y4:AD4) -> 1.2357291e+08 | AM4: =SUM(AE4:AJ4) -> 1.160871e+08 | AN4: =SUM(Y4:AA4) -> 65486104 | AO4: =SUM(AB4:AD4) -> 58086810 | AP4: =SUM(AE4:AG4) -> 54222411 | AQ4: =SUM(AH4:AJ4) -> 61864690 | AR4: 0.905767 | AS4: 1.12 | AT4: 1电视及APP业务（含自营旅游） | AU4: =Y4*$AS4/C4 -> 0.2691681 | AV4: =Z4*$AS4/D4 -> 0.25589356 | AW4: =AA4*$AS4/E4 -> 0.2770181 | AX4: =AB4*$AS4/F4 -> 0.26697364 | AY4: =AC4*$AS4/G4 -> 0.25211302 | AZ4: =AD4*$AS4/H4 -> 0.272817 | BA4: =AE4*$AS4/I4 -> 0.25839882 | BB4: =AF4*$AS4/J4 -> 0.26411227 | ... BM4: =AQ4*$AS4/U4 -> 0.26428278
A5: 25年口径 | B5: 7数据库营销 | C5: 11875837 | D5: 9505244.6 | E5: 8448582.2 | F5: 10411125 | G5: 7751860 | H5: 8753480.6 | I5: 9067021.2 | J5: 7495744.8 | K5: 13999988 | L5: 18029060 | M5: 16780507 | N5: 8632591.5 | O5: =SUM(C5:N5) -> 1.3075104e+08 | P5: =SUM(C5:H5) -> 56746130 | Q5: =SUM(I5:N5) -> 74004912 | R5: =SUM(C5:E5) -> 29829664 | S5: =SUM(F5:H5) -> 26916466 | T5: =SUM(I5:K5) -> 30562754 | U5: =SUM(L5:N5) -> 43442158 | V5: 0.91563774 | W5: 25年口径 | X5: 7数据库营销 | Y5: 2549751.2 | Z5: 1880081.8 | AA5: 2130051.2 | AB5: 2615080.4 | AC5: 1752152.4 | AD5: 2225886 | AE5: 1876419.1 | AF5: 1908652.7 | AG5: 2008057.6 | AH5: 1945294.6 | AI5: 3494718 | AJ5: 2180017.1 | AK5: =SUM(Y5:AJ5) -> 26566162 | AL5: =SUM(Y5:AD5) -> 13153003 | AM5: =SUM(AE5:AJ5) -> 13413159 | AN5: =SUM(Y5:AA5) -> 6559884.2 | AO5: =SUM(AB5:AD5) -> 6593118.8 | AP5: =SUM(AE5:AG5) -> 5793129.4 | AQ5: =SUM(AH5:AJ5) -> 7620029.7 | AR5: 0.90104535 | AS5: 1.12 | AT5: 7数据库营销 | AU5: =Y5*$AS5/C5 -> 0.24046484 | AV5: =Z5*$AS5/D5 -> 0.22152945 | AW5: =AA5*$AS5/E5 -> 0.28237369 | AX5: =AB5*$AS5/F5 -> 0.28132311 | AY5: =AC5*$AS5/G5 -> 0.25315353 | AZ5: =AD5*$AS5/H5 -> 0.28480012 | BA5: =AE5*$AS5/I5 -> 0.23178388 | BB5: =AF5*$AS5/J5 -> 0.28518727 | ... BM5: =AQ5*$AS5/U5 -> 0.19645509
A6: 25年口径 | B6: 8私域整体 | C6: 5280469.7 | D6: 5228202.1 | E6: 5686460.7 | F6: 4949084.3 | G6: 4623575.5 | H6: 4963729.5 | I6: 5789922.8 | J6: 7084063.3 | K6: 5517952.4 | L6: 6676835 | M6: 5965314.6 | N6: 7951606.3 | O6: =SUM(C6:N6) -> 69717216 | P6: =SUM(C6:H6) -> 30731522 | Q6: =SUM(I6:N6) -> 38985694 | R6: =SUM(C6:E6) -> 16195133 | S6: =SUM(F6:H6) -> 14536389 | T6: =SUM(I6:K6) -> 18391938 | U6: =SUM(L6:N6) -> 20593756 | V6: 0.87837455 | W6: 25年口径 | X6: 8私域整体 | Y6: 573137.28 | Z6: 613994.73 | AA6: 694290.26 | AB6: 571341.18 | AC6: 565277.8 | AD6: 628136.96 | AE6: 728343.65 | AF6: 803735.23 | AG6: 605885.04 | AH6: 791985.12 | AI6: 680080.68 | AJ6: 799188.63 | AK6: =SUM(Y6:AJ6) -> 8055396.6 | AL6: =SUM(Y6:AD6) -> 3646178.2 | AM6: =SUM(AE6:AJ6) -> 4409218.3 | AN6: =SUM(Y6:AA6) -> 1881422.3 | AO6: =SUM(AB6:AD6) -> 1764755.9 | AP6: =SUM(AE6:AG6) -> 2137963.9 | AQ6: =SUM(AH6:AJ6) -> 2271254.4 | AR6: 0.89709832 | AS6: 1.12 | AT6: 8私域整体 | AU6: =Y6*$AS6/C6 -> 0.12156376 | AV6: =Z6*$AS6/D6 -> 0.13153166 | AW6: =AA6*$AS6/E6 -> 0.13674676 | AX6: =AB6*$AS6/F6 -> 0.12929707 | AY6: =AC6*$AS6/G6 -> 0.13693107 | AZ6: =AD6*$AS6/H6 -> 0.14173081 | BA6: =AE6*$AS6/I6 -> 0.14089046 | BB6: =AF6*$AS6/J6 -> 0.12707163 | ... BM6: =AQ6*$AS6/U6 -> 0.12352312
A7: 25年口径 | B7: 9私域-东购商品 | C7: 2871360.4 | D7: 3366411.8 | E7: 3379447.8 | F7: 2675906.4 | G7: 2563448.3 | H7: 3021255.9 | I7: 3773571 | J7: 5072870 | K7: 3530388.4 | L7: 4745655.6 | M7: 3798862.2 | N7: 6133310.3 | O7: =SUM(C7:N7) -> 44932488 | P7: =SUM(C7:H7) -> 17877831 | Q7: =SUM(I7:N7) -> 27054658 | R7: =SUM(C7:E7) -> 9617219.9 | S7: =SUM(F7:H7) -> 8260610.6 | T7: =SUM(I7:K7) -> 12376829 | U7: =SUM(L7:N7) -> 14677828 | V7: 0.85024824 | W7: 25年口径 | X7: 9私域-东购商品 | Y7: 300071.9 | Z7: 384120.96 | AA7: 411329.62 | AB7: 328537.07 | AC7: 327206.24 | AD7: 401054.42 | AE7: 491893.96 | AF7: 570942.71 | AG7: 381189.1 | AH7: 568369.12 | AI7: 445359.18 | AJ7: 591029.63 | AK7: =SUM(Y7:AJ7) -> 5201103.9 | AL7: =SUM(Y7:AD7) -> 2152320.2 | AM7: =SUM(AE7:AJ7) -> 3048783.7 | AN7: =SUM(Y7:AA7) -> 1095522.5 | AO7: =SUM(AB7:AD7) -> 1056797.7 | AP7: =SUM(AE7:AG7) -> 1444025.8 | AQ7: =SUM(AH7:AJ7) -> 1604757.9 | AR7: 0.88615695 | AS7: 1.12 | AT7: 9私域-东购商品 | AU7: =Y7*$AS7/C7 -> 0.11704575 | AV7: =Z7*$AS7/D7 -> 0.12779645 | AW7: =AA7*$AS7/E7 -> 0.13632084 | AX7: =AB7*$AS7/F7 -> 0.13750911 | AY7: =AC7*$AS7/G7 -> 0.14296016 | AZ7: =AD7*$AS7/H7 -> 0.14867359 | BA7: =AE7*$AS7/I7 -> 0.14599467 | BB7: =AF7*$AS7/J7 -> 0.12605406 | ... BM7: =AQ7*$AS7/U7 -> 0.12245196
A8: 25年口径 | B8: 10私域-第三方 | C8: 2409109.3 | D8: 1861790.4 | E8: 2307012.9 | F8: 2273177.9 | G8: 2060127.2 | H8: 1942473.6 | I8: 2016351.9 | J8: 2011193.3 | K8: 1987563.9 | L8: 1931179.4 | M8: 2166452.5 | N8: 1818296 | O8: =SUM(C8:N8) -> 24784728 | P8: =SUM(C8:H8) -> 12853691 | Q8: =SUM(I8:N8) -> 11931037 | R8: =SUM(C8:E8) -> 6577912.6 | S8: =SUM(F8:H8) -> 6275778.7 | T8: =SUM(I8:K8) -> 6015109.1 | U8: =SUM(L8:N8) -> 5915927.8 | V8: 0.90245668 | W8: 25年口径 | X8: 10私域-第三方 | Y8: 273065.38 | Z8: 229873.77 | AA8: 282960.64 | AB8: 242804.11 | AC8: 238071.56 | AD8: 227082.54 | AE8: 236449.69 | AF8: 232792.52 | AG8: 224695.94 | AH8: 223616 | AI8: 234721.5 | AJ8: 208159 | AK8: =SUM(Y8:AJ8) -> 2854292.6 | AL8: =SUM(Y8:AD8) -> 1493858 | AM8: =SUM(AE8:AJ8) -> 1360434.6 | AN8: =SUM(Y8:AA8) -> 785899.79 | AO8: =SUM(AB8:AD8) -> 707958.21 | AP8: =SUM(AE8:AG8) -> 693938.15 | AQ8: =SUM(AH8:AJ8) -> 666496.5 | AR8: 0.90681515 | AS8: 1.12 | AT8: 10私域-第三方 | AU8: =Y8*$AS8/C8 -> 0.12694867 | AV8: =Z8*$AS8/D8 -> 0.1382855 | AW8: =AA8*$AS8/E8 -> 0.13737067 | AX8: =AB8*$AS8/F8 -> 0.11963015 | AY8: =AC8*$AS8/G8 -> 0.12942897 | AZ8: =AD8*$AS8/H8 -> 0.13093226 | BA8: =AE8*$AS8/I8 -> 0.13133802 | BB8: =AF8*$AS8/J8 -> 0.12963827 | ... BM8: =AQ8*$AS8/U8 -> 0.12618073
B9: 存量整体 | C9: =C4+C8 -> 1.102224e+08 | D9: =D4+D8 -> 83609413 | E9: =E4+E8 -> 86799137 | F9: =F4+F8 -> 86919721 | G9: =G4+G8 -> 85535277 | H9: =H4+H8 -> 80433401 | I9: =I4+I8 -> 82719754 | J9: =J4+J8 -> 76924778 | ... N9: =N4+N8 -> 84507816 | O9: =SUM(C9:N9) -> 1.0463938e+09 | P9: =SUM(C9:H9) -> 5.3351935e+08 | Q9: =SUM(I9:N9) -> 5.1287444e+08 | R9: =SUM(C9:E9) -> 2.8063095e+08 | S9: =SUM(F9:H9) -> 2.528884e+08 | T9: =SUM(I9:K9) -> 2.4478307e+08 | U9: =SUM(L9:N9) -> 2.6809137e+08 | X9: 存量整体 | Y9: =Y4+Y8 -> 26183689 | Z9: =Z4+Z8 -> 18907276 | AA9: =AA4+AA8 -> 21181039 | AB9: =AB4+AB8 -> 20419943 | AC9: =AC4+AC8 -> 19028404 | AD9: =AD4+AD8 -> 19346421 | AE9: =AE4+AE8 -> 18855792 | AF9: =AF4+AF8 -> 17898504 | ... AJ9: =AJ4+AJ8 -> 22971148 | AK9: =SUM(Y9:AJ9) -> 2.4251431e+08 | AL9: =SUM(Y9:AD9) -> 1.2506677e+08 | AM9: =SUM(AE9:AJ9) -> 1.1744754e+08 | AN9: =SUM(Y9:AA9) -> 66272004 | AO9: =SUM(AB9:AD9) -> 58794768 | AP9: =SUM(AE9:AG9) -> 54916349 | AQ9: =SUM(AH9:AJ9) -> 62531187 | AS9: 1.12 | AT9: 存量整体 | AU9: =Y9*$AS9/C9 -> 0.26605964 | AV9: =Z9*$AS9/D9 -> 0.2532747 | AW9: =AA9*$AS9/E9 -> 0.27330645 | AX9: =AB9*$AS9/F9 -> 0.26312022 | AY9: =AC9*$AS9/G9 -> 0.24915816 | AZ9: =AD9*$AS9/H9 -> 0.26939047 | BA9: =AE9*$AS9/I9 -> 0.25530162 | BB9: =AF9*$AS9/J9 -> 0.26059646 | ... BM9: =AQ9*$AS9/U9 -> 0.2612353
A10: 26年口径 | B10: 仅电视端及APP业务 （含自营业务） | C10: =C4-C11-C7 -> 93066095 | D10: =D4-D11-D7 -> 68875967 | E10: =E4-E11-E7 -> 72664094 | F10: =F4-F11-F7 -> 71559512 | G10: =G4-G11-G7 -> 73159842 | H10: =H4-H11-H7 -> 66716190 | I10: =I4-I11-I7 -> 67862810 | J10: =J4-J11-J7 -> 62344970 | ... N10: =N4-N11-N7 -> 67923619 | O10: =SUM(C10:N10) -> 8.4592553e+08 | P10: =SUM(C10:H10) -> 4.460417e+08 | Q10: =SUM(I10:N10) -> 3.9988383e+08 | R10: =SUM(C10:E10) -> 2.3460616e+08 | S10: =SUM(F10:H10) -> 2.1143554e+08 | T10: =SUM(I10:K10) -> 1.9582838e+08 | U10: =SUM(L10:N10) -> 2.0405545e+08 | W10: 26年口径 | X10: 仅电视端及APP业务 （含自营业务） | Y10: =Y4-Y11-Y7 -> 23060801 | Z10: =Z4-Z11-Z7 -> 16413199 | AA10: =AA4-AA11-AA7 -> 18356698 | AB10: =AB4-AB11-AB7 -> 17233521 | AC10: =AC4-AC11-AC7 -> 16710974 | AD10: =AD4-AD11-AD7 -> 16492398 | AE10: =AE4-AE11-AE7 -> 16251029 | AF10: =AF4-AF11-AF7 -> 15186116 | ... AJ10: =AJ4-AJ11-AJ7 -> 19991942 | AK10: =SUM(Y10:AJ10) -> 2.0789275e+08 | AL10: =SUM(Y10:AD10) -> 1.0826759e+08 | AM10: =SUM(AE10:AJ10) -> 99625158 | AN10: =SUM(Y10:AA10) -> 57830698 | AO10: =SUM(AB10:AD10) -> 50436894 | AP10: =SUM(AE10:AG10) -> 46985256 | AQ10: =SUM(AH10:AJ10) -> 52639903 | AS10: 1.12 | AT10: 仅电视端及APP业务 （含自营业务） | AU10: =Y10*$AS10/C10 -> 0.27752424 | AV10: =Z10*$AS10/D10 -> 0.26689692 | AW10: =AA10*$AS10/E10 -> 0.28293893 | AX10: =AB10*$AS10/F10 -> 0.26972716 | AY10: =AC10*$AS10/G10 -> 0.25582738 | AZ10: =AD10*$AS10/H10 -> 0.27686662 | BA10: =AE10*$AS10/I10 -> 0.26820512 | BB10: =AF10*$AS10/J10 -> 0.2728119 | ... BM10: =AQ10*$AS10/U10 -> 0.28892485
A11: 26年口径 | B11: 数据库营销 | C11: =C5 -> 11875837 | D11: =D5 -> 9505244.6 | E11: =E5 -> 8448582.2 | F11: =F5 -> 10411125 | G11: =G5 -> 7751860 | H11: =H5 -> 8753480.6 | I11: =I5 -> 9067021.2 | J11: =J5 -> 7495744.8 | ... N11: =N5 -> 8632591.5 | O11: =SUM(C11:N11) -> 1.3075104e+08 | P11: =SUM(C11:H11) -> 56746130 | Q11: =SUM(I11:N11) -> 74004912 | R11: =SUM(C11:E11) -> 29829664 | S11: =SUM(F11:H11) -> 26916466 | T11: =SUM(I11:K11) -> 30562754 | U11: =SUM(L11:N11) -> 43442158 | W11: 26年口径 | X11: 数据库营销 | Y11: =Y5 -> 2549751.2 | Z11: =Z5 -> 1880081.8 | AA11: =AA5 -> 2130051.2 | AB11: =AB5 -> 2615080.4 | AC11: =AC5 -> 1752152.4 | AD11: =AD5 -> 2225886 | AE11: =AE5 -> 1876419.1 | AF11: =AF5 -> 1908652.7 | ... AJ11: =AJ5 -> 2180017.1 | AK11: =SUM(Y11:AJ11) -> 26566162 | AL11: =SUM(Y11:AD11) -> 13153003 | AM11: =SUM(AE11:AJ11) -> 13413159 | AN11: =SUM(Y11:AA11) -> 6559884.2 | AO11: =SUM(AB11:AD11) -> 6593118.8 | AP11: =SUM(AE11:AG11) -> 5793129.4 | AQ11: =SUM(AH11:AJ11) -> 7620029.7 | AS11: 1.12 | AT11: 数据库营销 | AU11: =Y11*$AS11/C11 -> 0.24046484 | AV11: =Z11*$AS11/D11 -> 0.22152945 | AW11: =AA11*$AS11/E11 -> 0.28237369 | AX11: =AB11*$AS11/F11 -> 0.28132311 | AY11: =AC11*$AS11/G11 -> 0.25315353 | AZ11: =AD11*$AS11/H11 -> 0.28480012 | BA11: =AE11*$AS11/I11 -> 0.23178388 | BB11: =AF11*$AS11/J11 -> 0.28518727 | ... BM11: =AQ11*$AS11/U11 -> 0.19645509
A12: 26年口径 | B12: 私域 | C12: =C6 -> 5280469.7 | D12: =D6 -> 5228202.1 | E12: =E6 -> 5686460.7 | F12: =F6 -> 4949084.3 | G12: =G6 -> 4623575.5 | H12: =H6 -> 4963729.5 | I12: =I6 -> 5789922.8 | J12: =J6 -> 7084063.3 | ... N12: =N6 -> 7951606.3 | O12: =SUM(C12:N12) -> 69717216 | P12: =SUM(C12:H12) -> 30731522 | Q12: =SUM(I12:N12) -> 38985694 | R12: =SUM(C12:E12) -> 16195133 | S12: =SUM(F12:H12) -> 14536389 | T12: =SUM(I12:K12) -> 18391938 | U12: =SUM(L12:N12) -> 20593756 | W12: 26年口径 | X12: 私域 | Y12: =Y6 -> 573137.28 | Z12: =Z6 -> 613994.73 | AA12: =AA6 -> 694290.26 | AB12: =AB6 -> 571341.18 | AC12: =AC6 -> 565277.8 | AD12: =AD6 -> 628136.96 | AE12: =AE6 -> 728343.65 | AF12: =AF6 -> 803735.23 | ... AJ12: =AJ6 -> 799188.63 | AK12: =SUM(Y12:AJ12) -> 8055396.6 | AL12: =SUM(Y12:AD12) -> 3646178.2 | AM12: =SUM(AE12:AJ12) -> 4409218.3 | AN12: =SUM(Y12:AA12) -> 1881422.3 | AO12: =SUM(AB12:AD12) -> 1764755.9 | AP12: =SUM(AE12:AG12) -> 2137963.9 | AQ12: =SUM(AH12:AJ12) -> 2271254.4 | AS12: 1.12 | AT12: 私域 | AU12: =Y12*$AS12/C12 -> 0.12156376 | AV12: =Z12*$AS12/D12 -> 0.13153166 | AW12: =AA12*$AS12/E12 -> 0.13674676 | AX12: =AB12*$AS12/F12 -> 0.12929707 | AY12: =AC12*$AS12/G12 -> 0.13693107 | AZ12: =AD12*$AS12/H12 -> 0.14173081 | BA12: =AE12*$AS12/I12 -> 0.14089046 | BB12: =AF12*$AS12/J12 -> 0.12707163 | ... BM12: =AQ12*$AS12/U12 -> 0.12352312
B13: check | C13: =SUM(C10:C12)=C9 -> TRUE | D13: =SUM(D10:D12)=D9 -> TRUE | E13: =SUM(E10:E12)=E9 -> FALSE | F13: =SUM(F10:F12)=F9 -> TRUE | G13: =SUM(G10:G12)=G9 -> TRUE | H13: =SUM(H10:H12)=H9 -> TRUE | I13: =SUM(I10:I12)=I9 -> TRUE | J13: =SUM(J10:J12)=J9 -> TRUE | ... U13: =SUM(U10:U12)=U9 -> TRUE | X13: check | Y13: =SUM(Y10:Y12)=Y9 -> TRUE | Z13: =SUM(Z10:Z12)=Z9 -> TRUE | AA13: =SUM(AA10:AA12)=AA9 -> TRUE | AB13: =SUM(AB10:AB12)=AB9 -> TRUE | AC13: =SUM(AC10:AC12)=AC9 -> TRUE | AD13: =SUM(AD10:AD12)=AD9 -> TRUE | AE13: =SUM(AE10:AE12)=AE9 -> TRUE | AF13: =SUM(AF10:AF12)=AF9 -> TRUE | ... AQ13: =SUM(AQ10:AQ12)=AQ9 -> TRUE
X14: 电视及APP-电视商品（含自营业务） | Y14: 23141348 | Z14: 16740906 | AA14: 18651063 | AB14: 18127100 | AC14: 17050642 | AD14: 17242451 | AE14: 17060422 | AF14: 16235447 | AG14: 16150202 | AH14: 15755887 | AI14: 19418912 | AJ14: 18386453 | AK14: =SUM(Y14:AJ14) -> 2.1396083e+08 | AL14: =SUM(Y14:AD14) -> 1.1095351e+08 | AM14: =SUM(AE14:AJ14) -> 1.0300732e+08 | AN14: =SUM(Y14:AA14) -> 58533318 | AO14: =SUM(AB14:AD14) -> 52420192 | AP14: =SUM(AE14:AG14) -> 49446071 | AQ14: =SUM(AH14:AJ14) -> 53561252
X15: 电视及APP-电商商品 | Y15: 2769275.6 | Z15: 1936495.7 | AA15: 2247014.9 | AB15: 2050038.4 | AC15: 1739691.9 | AD15: 1876888.2 | AE15: 1558920 | AF15: 1430264.5 | AG15: 1787154.4 | AH15: 1736339.4 | AI15: 2199376.9 | AJ15: 4376535.8 | AK15: =SUM(Y15:AJ15) -> 25707996 | AL15: =SUM(Y15:AD15) -> 12619405 | AM15: =SUM(AE15:AJ15) -> 13088591 | AN15: =SUM(Y15:AA15) -> 6952786.2 | AO15: =SUM(AB15:AD15) -> 5666618.5 | AP15: =SUM(AE15:AG15) -> 4776338.9 | AQ15: =SUM(AH15:AJ15) -> 8312252.1
X16: 电视端及APP业务
X17: 自营旅游
W20: 趋势环比 | X20: 利润金额环比 | Y20: 1月 | Z20: 2月 | AA20: 3月 | AB20: 4月 | AC20: 5月 | AD20: 6月 | AE20: 7月 | AF20: 8月 | AG20: 9月 | AH20: 10月 | AI20: 11月 | AJ20: 12月
W21: 30641423 | X21: 存量整体 | Y21: -0.14548063 | Z21: =Z9/Y9-1 -> -0.27789871 | AA21: =AA9/Z9-1 -> 0.12025864 | AB21: =AB9/AA9-1 -> -0.035932897 | AC21: =AC9/AB9-1 -> -0.068146074 | AD21: =AD9/AC9-1 -> 0.016712761 | AE21: =AE9/AD9-1 -> -0.025360201 | AF21: =AF9/AE9-1 -> -0.05076891 | AG21: =AG9/AF9-1 -> 0.014724625 | ... AJ21: =AJ9/AI9-1 -> 0.051590449
W22: =W21-W24-W23 -> 27129328 | X22: 仅电视端及APP业务 （含自营业务） | Y22: -0.14996784 | Z22: =Z10/Y10-1 -> -0.28826413 | AA22: =AA10/Z10-1 -> 0.1184107 | AB22: =AB10/AA10-1 -> -0.061186181 | AC22: =AC10/AB10-1 -> -0.030321578 | AD22: =AD10/AC10-1 -> -0.013079764 | AE22: =AE10/AD10-1 -> -0.014635162 | AF22: =AF10/AE10-1 -> -0.065528968 | AG22: =AG10/AF10-1 -> 0.023837171 | ... AJ22: =AJ10/AI10-1 -> 0.13144448
W23: 2796841.2 | X23: 数据库营销 | Y23: -0.088346096 | Z23: =Z11/Y11-1 -> -0.26264108 | AA23: =AA11/Z11-1 -> 0.13295666 | AB23: =AB11/AA11-1 -> 0.22770777 | AC23: =AC11/AB11-1 -> -0.32998144 | AD23: =AD11/AC11-1 -> 0.27037237 | AE23: =AE11/AD11-1 -> -0.15700126 | AF23: =AF11/AE11-1 -> 0.017178252 | AG23: =AG11/AF11-1 -> 0.052081188 | ... AJ23: =AJ11/AI11-1 -> -0.37619656
W24: 715254.05 | X24: 私域 | Y24: -0.19869411 | Z24: =Z12/Y12-1 -> 0.071287371 | AA24: =AA12/Z12-1 -> 0.1307756 | AB24: =AB12/AA12-1 -> -0.17708599 | AC24: =AC12/AB12-1 -> -0.010612538 | AD24: =AD12/AC12-1 -> 0.11120048 | AE24: =AE12/AD12-1 -> 0.15953 | AF24: =AF12/AE12-1 -> 0.103511 | AG24: =AG12/AF12-1 -> -0.24616339 | ... AJ24: =AJ12/AI12-1 -> 0.17513797
B28: 销售额占比 | C28: 1月 | D28: 2月 | E28: 3月 | F28: 4月 | G28: 5月 | H28: 6月 | I28: 7月 | J28: 8月 | K28: 9月 | L28: 10月 | M28: 11月 | N28: 12月 | O28: 合计 | P28: H1 | Q28: H2 | R28: Q1 | S28: Q2 | T28: Q3 | U28: Q4 | X28: 利润额占比 | Y28: 1月 | Z28: 2月 | AA28: 3月 | AB28: 4月 | AC28: 5月 | AD28: 6月 | AE28: 7月 | AF28: 8月 | AG28: 9月 | AH28: 10月 | AI28: 11月 | AJ28: 12月 | AK28: 合计 | AL28: H1 | AM28: H2 | AN28: Q1 | AO28: Q2 | AP28: Q3 | AQ28: Q4
B29: 存量整体 | C29: =C9/$O9 -> 0.10533549 | D29: =D9/$O9 -> 0.079902436 | E29: =E9/$O9 -> 0.082950738 | F29: =F9/$O9 -> 0.083065975 | G29: =G9/$O9 -> 0.081742914 | H29: =H9/$O9 -> 0.076867238 | I29: =I9/$O9 -> 0.079052222 | J29: =J9/$O9 -> 0.073514177 | ... U29: =U9/$O9 -> 0.25620504 | X29: 存量整体 | Y29: =Y9/$AK9 -> 0.10796761 | Z29: =Z9/$AK9 -> 0.077963547 | AA29: =AA9/$AK9 -> 0.087339338 | AB29: =AB9/$AK9 -> 0.084200982 | AC29: =AC9/$AK9 -> 0.078463016 | AD29: =AD9/$AK9 -> 0.07977435 | AE29: =AE9/$AK9 -> 0.077751256 | AF29: =AF9/$AK9 -> 0.07380391 | ... AQ29: =AQ9/$AK9 -> 0.25784535
B30: 仅电视端及APP业务 （含自营业务） | C30: =C10/$O10 -> 0.11001689 | D30: =D10/$O10 -> 0.081420839 | E30: =E10/$O10 -> 0.085898925 | F30: =F10/$O10 -> 0.084593157 | G30: =G10/$O10 -> 0.086484967 | H30: =H10/$O10 -> 0.078867687 | I30: =I10/$O10 -> 0.080223149 | J30: =J10/$O10 -> 0.073700306 | ... U30: =U10/$O10 -> 0.24122153 | X30: 仅电视端及APP业务 （含自营业务） | Y30: =Y10/$AK10 -> 0.11092643 | Z30: =Z10/$AK10 -> 0.078950321 | AA30: =AA10/$AK10 -> 0.088298883 | AB30: =AB10/$AK10 -> 0.082896212 | AC30: =AC10/$AK10 -> 0.080382668 | AD30: =AD10/$AK10 -> 0.079331282 | AE30: =AE10/$AK10 -> 0.078170255 | AF30: =AF10/$AK10 -> 0.073047839 | ... AQ30: =AQ10/$AK10 -> 0.25320702
B31: 数据库营销 | C31: =C11/$O11 -> 0.090827861 | D31: =D11/$O11 -> 0.072697276 | E31: =E11/$O11 -> 0.064615793 | F31: =F11/$O11 -> 0.079625561 | G31: =G11/$O11 -> 0.059287176 | H31: =H11/$O11 -> 0.066947693 | I31: =I11/$O11 -> 0.06934569 | J31: =J11/$O11 -> 0.057328375 | ... U31: =U11/$O11 -> 0.33225095 | X31: 数据库营销 | Y31: =Y11/$AK11 -> 0.095977401 | Z31: =Z11/$AK11 -> 0.070769793 | AA31: =AA11/$AK11 -> 0.080179109 | AB31: =AB11/$AK11 -> 0.098436514 | AC31: =AC11/$AK11 -> 0.065954292 | AD31: =AD11/$AK11 -> 0.08378651 | AE31: =AE11/$AK11 -> 0.070631922 | AF31: =AF11/$AK11 -> 0.071845255 | ... AQ31: =AQ11/$AK11 -> 0.28683216
B32: 私域 | C32: =C12/$O12 -> 0.075741258 | D32: =D12/$O12 -> 0.07499155 | E32: =E12/$O12 -> 0.081564656 | F32: =F12/$O12 -> 0.070987979 | G32: =G12/$O12 -> 0.066318992 | H32: =H12/$O12 -> 0.071198045 | I32: =I12/$O12 -> 0.083048681 | J32: =J12/$O12 -> 0.10161139 | ... U32: =U12/$O12 -> 0.29538982 | X32: 私域 | Y32: =Y12/$AK12 -> 0.07114948 | Z32: =Z12/$AK12 -> 0.07622154 | AA32: =AA12/$AK12 -> 0.086189458 | AB32: =AB12/$AK12 -> 0.070926512 | AC32: =AC12/$AK12 -> 0.070173802 | AD32: =AD12/$AK12 -> 0.077977162 | AE32: =AE12/$AK12 -> 0.090416858 | AF32: =AF12/$AK12 -> 0.099775998 | ... AQ32: =AQ12/$AK12 -> 0.28195439
X33: 电视及APP-电视商品（含自营业务） | Y33: =Y14/$AK$14 -> 0.10815694 | Z33: =Z14/$AK$14 -> 0.078242855 | AA33: =AA14/$AK$14 -> 0.087170456 | AB33: =AB14/$AK$14 -> 0.08472158 | AC33: =AC14/$AK$14 -> 0.07969048 | AD33: =AD14/$AK$14 -> 0.08058695 | AE33: =AE14/$AK$14 -> 0.079736191 | AF33: =AF14/$AK$14 -> 0.075880463 | ... AQ33: =AQ14/$AK$14 -> 0.25033204
X34: 电视及APP-电商商品 | Y34: =Y15/$AK$15 -> 0.1077204 | Z34: =Z15/$AK$15 -> 0.075326592 | AA34: =AA15/$AK$15 -> 0.087405293 | AB34: =AB15/$AK$15 -> 0.079743222 | AC34: =AC15/$AK$15 -> 0.067671238 | AD34: =AD15/$AK$15 -> 0.073007955 | AE34: =AE15/$AK$15 -> 0.0606395 | AF34: =AF15/$AK$15 -> 0.055635006 | ... AQ34: =AQ15/$AK$15 -> 0.32333334
B38: 天数 | C38: 31 | D38: 28 | E38: 31 | F38: 30 | G38: 31 | H38: 30 | I38: 31 | J38: 31 | K38: 30 | L38: 31 | M38: 30 | N38: 31 | O38: =SUM(C38:N38) -> 365 | P38: =SUM(C38:H38) -> 181 | Q38: =SUM(I38:N38) -> 184 | R38: =SUM(C38:E38) -> 90 | S38: =SUM(F38:H38) -> 91 | T38: =SUM(I38:K38) -> 92 | U38: =SUM(L38:N38) -> 92 | X38: 天数 | Y38: 31 | Z38: 28 | AA38: 31 | AB38: 30 | AC38: 31 | AD38: 30 | AE38: 31 | AF38: 31 | AG38: 30 | AH38: 31 | AI38: 30 | AJ38: 31 | AK38: =SUM(Y38:AJ38) -> 365 | AL38: =SUM(Y38:AD38) -> 181 | AM38: =SUM(AE38:AJ38) -> 184 | AN38: =SUM(Y38:AA38) -> 90 | AO38: =SUM(AB38:AD38) -> 91 | AP38: =SUM(AE38:AG38) -> 92 | AQ38: =SUM(AH38:AJ38) -> 92
B39: 日均销售额 | C39: 1月 | D39: 2月 | E39: 3月 | F39: 4月 | G39: 5月 | H39: 6月 | I39: 7月 | J39: 8月 | K39: 9月 | L39: 10月 | M39: 11月 | N39: 12月 | O39: 合计 | P39: H1 | Q39: H2 | R39: Q1 | S39: Q2 | T39: Q3 | U39: Q4 | X39: 日均利润额 | Y39: 1月 | Z39: 2月 | AA39: 3月 | AB39: 4月 | AC39: 5月 | AD39: 6月 | AE39: 7月 | AF39: 8月 | AG39: 9月 | AH39: 10月 | AI39: 11月 | AJ39: 12月 | AK39: 合计 | AL39: H1 | AM39: H2 | AN39: Q1 | AO39: Q2 | AP39: Q3 | AQ39: Q4
B40: 存量整体 | C40: =C9/C$38 -> 3555561.4 | D40: =D9/D$38 -> 2986050.5 | E40: =E9/E$38 -> 2799972.2 | F40: =F9/F$38 -> 2897324 | G40: =G9/G$38 -> 2759202.5 | H40: =H9/H$38 -> 2681113.4 | I40: =I9/I$38 -> 2668379.2 | J40: =J9/J$38 -> 2481444.5 | ... U40: =U9/U$38 -> 2914036.6 | W40: =30641422.9222642/31 -> 988433 | X40: 存量整体 | Y40: =Y9/Y$38 -> 844635.14 | Z40: =Z9/Z$38 -> 675259.85 | AA40: =AA9/AA$38 -> 683259.33 | AB40: =AB9/AB$38 -> 680664.77 | AC40: =AC9/AC$38 -> 613819.49 | AD40: =AD9/AD$38 -> 644880.71 | AE40: =AE9/AE$38 -> 608251.36 | AF40: =AF9/AF$38 -> 577371.1 | ... AQ40: =AQ9/AQ$38 -> 679686.81
B41: 仅电视端及APP业务 （含自营业务） | C41: =C10/C$38 -> 3002132.1 | D41: =D10/D$38 -> 2459856 | E41: =E10/E$38 -> 2344003 | F41: =F10/F$38 -> 2385317.1 | G41: =G10/G$38 -> 2359994.9 | H41: =H10/H$38 -> 2223873 | I41: =I10/I$38 -> 2189122.9 | J41: =J10/J$38 -> 2011128.1 | ... U41: =U10/U$38 -> 2217994 | W41: =W22/31 -> 875139.6 | X41: 仅电视端及APP业务 （含自营业务） | Y41: =Y10/Y$38 -> 743896.8 | Z41: =Z10/Z$38 -> 586185.69 | AA41: =AA10/AA$38 -> 592151.54 | AB41: =AB10/AB$38 -> 574450.71 | AC41: =AC10/AC$38 -> 539063.67 | AD41: =AD10/AD$38 -> 549746.61 | AE41: =AE10/AE$38 -> 524226.75 | AF41: =AF10/AF$38 -> 489874.71 | ... AQ41: =AQ10/AQ$38 -> 572172.85
B42: 数据库营销 | C42: =C11/C$38 -> 383091.53 | D42: =D11/D$38 -> 339473.02 | E42: =E11/E$38 -> 272534.91 | F42: =F11/F$38 -> 347037.5 | G42: =G11/G$38 -> 250060 | H42: =H11/H$38 -> 291782.69 | I42: =I11/I$38 -> 292484.55 | J42: =J11/J$38 -> 241798.22 | ... U42: =U11/U$38 -> 472197.37 | W42: =2796841.2/31 -> 90220.684 | X42: 数据库营销 | Y42: =Y11/Y$38 -> 82250.039 | Z42: =Z11/Z$38 -> 67145.779 | AA42: =AA11/AA$38 -> 68711.329 | AB42: =AB11/AB$38 -> 87169.347 | AC42: =AC11/AC$38 -> 56521.045 | AD42: =AD11/AD$38 -> 74196.2 | AE42: =AE11/AE$38 -> 60529.648 | AF42: =AF11/AF$38 -> 61569.442 | ... AQ42: =AQ11/AQ$38 -> 82826.41
B43: 私域 | C43: =C12/C$38 -> 170337.73 | D43: =D12/D$38 -> 186721.51 | E43: =E12/E$38 -> 183434.22 | F43: =F12/F$38 -> 164969.48 | G43: =G12/G$38 -> 149147.6 | H43: =H12/H$38 -> 165457.65 | I43: =I12/I$38 -> 186771.7 | J43: =J12/J$38 -> 228518.17 | ... U43: =U12/U$38 -> 223845.17 | W43: =715254.05/31 -> 23072.711 | X43: 私域 | Y43: =Y12/Y$38 -> 18488.299 | Z43: =Z12/Z$38 -> 21928.383 | AA43: =AA12/AA$38 -> 22396.46 | AB43: =AB12/AB$38 -> 19044.706 | AC43: =AC12/AC$38 -> 18234.768 | AD43: =AD12/AD$38 -> 20937.899 | AE43: =AE12/AE$38 -> 23494.956 | AF43: =AF12/AF$38 -> 25926.943 | ... AQ43: =AQ12/AQ$38 -> 24687.548
X44: 电视及APP-电视商品（含自营业务） | Y44: =Y14/Y$38 -> 746495.11 | Z44: =Z14/Z$38 -> 597889.52 | AA44: =AA14/AA$38 -> 601647.21 | AB44: =AB14/AB$38 -> 604236.66 | AC44: =AC14/AC$38 -> 550020.7 | AD44: =AD14/AD$38 -> 574748.37 | AE44: =AE14/AE$38 -> 550336.19 | AF44: =AF14/AF$38 -> 523724.1 | ... AQ44: =AQ14/AQ$38 -> 582187.52
X45: 电视及APP-电商商品 | Y45: =Y15/Y$38 -> 89331.471 | Z45: =Z15/Z$38 -> 69160.561 | AA45: =AA15/AA$38 -> 72484.352 | AB45: =AB15/AB$38 -> 68334.613 | AC45: =AC15/AC$38 -> 56119.094 | AD45: =AD15/AD$38 -> 62562.94 | AE45: =AE15/AE$38 -> 50287.742 | AF45: =AF15/AF$38 -> 46137.565 | ... AQ45: =AQ15/AQ$38 -> 90350.566
W49: 趋势环比 | X49: 日均利润环比 | Y49: 1月 | Z49: 2月 | AA49: 3月 | AB49: 4月 | AC49: 5月 | AD49: 6月 | AE49: 7月 | AF49: 8月 | AG49: 9月 | AH49: 10月 | AI49: 11月 | AJ49: 12月
X50: 存量整体 | Y50: -0.14548063 | Z50: =Z40/Y40-1 -> -0.20053072 | AA50: =AA40/Z40-1 -> 0.011846516 | AB50: =AB40/AA40-1 -> -0.0037973269 | AC50: =AC40/AB40-1 -> -0.098205878 | AD50: =AD40/AC40-1 -> 0.050603186 | AE50: =AE40/AD40-1 -> -0.056800195 | AF50: =AF40/AE40-1 -> -0.05076891 | AG50: =AG40/AF40-1 -> 0.048548779 | ... AJ50: =AJ40/AI40-1 -> 0.017668176
X51: 仅电视端及APP业务 （含自营业务） | Y51: -0.14996784 | Z51: =Z41/Y41-1 -> -0.21200671 | AA51: =AA41/Z41-1 -> 0.010177405 | AB51: =AB41/AA41-1 -> -0.029892387 | AC51: =AC41/AB41-1 -> -0.061601527 | AD51: =AD41/AC41-1 -> 0.019817577 | AE51: =AE41/AD41-1 -> -0.046421125 | AF51: =AF41/AE41-1 -> -0.065528968 | AG51: =AG41/AF41-1 -> 0.057965077 | ... AJ51: =AJ41/AI41-1 -> 0.094946276
X52: 数据库营销 | Y52: -0.088346096 | Z52: =Z42/Y42-1 -> -0.18363833 | AA52: =AA42/Z42-1 -> 0.023315695 | AB52: =AB42/AA42-1 -> 0.26863136 | AC52: =AC42/AB42-1 -> -0.35159494 | AD52: =AD42/AC42-1 -> 0.31271812 | AE52: =AE42/AD42-1 -> -0.18419476 | AF52: =AF42/AE42-1 -> 0.017178252 | AG52: =AG42/AF42-1 -> 0.087150561 | ... AJ52: =AJ42/AI42-1 -> -0.39631925
X53: 私域 | Y53: -0.19869411 | Z53: =Z43/Y43-1 -> 0.18606816 | AA53: =AA43/Z43-1 -> 0.021345704 | AB53: =AB43/AA43-1 -> -0.14965553 | AC53: =AC43/AB43-1 -> -0.042528263 | AD53: =AD43/AC43-1 -> 0.14824049 | AE53: =AE43/AD43-1 -> 0.12212581 | AF53: =AF43/AE43-1 -> 0.103511 | AG53: =AG43/AF43-1 -> -0.2210355 | ... AJ53: =AJ43/AI43-1 -> 0.13723029
AL56: 4343821.7 | AM56: =AK62-AL56 -> 7656178.3 | AN56: =AL56/$AK$62 -> 0.36198514 | AO56: =AM56/$AK$62 -> 0.63801486
B57: 26年销售额目标 | X57: 26年销售利润目标 | Z57: 23226681 | AT57: 26年毛利率目标
B58: 销售金额 | C58: 1月 | D58: 2月 | E58: 3月 | F58: 4月 | G58: 5月 | H58: 6月 | I58: 7月 | J58: 8月 | K58: 9月 | L58: 10月 | M58: 11月 | N58: 12月 | O58: 合计 | P58: H1 | Q58: H2 | R58: Q1 | S58: Q2 | T58: Q3 | U58: Q4 | X58: 利润金额 | Y58: 1月 | Z58: 2月 | AA58: 3月 | AB58: 4月 | AC58: 5月 | AD58: 6月 | AE58: 7月 | AF58: 8月 | AG58: 9月 | AH58: 10月 | AI58: 11月 | AJ58: 12月 | AK58: 合计 | AL58: H1 | AM58: H2 | AN58: Q1 | AO58: Q2 | AP58: Q3 | AQ58: Q4 | AT58: 手动毛利率 | AU58: 1月 | AV58: 2月 | AW58: 3月 | AX58: 4月 | AY58: 5月 | AZ58: 6月 | BA58: 7月 | BB58: 8月 | BC58: 9月 | BD58: 10月 | BE58: 11月 | BF58: 12月 | BG58: 合计 | BH58: H1 | BI58: H2 | BJ58: Q1 | BK58: Q2 | BL58: Q3 | BM58: Q4
B59: 存量整体 | C59: =C60+C61+C62 -> 99061446 | D59: =D60+D61+D62 -> 71731576 | E59: =E60+E61+E62 -> 79220420 | F59: =F60+F61+F62 -> 81951908 | G59: =G60+G61+G62 -> 78847804 | H59: =H60+H61+H62 -> 75920356 | I59: =I60+I61+I62 -> 77009398 | J59: =J60+J61+J62 -> 73330395 | ... O59: =O60+O61+O62 -> 9.517968e+08 | P59: =SUM(C59:H59) -> 4.8673351e+08 | Q59: =SUM(I59:N59) -> 4.6506329e+08 | R59: =SUM(C59:E59) -> 2.5001344e+08 | S59: =SUM(F59:H59) -> 2.3672007e+08 | T59: =SUM(I59:K59) -> 2.2527788e+08 | U59: =SUM(L59:N59) -> 2.3978541e+08 | X59: 存量整体(不含其他收入) | Y59: =Y60+Y61+Y62 -> 23226681 | Z59: =Z60+Z61+Z62 -> 16184643 | AA59: =AA60+AA61+AA62 -> 18883028 | AB59: =AB60+AB61+AB62 -> 18605316 | AC59: =AC60+AC61+AC62 -> 17245454 | AD59: =AD60+AD61+AD62 -> 17507669 | AE59: =AE60+AE61+AE62 -> 17209969 | AF59: =AF60+AF61+AF62 -> 16413118 | ... AK59: =AK60+AK61+AK62 -> 2.1760703e+08 | AL59: =SUM(Y59:AD59) -> 1.1165279e+08 | AM59: =SUM(AE59:AJ59) -> 1.0595424e+08 | AN59: =SUM(Y59:AA59) -> 58294352 | AO59: =SUM(AB59:AD59) -> 53358439 | AP59: =SUM(AE59:AG59) -> 50331686 | AQ59: =SUM(AH59:AJ59) -> 55622554 | AR59: 4.求和计算存量月度目标 | AS59: 1.12 | AT59: 存量整体 | AU59: =Y59*$AS59/C59 -> 0.2626035 | AV59: =Z59*$AS59/D59 -> 0.25270323 | AW59: =AA59*$AS59/E59 -> 0.26696388 | AX59: =AB59*$AS59/F59 -> 0.25427051 | AY59: =AC59*$AS59/G59 -> 0.24496445 | AZ59: =AD59*$AS59/H59 -> 0.25827842 | BA59: =AE59*$AS59/I59 -> 0.25029627 | BB59: =AF59*$AS59/J59 -> 0.25068312 | ... BM59: =AQ59*$AS59/U59 -> 0.25980422
A60: 25年单月最高日均基数 | B60: 仅电视端及APP业务 （含自营业务） | C60: =$O$60*C71 -> 78968729 | D60: =$O$60*D71 -> 58442847 | E60: =$O$60*E71 -> 61657160 | F60: =$O$60*F71 -> 60719897 | G60: =$O$60*G71 -> 62077814 | H60: =$O$60*H71 -> 56610227 | I60: =$O$60*I71 -> 57583160 | J60: =$O$60*J71 -> 52901146 | ... N60: =$O$60*N71 -> 57929538 | O60: 7.1808211e+08 | P60: =SUM(C60:H60) -> 3.7847667e+08 | Q60: =SUM(I60:N60) -> 3.3960544e+08 | R60: =SUM(C60:E60) -> 1.9906874e+08 | S60: =SUM(F60:H60) -> 1.7940794e+08 | T60: =SUM(I60:K60) -> 1.661649e+08 | U60: =SUM(L60:N60) -> 1.7344054e+08 | W60: 25年单月最高日均基数 | X60: 仅电视端及APP业务 （含自营业务） | Y60: 19601681 | Z60: 13951219 | AA60: 15859315 | AB60: 14891718 | AC60: 14441552 | AD60: 14253253 | AE60: 14045318 | AF60: 13127913 | AG60: 13439765 | AH60: 12949109 | AI60: 15267218 | AJ60: 16278970 | AK60: 1.7810703e+08 | AL60: =SUM(Y60:AD60) -> 92998738 | AM60: =SUM(AE60:AJ60) -> 85108292 | AN60: =SUM(Y60:AA60) -> 49412216 | AO60: =SUM(AB60:AD60) -> 43586523 | AP60: =SUM(AE60:AG60) -> 40612995 | AQ60: =SUM(AH60:AJ60) -> 44495298 | AR60: 1.考虑历史数据取值的问题，年度总目标*2025年各月度占比 | AS60: 1.12 | AT60: 仅电视端及APP业务 （含自营业务） | AU60: =Y60*$AS60/C60 -> 0.27800729 | AV60: =Z60*$AS60/D60 -> 0.26736147 | AW60: =AA60*$AS60/E60 -> 0.28808387 | AX60: =AB60*$AS60/F60 -> 0.27468301 | AY60: =AC60*$AS60/G60 -> 0.26055264 | AZ60: =AD60*$AS60/H60 -> 0.28199221 | BA60: =AE60*$AS60/I60 -> 0.27318327 | BB60: =AF60*$AS60/J60 -> 0.27793845 | ... BM60: =AQ60*$AS60/U60 -> 0.28733036
A61: =MAX(C42:N42) -> 581582.58 | B61: 数据库营销 | C61: =Y61*1.12/$BG$61 -> 13874286 | D61: =Z61*1.12/$BG$61 -> 7789072.9 | E61: =AA61*1.12/$BG$61 -> 10709975 | F61: =AB61*1.12/$BG$61 -> 13630878 | G61: =AC61*1.12/$BG$61 -> 9249524.1 | H61: =AD61*1.12/$BG$61 -> 10953384 | I61: =AE61*1.12/$BG$61 -> 9736341.1 | J61: =AF61*1.12/$BG$61 -> 9736341.1 | ... N61: =AJ61*1.12/$BG$61 -> 11683609 | O61: 1.3387469e+08 | P61: =SUM(C61:H61) -> 66207120 | Q61: =SUM(I61:N61) -> 67667571 | R61: =SUM(C61:E61) -> 32373334 | S61: =SUM(F61:H61) -> 33833785 | T61: =SUM(I61:K61) -> 30669474 | U61: =SUM(L61:N61) -> 36998096 | W61: =MAX(Y42:AJ42) -> 116490.6 | X61: 数据库营销 | Y61: 2850000 | Z61: 1600000 | AA61: 2200000 | AB61: 2800000 | AC61: 1900000 | AD61: 2250000 | AE61: 2000000 | AF61: 2000000 | AG61: 2300000 | AH61: 1900000 | AI61: 3300000 | AJ61: 2400000 | AK61: 27500000 | AL61: =SUM(Y61:AD61) -> 13600000 | AM61: =SUM(AE61:AJ61) -> 13900000 | AN61: =SUM(Y61:AA61) -> 6650000 | AO61: =SUM(AB61:AD61) -> 6950000 | AP61: =SUM(AE61:AG61) -> 6300000 | AQ61: =SUM(AH61:AJ61) -> 7600000 | AS61: 1.12 | AT61: 数据库营销 | AU61: =Y61*$AS61/C61 -> 0.23006589 | AV61: =Z61*$AS61/D61 -> 0.23006589 | AW61: =AA61*$AS61/E61 -> 0.23006589 | AX61: =AB61*$AS61/F61 -> 0.23006589 | AY61: =AC61*$AS61/G61 -> 0.23006589 | AZ61: =AD61*$AS61/H61 -> 0.23006589 | BA61: =AE61*$AS61/I61 -> 0.23006589 | BB61: =AF61*$AS61/J61 -> 0.23006589 | ... BM61: =AQ61*$AS61/U61 -> 0.23006589
A62: =MAX(C43:N43) -> 256503.43 | B62: 私域 | C62: =C73*$O$62 -> 6218431.4 | D62: =D73*$O$62 -> 5499656 | E62: =E73*$O$62 -> 6853285 | F62: =F73*$O$62 -> 7601133.4 | G62: =G73*$O$62 -> 7520466.1 | H62: =H73*$O$62 -> 8356745.5 | I62: =I73*$O$62 -> 9689897.1 | J62: =J73*$O$62 -> 10692908 | ... N62: =N73*$O$62 -> 9762382 | O62: 99840000 | P62: =SUM(C62:H62) -> 42049717 | Q62: =SUM(I62:N62) -> 57790283 | R62: =SUM(C62:E62) -> 18571372 | S62: =SUM(F62:H62) -> 23478345 | T62: =SUM(I62:K62) -> 28443511 | U62: =SUM(L62:N62) -> 29346772 | W62: =MAX(Y43:AJ43) -> 25926.943 | X62: 私域 | Y62: 775000 | Z62: 633423.97 | AA62: 823712.13 | AB62: 913597.76 | AC62: 903902.17 | AD62: 1004416.5 | AE62: 1164651.1 | AF62: 1285205.3 | AG62: 968834.8 | AH62: 1266416.4 | AI62: 1087476.6 | AJ62: 1173363.2 | AK62: 12000000 | AL62: =SUM(Y62:AD62) -> 5054052.6 | AM62: =SUM(AE62:AJ62) -> 6945947.4 | AN62: =SUM(Y62:AA62) -> 2232136.1 | AO62: =SUM(AB62:AD62) -> 2821916.5 | AP62: =SUM(AE62:AG62) -> 3418691.2 | AQ62: =SUM(AH62:AJ62) -> 3527256.3 | AR62: 3.考虑目前无额外举措与增长性抓手，且25年上下半年已呈现46%：54%的权重配比，因此26年月度占比仍参考2025年，考虑公司整体目标的达成情况，不建议继续将更多目标分摊到下半年 | AS62: 1.12 | AT62: 私域 | AU62: =Y62*$AS62/C62 -> 0.13958504 | AV62: =Z62*$AS62/D62 -> 0.12899622 | AW62: =AA62*$AS62/E62 -> 0.13461538 | AX62: =AB62*$AS62/F62 -> 0.13461538 | AY62: =AC62*$AS62/G62 -> 0.13461538 | AZ62: =AD62*$AS62/H62 -> 0.13461538 | BA62: =AE62*$AS62/I62 -> 0.13461538 | BB62: =AF62*$AS62/J62 -> 0.13461538 | ... BM62: =AQ62*$AS62/U62 -> 0.13461538
X63: 其他收入（按25年预估占比） | Y63: =$AK$63*Y74 -> 4905857.1 | Z63: =$AK$63*Z74 -> 4552528.9 | AA63: =$AK$63*AA74 -> 4685672.8 | AB63: =$AK$63*AB74 -> 3466841.7 | AC63: =$AK$63*AC74 -> 3413946.2 | AD63: =$AK$63*AD74 -> 4560145.1 | AE63: =$AK$63*AE74 -> 3547587.1 | AF63: =$AK$63*AF74 -> 3777342.1 | ... AJ63: =$AK$63*AJ74 -> 5271958.5 | AK63: 50075000
X64: 电视及APP-电视商品（含自营业务） | Y64: =0.9*Y59 -> 20904013 | Z64: =0.9*Z59 -> 14566179 | AA64: =0.9*AA59 -> 16994725 | AB64: =0.9*AB59 -> 16744784 | AC64: =0.9*AC59 -> 15520909 | AD64: =0.9*AD59 -> 15756902 | AE64: =0.9*AE59 -> 15488972 | AF64: =0.9*AF59 -> 14771806 | ... AQ64: =0.9*AQ59 -> 50060298
X65: 电视及APP-电商商品 | Y65: =0.1*Y59 -> 2322668.1 | Z65: =0.1*Z59 -> 1618464.3 | AA65: =0.1*AA59 -> 1888302.8 | AB65: =0.1*AB59 -> 1860531.6 | AC65: =0.1*AC59 -> 1724545.4 | AD65: =0.1*AD59 -> 1750766.9 | AE65: =0.1*AE59 -> 1720996.9 | AF65: =0.1*AF59 -> 1641311.8 | ... AQ65: =0.1*AQ59 -> 5562255.4
C66: =C60/C$59 -> 0.79716915 | D66: =D60/D$59 -> 0.81474366 | E66: =E60/E$59 -> 0.77829883 | F66: =F60/F$59 -> 0.74092109 | G66: =G60/G$59 -> 0.78731189 | H66: =H60/H$59 -> 0.74565281 | I66: =I60/I$59 -> 0.74774198 | J66: =J60/J$59 -> 0.72140817 | ... U66: =U60/U$59 -> 0.72331566 | Y66: =Y60/Y$59 -> 0.84392949 | Z66: =Z60/Z$59 -> 0.86200351 | AA66: =AA60/AA$59 -> 0.83987143 | AB66: =AB60/AB$59 -> 0.80040125 | AC66: =AC60/AC$59 -> 0.8374121 | AD66: =AD60/AD$59 -> 0.81411481 | AE66: =AE60/AE$59 -> 0.81611523 | AF66: =AF60/AF$59 -> 0.79984271 | ... AQ66: =AQ60/AQ$59 -> 0.79995064
C67: =C61/C$59 -> 0.14005737 | D67: =D61/D$59 -> 0.10858639 | E67: =E61/E$59 -> 0.1351921 | F67: =F61/F$59 -> 0.16632776 | G67: =G61/G$59 -> 0.11730858 | H67: =H61/H$59 -> 0.14427466 | I67: =I61/I$59 -> 0.12643056 | J67: =J61/J$59 -> 0.13277361 | ... U67: =U61/U$59 -> 0.1542967 | Y67: =Y61/Y$59 -> 0.12270371 | Z67: =Z61/Z$59 -> 0.098859145 | AA67: =AA61/AA$59 -> 0.11650674 | AB67: =AB61/AB$59 -> 0.15049462 | AC67: =AC61/AC$59 -> 0.11017396 | AD67: =AD61/AD$59 -> 0.12851511 | AE67: =AE61/AE$59 -> 0.11621172 | AF67: =AF61/AF$59 -> 0.12185375 | ... AQ67: =AQ61/AQ$59 -> 0.13663522
C68: =C62/C$59 -> 0.062773477 | D68: =D62/D$59 -> 0.076669946 | E68: =E62/E$59 -> 0.086509071 | F68: =F62/F$59 -> 0.092751147 | G68: =G62/G$59 -> 0.095379525 | H68: =H62/H$59 -> 0.11007253 | I68: =I62/I$59 -> 0.12582746 | J68: =J62/J$59 -> 0.14581823 | ... U68: =U62/U$59 -> 0.12238765 | Y68: =Y62/Y$59 -> 0.033366799 | Z68: =Z62/Z$59 -> 0.039137345 | AA68: =AA62/AA$59 -> 0.043621826 | AB68: =AB62/AB$59 -> 0.049104126 | AC68: =AC62/AC$59 -> 0.052413938 | AD68: =AD62/AD$59 -> 0.057370088 | AE68: =AE62/AE$59 -> 0.067673051 | AF68: =AF62/AF$59 -> 0.078303543 | ... AQ68: =AQ62/AQ$59 -> 0.063414137
B69: 销售额占比 | C69: 1月 | D69: 2月 | E69: 3月 | F69: 4月 | G69: 5月 | H69: 6月 | I69: 7月 | J69: 8月 | K69: 9月 | L69: 10月 | M69: 11月 | N69: 12月 | O69: 合计 | P69: H1 | Q69: H2 | R69: Q1 | S69: Q2 | T69: Q3 | U69: Q4 | X69: 利润额占比 | Y69: 1月 | Z69: 2月 | AA69: 3月 | AB69: 4月 | AC69: 5月 | AD69: 6月 | AE69: 7月 | AF69: 8月 | AG69: 9月 | AH69: 10月 | AI69: 11月 | AJ69: 12月 | AK69: 合计 | AL69: H1 | AM69: H2 | AN69: Q1 | AO69: Q2 | AP69: Q3 | AQ69: Q4
B70: 存量整体 | C70: =C59/$O59 -> 0.10407836 | D70: =D59/$O59 -> 0.07536438 | E70: =E59/$O59 -> 0.083232493 | F70: =F59/$O59 -> 0.086102314 | G70: =G59/$O59 -> 0.082841005 | H70: =H59/$O59 -> 0.079765299 | I70: =I59/$O59 -> 0.080909494 | J70: =J59/$O59 -> 0.07704417 | ... U70: =U59/$O59 -> 0.2519292 | X70: 存量整体 | Y70: =Y59/$AK59 -> 0.10673681 | Z70: =Z59/$AK59 -> 0.074375553 | AA70: =AA59/$AK59 -> 0.086775815 | AB70: =AB59/$AK59 -> 0.085499608 | AC70: =AC59/$AK59 -> 0.079250446 | AD70: =AD59/$AK59 -> 0.08045544 | AE70: =AE59/$AK59 -> 0.079087374 | AF70: =AF59/$AK59 -> 0.075425495 | ... AQ70: =AQ59/$AK59 -> 0.2556101 | AR70: 5.验证按历史当年权重配比的月度占比，是否趋势一致
B71: 仅电视端及APP业务 （含自营业务） | C71: 0.10997173 | D71: 0.081387415 | E71: 0.085863663 | F71: 0.084558431 | G71: 0.086449464 | H71: 0.078835311 | I71: 0.080190216 | J71: 0.073670051 | K71: 0.077540706 | L71: 0.080078255 | M71: 0.080782181 | N71: 0.080672582 | O71: =O60/$O60 -> 1 | P71: =P60/$O60 -> 0.52706601 | Q71: =Q60/$O60 -> 0.47293399 | R71: =R60/$O60 -> 0.2772228 | S71: =S60/$O60 -> 0.24984321 | T71: =T60/$O60 -> 0.23140097 | U71: =U60/$O60 -> 0.24153302 | W71: 比重逻辑修改 | X71: 仅电视端及APP业务 （含自营业务） | Y71: =Y60/$AK$60 -> 0.11005563 | Z71: =Z60/$AK$60 -> 0.078330537 | AA71: =AA60/$AK$60 -> 0.089043736 | AB71: =AB60/$AK$60 -> 0.083611062 | AC71: =AC60/$AK$60 -> 0.081083559 | AD71: =AD60/$AK$60 -> 0.080026335 | AE71: =AE60/$AK$60 -> 0.078858861 | AF71: =AF60/$AK$60 -> 0.073707998 | ... AJ71: =AJ60/$AK$60 -> 0.091399932 | AK71: =AK60/$AK60 -> 1 | AL71: =AL60/$AK60 -> 0.52215085 | AM71: =AM60/$AK60 -> 0.47784915 | AN71: =AN60/$AK60 -> 0.2774299 | AO71: =AO60/$AK60 -> 0.24472096 | AP71: =AP60/$AK60 -> 0.22802578 | AQ71: =AQ60/$AK60 -> 0.24982336
B72: 数据库营销 | C72: =C61/$O61 -> 0.10363636 | D72: =D61/$O61 -> 0.058181818 | E72: =E61/$O61 -> 0.08 | F72: =F61/$O61 -> 0.10181818 | G72: =G61/$O61 -> 0.069090909 | H72: =H61/$O61 -> 0.081818182 | I72: =I61/$O61 -> 0.072727273 | J72: =J61/$O61 -> 0.072727273 | ... U72: =U61/$O61 -> 0.27636364 | X72: 数据库营销 | Y72: =Y61/$AK61 -> 0.10363636 | Z72: =Z61/$AK61 -> 0.058181818 | AA72: =AA61/$AK61 -> 0.08 | AB72: =AB61/$AK61 -> 0.10181818 | AC72: =AC61/$AK61 -> 0.069090909 | AD72: =AD61/$AK61 -> 0.081818182 | AE72: =AE61/$AK61 -> 0.072727273 | AF72: =AF61/$AK61 -> 0.072727273 | ... AQ72: =AQ61/$AK61 -> 0.27636364
B73: 私域 | C73: 0.062283968 | D73: 0.055084696 | E73: 0.068642678 | F73: 0.076133147 | G73: 0.075325181 | H73: 0.083701377 | I73: 0.097054258 | J73: 0.10710044 | K73: 0.080736233 | L73: 0.1055347 | M73: 0.090623054 | N73: 0.097780269 | O73: =O62/$O62 -> 1 | P73: =P62/$O62 -> 0.42117105 | Q73: =Q62/$O62 -> 0.57882895 | R73: =R62/$O62 -> 0.18601134 | S73: =S62/$O62 -> 0.2351597 | T73: =T62/$O62 -> 0.28489093 | U73: =U62/$O62 -> 0.29393802 | X73: 私域 | Y73: =Y62/$AK$62 -> 0.064583333 | Z73: =Z62/$AK$62 -> 0.052785331 | AA73: =AA62/$AK$62 -> 0.068642678 | AB73: =AB62/$AK$62 -> 0.076133147 | AC73: =AC62/$AK$62 -> 0.075325181 | AD73: =AD62/$AK$62 -> 0.083701377 | AE73: =AE62/$AK$62 -> 0.097054258 | AF73: =AF62/$AK$62 -> 0.10710044 | ... AJ73: =AJ62/$AK$62 -> 0.097780269 | AK73: =AK62/$AK62 -> 1 | AL73: =AL62/$AK62 -> 0.42117105 | AM73: =AM62/$AK62 -> 0.57882895 | AN73: =AN62/$AK62 -> 0.18601134 | AO73: =AO62/$AK62 -> 0.2351597 | AP73: =AP62/$AK62 -> 0.28489093 | AQ73: =AQ62/$AK62 -> 0.29393802
X74: 其他收入（按25年预估占比） | Y74: 0.097970187 | Z74: 0.090914207 | AA74: 0.093573097 | AB74: 0.069232985 | AC74: 0.068176659 | AD74: 0.091066302 | AE74: 0.070845474 | AF74: 0.075433692 | AG74: 0.07227684 | AH74: 0.056014642 | AI74: 0.10921467 | AJ74: 0.10528125 | AK74: =SUM(Y74:AJ74) -> 1
X75: 电视及APP-电视商品（含自营业务） | Y75: =Y64/$AK$64 -> 0.10673681 | Z75: =Z64/$AK$64 -> 0.074375553 | AA75: =AA64/$AK$64 -> 0.086775815 | AB75: =AB64/$AK$64 -> 0.085499608 | AC75: =AC64/$AK$64 -> 0.079250446 | AD75: =AD64/$AK$64 -> 0.08045544 | AE75: =AE64/$AK$64 -> 0.079087374 | AF75: =AF64/$AK$64 -> 0.075425495 | ... AQ75: =AQ64/$AK$64 -> 0.2556101
X76: 电视及APP-电商商品 | Y76: =Y65/$AK$65 -> 0.10673681 | Z76: =Z65/$AK$65 -> 0.074375553 | AA76: =AA65/$AK$65 -> 0.086775815 | AB76: =AB65/$AK$65 -> 0.085499608 | AC76: =AC65/$AK$65 -> 0.079250446 | AD76: =AD65/$AK$65 -> 0.08045544 | AE76: =AE65/$AK$65 -> 0.079087374 | AF76: =AF65/$AK$65 -> 0.075425495 | ... AQ76: =AQ65/$AK$65 -> 0.2556101
X77: 其他收入占比（拟） | Y77: 0.10104717 | Z77: 0.093769579 | AA77: 0.096511978 | AB77: 0.071407408 | AC77: 0.070317906 | AD77: 0.093926451 | AE77: 0.073070542 | AF77: 0.077802863 | AG77: 0.074546863 | AH77: 0.057773912 | AI77: 0.11264481 | AJ77: 0.077180523
B79: 天数 | C79: 31 | D79: 28 | E79: 31 | F79: 30 | G79: 31 | H79: 30 | I79: 31 | J79: 31 | K79: 30 | L79: 31 | M79: 30 | N79: 31 | O79: =SUM(C79:N79) -> 365 | P79: =SUM(C79:H79) -> 181 | Q79: =SUM(I79:N79) -> 184 | R79: =SUM(C79:E79) -> 90 | S79: =SUM(F79:H79) -> 91 | T79: =SUM(I79:K79) -> 92 | U79: =SUM(L79:N79) -> 92 | X79: 天数 | Y79: 31 | Z79: 28 | AA79: 31 | AB79: 30 | AC79: 31 | AD79: 30 | AE79: 31 | AF79: 31 | AG79: 30 | AH79: 31 | AI79: 30 | AJ79: 31 | AK79: =SUM(Y79:AJ79) -> 365 | AL79: =SUM(Y79:AD79) -> 181 | AM79: =SUM(AE79:AJ79) -> 184 | AN79: =SUM(Y79:AA79) -> 90 | AO79: =SUM(AB79:AD79) -> 91 | AP79: =SUM(AE79:AG79) -> 92 | AQ79: =SUM(AH79:AJ79) -> 92
B80: 日均销售额 | C80: 1月 | D80: 2月 | E80: 3月 | F80: 4月 | G80: 5月 | H80: 6月 | I80: 7月 | J80: 8月 | K80: 9月 | L80: 10月 | M80: 11月 | N80: 12月 | O80: 合计 | P80: H1 | Q80: H2 | R80: Q1 | S80: Q2 | T80: Q3 | U80: Q4 | X80: 日均利润额 | Y80: 1月 | Z80: 2月 | AA80: 3月 | AB80: 4月 | AC80: 5月 | AD80: 6月 | AE80: 7月 | AF80: 8月 | AG80: 9月 | AH80: 10月 | AI80: 11月 | AJ80: 12月 | AK80: 合计 | AL80: H1 | AM80: H2 | AN80: Q1 | AO80: Q2 | AP80: Q3 | AQ80: Q4
B81: 存量整体 | C81: =C59/C$79 -> 3195530.5 | D81: =D59/D$79 -> 2561842 | E81: =E59/E$79 -> 2555497.4 | F81: =F59/F$79 -> 2731730.3 | G81: =G59/G$79 -> 2543477.5 | H81: =H59/H$79 -> 2530678.5 | I81: =I59/I$79 -> 2484174.1 | J81: =J59/J$79 -> 2365496.6 | ... U81: =U59/U$79 -> 2606363.1 | X81: 存量整体 | Y81: =Y59/Y$79 -> 749247.77 | Z81: =Z59/Z$79 -> 578022.98 | AA81: =AA59/AA$79 -> 609129.92 | AB81: =AB59/AB$79 -> 620177.19 | AC81: =AC59/AC$79 -> 556304.97 | AD81: =AD59/AD$79 -> 583588.98 | AE81: =AE59/AE$79 -> 555160.28 | AF81: =AF59/AF$79 -> 529455.42 | ... AQ81: =AQ59/AQ$79 -> 604592.98
B82: 仅电视端及APP业务 （含自营业务） | C82: =C60/C$79 -> 2547378.4 | D82: =D60/D$79 -> 2087244.5 | E82: =E60/E$79 -> 1988940.7 | F82: =F60/F$79 -> 2023996.6 | G82: =G60/G$79 -> 2002510.1 | H82: =H60/H$79 -> 1887007.6 | I82: =I60/I$79 -> 1857521.3 | J82: =J60/J$79 -> 1706488.6 | ... U82: =U60/U$79 -> 1885223.3 | X82: 仅电视端及APP业务 （含自营业务） | Y82: =Y60/Y$79 -> 632312.28 | Z82: =Z60/Z$79 -> 498257.83 | AA82: =AA60/AA$79 -> 511590.82 | AB82: =AB60/AB$79 -> 496390.6 | AC82: =AC60/AC$79 -> 465856.52 | AD82: =AD60/AD$79 -> 475108.43 | AE82: =AE60/AE$79 -> 453074.76 | AF82: =AF60/AF$79 -> 423481.06 | ... AQ82: =AQ60/AQ$79 -> 483644.54
B83: 数据库营销 | C83: =C61/C$79 -> 447557.62 | D83: =D61/D$79 -> 278181.17 | E83: =E61/E$79 -> 345483.07 | F83: =F61/F$79 -> 454362.59 | G83: =G61/G$79 -> 298371.74 | H83: =H61/H$79 -> 365112.79 | I83: =I61/I$79 -> 314075.52 | J83: =J61/J$79 -> 314075.52 | ... U83: =U61/U$79 -> 402153.22 | X83: 数据库营销 | Y83: =Y61/Y$79 -> 91935.484 | Z83: =Z61/Z$79 -> 57142.857 | AA83: =AA61/AA$79 -> 70967.742 | AB83: =AB61/AB$79 -> 93333.333 | AC83: =AC61/AC$79 -> 61290.323 | AD83: =AD61/AD$79 -> 75000 | AE83: =AE61/AE$79 -> 64516.129 | AF83: =AF61/AF$79 -> 64516.129 | ... AQ83: =AQ61/AQ$79 -> 82608.696
B84: 私域 | C84: =C62/C$79 -> 200594.56 | D84: =D62/D$79 -> 196416.29 | E84: =E62/E$79 -> 221073.71 | F84: =F62/F$79 -> 253371.11 | G84: =G62/G$79 -> 242595.68 | H84: =H62/H$79 -> 278558.18 | I84: =I62/I$79 -> 312577.33 | J84: =J62/J$79 -> 344932.52 | ... U84: =U62/U$79 -> 318986.65 | X84: 私域 | Y84: =Y62/Y$79 -> 25000 | Z84: =Z62/Z$79 -> 22622.285 | AA84: =AA62/AA$79 -> 26571.359 | AB84: =AB62/AB$79 -> 30453.259 | AC84: =AC62/AC$79 -> 29158.135 | AD84: =AD62/AD$79 -> 33480.551 | AE84: =AE62/AE$79 -> 37569.39 | AF84: =AF62/AF$79 -> 41458.235 | ... AQ84: =AQ62/AQ$79 -> 38339.742
X85: 电视及APP-电视商品（含自营业务） | Y85: =Y64/Y$79 -> 674322.99 | Z85: =Z64/Z$79 -> 520220.68 | AA85: =AA64/AA$79 -> 548216.93 | AB85: =AB64/AB$79 -> 558159.47 | AC85: =AC64/AC$79 -> 500674.48 | AD85: =AD64/AD$79 -> 525230.08 | AE85: =AE64/AE$79 -> 499644.25 | AF85: =AF64/AF$79 -> 476509.88 | ... AQ85: =AQ64/AQ$79 -> 544133.68
X86: 电视及APP-电商商品 | Y86: =Y65/Y$79 -> 74924.777 | Z86: =Z65/Z$79 -> 57802.298 | AA86: =AA65/AA$79 -> 60912.992 | AB86: =AB65/AB$79 -> 62017.719 | AC86: =AC65/AC$79 -> 55630.497 | AD86: =AD65/AD$79 -> 58358.898 | AE86: =AE65/AE$79 -> 55516.028 | AF86: =AF65/AF$79 -> 52945.542 | ... AQ86: =AQ65/AQ$79 -> 60459.298
Y87: 747407.62 | Z87: 661016.35 | AA87: 823712.13 | AB87: 0.093530968 | AC87: 0.092538367 | AD87: 0.10282868 | AE87: 0.11923294 | AF87: 0.13157486 | AG87: 0.099185944 | AH87: 0.12965131 | AI87: 0.11133208 | AJ87: 0.12012485 | AL87: 9174334.5
Y88: 1.0212725 | Z88: 1 | AA88: 1.1255365 | AB88: 55513.38 | AC88: 54924.242 | AD88: 61031.844 | AE88: 70768.254 | AF88: 78093.547 | AG88: 58869.775 | AH88: 76951.868 | AI88: 66078.866 | AJ88: 71297.634
Y89: 198737.17 | Z89: 175765.56 | AA89: 219026.69 | AB89: 913597.76 | AC89: 903902.17 | AD89: 1004416.5 | AE89: 1164651.1 | AF89: 1285205.3 | AG89: 968834.8 | AH89: 1266416.4 | AI89: 1087476.6 | AJ89: 1173363.2 | AL89: 593529.41
X91: 关于私域目标：
X92: 1. 私域2026年总体目标1200万中：2025年各渠道整体800万（含快团团），同比持平；增长的400万主要集中在“公域转私域”渠道。快团团与公域转私域数据，目前不进入ERP，不涉及双计；
X93: 2. 上下半年的目标配比数据：（1）2025年上下半年比重46:54；（2）26年上半年目标总额，拟持平25年下半年，其他计入下半年，比重为36：64；（3）业务提供的方案，上半年占比仅33.9%、比重过低，对公司完成度有较大风险；
X94: 3. 目前设计方案，1-2月考虑春节因素，一季度维持25年下半年月均水平，二季度开始提升；
X95: 4. 存量整体月度比重，1-2月较按趋势模式的比重略低（影响0.36个点），主要受私域一季度目标占比较低影响。
X98: 2026年目标同比2025年 | Y98: 1月 | Z98: 2月 | AA98: 1-2月合计
X99: 仅电视及APP 同比下降15% | AA99: =(Y10+Z10)*0.85 -> 33552900
X100: 数据库营销同比增长4% | AA100: =(Y11+Z11)*1.04 -> 4607026.3 | AB100: 443
X101: 私域同比增长 | Y101: 140.8 | AA101: =AVERAGE(AE12:AJ12)*2 -> 1469739.4
Y102: 68.4 | AA102: =AA101/(31+28)*(31+20+8*0.7) -> 1409953.4
Y103: =Y101/Y102-1 -> 1.0584795
X104: 26年利润目标同比25年实际
X105: 利润同比 | Y105: 1月 | Z105: 2月 | AA105: 3月 | AB105: 4月 | AC105: 5月 | AD105: 6月 | AE105: 7月 | AF105: 8月 | AG105: 9月 | AH105: 10月 | AI105: 11月 | AJ105: 12月 | AK105: 合计 | AL105: H1 | AM105: H2 | AN105: Q1 | AO105: Q2 | AP105: Q3 | AQ105: Q4 | AR105: 1-2月合计
X106: 存量整体 | Y106: =Y59/Y9-1 -> -0.11293323 | Z106: =Z59/Z9-1 -> -0.14399919 | AA106: =AA59/AA9-1 -> -0.10849381 | AB106: =AB59/AB9-1 -> -0.088865443 | AC106: =AC59/AC9-1 -> -0.093699391 | AD106: =AD59/AD9-1 -> -0.095043516 | AE106: =AE59/AE9-1 -> -0.087284769 | AF106: =AF59/AF9-1 -> -0.082989397 | ... AQ106: =AQ59/AQ9-1 -> -0.110483 | AR106: =(Y59+Z59)/(Y9+Z9)-1 -> -0.12595963
X107: 仅电视端及APP业务 （含自营业务） | Y107: =Y60/Y10-1 -> -0.15 | Z107: =Z60/Z10-1 -> -0.15 | AA107: =AA60/AA10-1 -> -0.13604747 | AB107: =AB60/AB10-1 -> -0.13588653 | AC107: =AC60/AC10-1 -> -0.13580428 | AD107: =AD60/AD10-1 -> -0.13576833 | AE107: =AE60/AE10-1 -> -0.13572751 | AF107: =AF60/AF10-1 -> -0.13553192 | ... AQ107: =AQ60/AQ10-1 -> -0.15472303 | AR107: =(Y60+Z60)/(Y10+Z10)-1 -> -0.15
X108: 数据库营销 | Y108: =Y61/Y11-1 -> 0.11775612 | Z108: =Z61/Z11-1 -> -0.1489732 | AA108: =AA61/AA11-1 -> 0.032839023 | AB108: =AB61/AB11-1 -> 0.070712778 | AC108: =AC61/AC11-1 -> 0.08438056 | AD108: =AD61/AD11-1 -> 0.010833439 | AE108: =AE61/AE11-1 -> 0.065859967 | AF108: =AF61/AF11-1 -> 0.047859571 | ... AQ108: =AQ61/AQ11-1 -> -0.0026285593 | AR108: =(Y61+Z61)/(Y11+Z11)-1 -> 0.0045525418
X109: 私域 | Y109: =Y62/Y12-1 -> 0.35220658 | Z109: =Z62/Z12-1 -> 0.03164398 | AA109: =AA62/AA12-1 -> 0.18640889 | AB109: =AB62/AB12-1 -> 0.59904063 | AC109: =AC62/AC12-1 -> 0.59904063 | AD109: =AD62/AD12-1 -> 0.59904063 | AE109: =AE62/AE12-1 -> 0.59904063 | AF109: =AF62/AF12-1 -> 0.59904063 | ... AQ109: =AQ62/AQ12-1 -> 0.55299918 | AR109: =(Y62+Z62)/(Y12+Z12)-1 -> 0.18640889
X110: 电视及APP-电视商品（含自营业务） | Y110: =Y64/Y14-1 -> -0.096681303 | Z110: =Z64/Z14-1 -> -0.129905 | AA110: =AA64/AA14-1 -> -0.088806661 | AB110: =AB64/AB14-1 -> -0.076256861 | AC110: =AC64/AC14-1 -> -0.089717024 | AD110: =AD64/AD14-1 -> -0.086156462 | AE110: =AE64/AE14-1 -> -0.092110865 | AF110: =AF64/AF14-1 -> -0.090150948 | ... AQ110: =AQ64/AQ14-1 -> -0.065363551 | AR110: =(Y64+Z64)/(Y14+Z14)-1 -> -0.11062723
X111: 电视及APP-电商商品 | Y111: =Y65/Y15-1 -> -0.16127233 | Z111: =Z65/Z15-1 -> -0.16423035 | AA111: =AA65/AA15-1 -> -0.15963942 | AB111: =AB65/AB15-1 -> -0.092440623 | AC111: =AC65/AC15-1 -> -0.0087064162 | AD111: =AD65/AD15-1 -> -0.067197005 | AE111: =AE65/AE15-1 -> 0.1039674 | AF111: =AF65/AF15-1 -> 0.14755823 | ... AQ111: =AQ65/AQ15-1 -> -0.33083654 | AR111: =(Y65+Z65)/(Y15+Z15)-1 -> -0.1624896
X113: 仅电视端及APP业务 （含自营业务）同比下降15% | Y113: =Y10*0.85 -> 19601681 | Z113: =Z10*0.85 -> 13951219 | AA113: =AA60+$AA$116 -> 15904644 | AB113: =AB60+$AA$116 -> 14937047 | AC113: =AC60+$AA$116 -> 14486881 | AD113: =AD60+$AA$116 -> 14298582 | AE113: =AE60+$AA$116 -> 14090646 | AF113: =AF60+$AA$116 -> 13173242 | AG113: =AG60+$AA$116 -> 13485093 | AH113: =AH60+$AA$116 -> 12994438 | ... AJ113: =AJ60+$AA$116 -> 16324299 | AK113: =SUM(Y113:AJ113) -> 1.7856032e+08
Y114: 19866493 | Z114: 14139695 | AA114: =Y114+Z114 -> 34006188
AA115: =AA114-AA113 -> 18101544
AA116: 45328.783

Sheet 2. 按趋势预测Q1
C2: 预测26年 | D2: 基础版 | L2: 预测26年 | M2: 业务非常规举措版 | S2: 业务增额部分
B3: 12月 | C3: 利润金额 | D3: 1月 | E3: 2月 | F3: 3月 | G3: Q1 | H3: 全年 | L3: 利润金额 | M3: 1月 | N3: 2月 | O3: 3月 | P3: Q1 | S3: 利润金额 | T3: 1月 | U3: 2月 | V3: 3月 | W3: Q1
B4: 22971148 | C4: 存量整体 | D4: =SUM(D5:D7) -> 21932055 | E4: =SUM(E5:E7) -> 15165372 | F4: =SUM(F5:F7) -> 17259164 | G4: =SUM(G5:G7) -> 54356591 | H4: 2.1760703e+08 | L4: 存量整体 | M4: =SUM(M5:M7) -> 22767055 | N4: =SUM(N5:N7) -> 15925372 | O4: =SUM(O5:O7) -> 18334164 | P4: =SUM(P5:P7) -> 57026591 | S4: 存量整体 | T4: =SUM(T5:T7) -> 835000 | U4: =SUM(U5:U7) -> 760000 | V4: =SUM(V5:V7) -> 1075000 | W4: =SUM(W5:W7) -> 2670000
B5: 19991942 | C5: 仅电视端及APP业务 （含自营业务） | D5: =B5/31*(1+D8)*31 -> 18991594 | E5: =D5/31*(1+E8)*28 -> 12876303 | F5: =E5/28*(1+F8)*31 -> 14318702 | G5: =SUM(D5:F5) -> 46186600 | H5: 1.7810703e+08 | I5: 26年涨幅 | J5: 25年最高月日均利润 | L5: 仅电视端及APP业务 （含自营业务） | M5: =D5+T5 -> 19526594 | N5: =E5+U5 -> 13636303 | O5: =F5+V5 -> 15393702 | P5: =SUM(M5:O5) -> 48556600 | S5: 仅电视端及APP业务 （含自营业务） | T5: 535000 | U5: 760000 | V5: 1075000 | W5: =SUM(T5:V5) -> 2370000
B6: 2180017.1 | C6: 数据库营销 | D6: ='1. 按目标v0.2'!$AK$42*(1+0)*D15 -> 2256304.2 | E6: ='1. 按目标v0.2'!$AK$42*(1+0)*E15*(1-0.18) -> 1671120.8 | F6: ='1. 按目标v0.2'!$AK$42*(1+0)*F15 -> 2256304.2 | G6: =SUM(D6:F6) -> 6183729.1 | H6: 27500000 | I6: 0.042213631 | J6: 116490.6 | K6: 82250.039 | L6: 数据库营销 | M6: =D6+T6 -> 2556304.2 | N6: =E6+U6 -> 1671120.8 | O6: =F6+V6 -> 2256304.2 | P6: =SUM(M6:O6) -> 6483729.1 | S6: 数据库营销 | T6: 300000 | W6: =SUM(T6:V6) -> 300000
B7: 799188.63 | C7: 私域 | D7: ='1. 按目标v0.2'!$AK$43*(1+0)*'2. 按趋势预测Q1'!D15 -> 684156.97 | E7: ='1. 按目标v0.2'!$AK$43*(1+0)*'2. 按趋势预测Q1'!E15 -> 617948.23 | F7: ='1. 按目标v0.2'!$AK$43*(1+0)*'2. 按趋势预测Q1'!F15 -> 684156.97 | G7: =SUM(D7:F7) -> 1986262.2 | H7: 12000000 | I7: 0.50187736 | J7: 25926.943 | L7: 私域 | M7: =D7+T7 -> 684156.97 | N7: =E7+U7 -> 617948.23 | O7: =F7+V7 -> 684156.97 | P7: =SUM(M7:O7) -> 1986262.2 | S7: 私域 | W7: =SUM(T7:V7) -> 0
C8: 参考24年日均环比 | D8: -0.050037558 | E8: -0.249357 | F8: 0.0044048615
D10: =D5/D$4 -> 0.86592861 | E10: =E5/E$4 -> 0.84905949 | F10: =F5/F$4 -> 0.82962899 | G10: =G5/G$4 -> 0.8496964 | H10: =H5/H$4 -> 0.81848013 | M10: =M5/M$4 -> 0.85766885 | N10: =N5/N$4 -> 0.85626276 | O10: =O5/O$4 -> 0.83961847 | P10: =P5/P$4 -> 0.85147295
D11: =D6/D$4 -> 0.10287701 | E11: =E6/E$4 -> 0.11019319 | F11: =F6/F$4 -> 0.13073079 | G11: =G6/G$4 -> 0.11376227 | H11: =H6/H$4 -> 0.12637459 | M11: =M6/M$4 -> 0.11228084 | N11: =N6/N$4 -> 0.10493449 | O11: =O6/O$4 -> 0.12306556 | P11: =P6/P$4 -> 0.11369659
D12: =D7/D$4 -> 0.031194385 | E12: =E7/E$4 -> 0.040747317 | F12: =F7/F$4 -> 0.039640216 | G12: =G7/G$4 -> 0.036541331 | H12: =H7/H$4 -> 0.055145277 | M12: =M7/M$4 -> 0.030050306 | N12: =N7/N$4 -> 0.038802749 | O12: =O7/O$4 -> 0.037315963 | P12: =P7/P$4 -> 0.034830456
C15: 天数 | D15: 31 | E15: 28 | F15: 31 | G15: 90 | L15: 天数 | M15: 31 | N15: 28 | O15: 31 | P15: 90
B16: 12月 | C16: 日均利润额 | D16: 1月 | E16: 2月 | F16: 3月 | G16: Q1 | L16: 日均利润额 | M16: 1月 | N16: 2月 | O16: 3月 | P16: Q1
B17: =B4/31 -> 741004.77 | C17: 存量整体 | D17: =D4/D$15 -> 707485.65 | E17: =E4/E$15 -> 541620.44 | F17: =F4/F$15 -> 556747.21 | G17: =G4/G$15 -> 603962.12 | L17: 存量整体 | M17: =M4/M$15 -> 734421.14 | N17: =N4/N$15 -> 568763.29 | O17: =O4/O$15 -> 591424.63 | P17: =P4/P$15 -> 633628.79
B18: =B5/31 -> 644901.36 | C18: 仅电视端及APP业务 （含自营业务） | D18: =D5/D$15 -> 612632.07 | E18: =E5/E$15 -> 459867.97 | F18: =F5/F$15 -> 461893.63 | G18: =G5/G$15 -> 513184.44 | L18: 仅电视端及APP业务 （含自营业务） | M18: =M5/M$15 -> 629890.13 | N18: =N5/N$15 -> 487010.83 | O18: =O5/O$15 -> 496571.05 | P18: =P5/P$15 -> 539517.78
B19: =B6/31 -> 70323.132 | C19: 数据库营销 | D19: =D6/D$15 -> 72784.006 | E19: =E6/E$15 -> 59682.885 | F19: =F6/F$15 -> 72784.006 | G19: =G6/G$15 -> 68708.101 | L19: 数据库营销 | M19: =M6/M$15 -> 82461.425 | N19: =N6/N$15 -> 59682.885 | O19: =O6/O$15 -> 72784.006 | P19: =P6/P$15 -> 72041.435
B20: =B7/31 -> 25780.278 | C20: 私域 | D20: =D7/D$15 -> 22069.58 | E20: =E7/E$15 -> 22069.58 | F20: =F7/F$15 -> 22069.58 | G20: =G7/G$15 -> 22069.58 | L20: 私域 | M20: =M7/M$15 -> 22069.58 | N20: =N7/N$15 -> 22069.58 | O20: =O7/O$15 -> 22069.58 | P20: =P7/P$15 -> 22069.58
C24: 日均环比 | D24: 1月 | E24: 2月 | F24: 3月 | L24: 日均环比 | M24: 1月 | N24: 2月 | O24: 3月
C25: 存量整体 | D25: =D17/B17-1 -> -0.045234681 | E25: =E17/D17-1 -> -0.23444322 | F25: =F17/E17-1 -> 0.027928739 | L25: 存量整体 | M25: =M17/B17-1 -> -0.0088847348 | N25: =N17/M17-1 -> -0.22556247 | O25: =O17/N17-1 -> 0.039843179
C26: 仅电视端及APP业务 （含自营业务） | D26: =D18/B18-1 -> -0.050037558 | E26: =E18/D18-1 -> -0.249357 | F26: =F18/E18-1 -> 0.0044048615 | L26: 仅电视端及APP业务 （含自营业务） | M26: =M18/B18-1 -> -0.023276777 | N26: =N18/M18-1 -> -0.2268321 | O26: =O18/N18-1 -> 0.019630399
C27: 数据库营销 | D27: =D19/B19-1 -> 0.034993798 | E27: =E19/D19-1 -> -0.18 | F27: =F19/E19-1 -> 0.2195122 | L27: 数据库营销 | M27: =M19/B19-1 -> 0.1726074 | N27: =N19/M19-1 -> -0.27623268 | O27: =O19/N19-1 -> 0.2195122
C28: 私域 | D28: =D20/B20-1 -> -0.14393556 | E28: =E20/D20-1 -> 0 | F28: =F20/E20-1 -> 0 | L28: 私域 | M28: =M20/B20-1 -> -0.14393556 | N28: =N20/M20-1 -> 0 | O28: =O20/N20-1 -> 0
C32: 日均占比 | D32: 1月 | E32: 2月 | F32: 3月 | G32: Q1 | L32: 日均占比 | M32: 1月 | N32: 2月 | O32: 3月 | P32: Q1
C33: 存量整体 | D33: =D4/$H4 -> 0.10078744 | E33: =E4/$H4 -> 0.069691555 | F33: =F4/$H4 -> 0.079313447 | G33: =G4/$H4 -> 0.24979244 | L33: 存量整体 | M33: =M4/$H4 -> 0.10462463 | N33: =N4/$H4 -> 0.073184089 | O33: =O4/$H4 -> 0.084253544 | P33: =P4/$H4 -> 0.26206226
C34: 仅电视端及APP业务 （含自营业务） | D34: =D5/$H5 -> 0.10663023 | E34: =E5/$H5 -> 0.072295311 | F34: =F5/$H5 -> 0.080393808 | G34: =G5/$H5 -> 0.25931935 | L34: 仅电视端及APP业务 （含自营业务） | M34: =M5/$H5 -> 0.10963404 | N34: =N5/$H5 -> 0.076562409 | O34: =O5/$H5 -> 0.086429505 | P34: =P5/$H5 -> 0.27262596
C35: 数据库营销 | D35: =D6/$H6 -> 0.082047425 | E35: =E6/$H6 -> 0.060768028 | F35: =F6/$H6 -> 0.082047425 | G35: =G6/$H6 -> 0.22486288 | L35: 数据库营销 | M35: =M6/$H6 -> 0.092956516 | N35: =N6/$H6 -> 0.060768028 | O35: =O6/$H6 -> 0.082047425 | P35: =P6/$H6 -> 0.23577197
C36: 私域 | D36: =D7/$H7 -> 0.057013081 | E36: =E7/$H7 -> 0.051495686 | F36: =F7/$H7 -> 0.057013081 | G36: =G7/$H7 -> 0.16552185 | L36: 私域 | M36: =M7/$H7 -> 0.057013081 | N36: =N7/$H7 -> 0.051495686 | O36: =O7/$H7 -> 0.057013081 | P36: =P7/$H7 -> 0.16552185
C40: 利润目标 | D40: 1月 | E40: 2月 | F40: 3月 | G40: Q1
C41: 存量整体 | D41: 23226681 | E41: 16184643 | F41: 18883028 | G41: 58294352
C42: 仅电视端及APP业务 （含自营业务） | D42: 19601681 | E42: 13951219 | F42: 15859315 | G42: 49412216
C43: 数据库营销 | D43: 2850000 | E43: 1600000 | F43: 2200000 | G43: 6650000
C44: 私域 | D44: 775000 | E44: 633423.97 | F44: 823712.13 | G44: 2232136.1
C48: 预测达成率 | D48: 1月 | E48: 2月 | F48: 3月 | G48: Q1 | L48: 预测达成率 | M48: 1月 | N48: 2月 | O48: 3月 | P48: Q1
C49: 存量整体 | D49: =D4/D41 -> 0.94426128 | E49: =E4/E41 -> 0.93702233 | F49: =F4/F41 -> 0.91400405 | G49: =G4/G41 -> 0.93245039 | L49: 存量整体 | M49: =M4/D41 -> 0.98021132 | N49: =N4/E41 -> 0.98398043 | O49: =O4/F41 -> 0.97093348 | P49: =P4/G41 -> 0.97825243
C50: 仅电视端及APP业务 （含自营业务） | D50: =D5/D42 -> 0.9688758 | E50: =E5/E42 -> 0.92295182 | F50: =F5/F42 -> 0.90285754 | G50: =G5/G42 -> 0.93472028 | L50: 仅电视端及APP业务 （含自营业务） | M50: =M5/D42 -> 0.99616938 | N50: =N5/E42 -> 0.97742734 | O50: =O5/F42 -> 0.97064104 | P50: =P5/G42 -> 0.98268413
C51: 数据库营销 | D51: =D6/D43 -> 0.79168568 | E51: =E6/E43 -> 1.0444505 | F51: =F6/F43 -> 1.0255928 | G51: =G6/G43 -> 0.92988408 | L51: 数据库营销 | M51: =M6/D43 -> 0.89694883 | N51: =N6/E43 -> 1.0444505 | O51: =O6/F43 -> 1.0255928 | P51: =P6/G43 -> 0.97499686
C52: 私域 | D52: =D7/D44 -> 0.88278318 | E52: =E7/E44 -> 0.97556812 | F52: =F7/F44 -> 0.83057775 | G52: =G7/G44 -> 0.88984814 | L52: 私域 | M52: =M7/D44 -> 0.88278318 | N52: =N7/E44 -> 0.97556812 | O52: =O7/F44 -> 0.83057775 | P52: =P7/G44 -> 0.88984814
C56: 25年利润实际 | D56: 1月 | E56: 2月 | F56: 3月 | G56: Q1
C57: 存量整体 | D57: 26183689 | E57: 18907276 | F57: 21181039 | G57: 66272004
C58: 仅电视端及APP业务 （含自营业务） | D58: 23060801 | E58: 16413199 | F58: 18356698 | G58: 57830698
C59: 数据库营销 | D59: 2549751.2 | E59: 1880081.8 | F59: 2130051.2 | G59: 6559884.2
C60: 私域 | D60: 573137.28 | E60: 613994.73 | F60: 694290.26 | G60: 1881422.3
C62: 基础版 | L62: 业务非常规举措版
C63: 预测实际同比 | D63: 1月 | E63: 2月 | F63: 3月 | G63: Q1 | L63: 预测实际同比 | M63: 1月 | N63: 2月 | O63: 3月 | P63: Q1
C64: 存量整体 | D64: =D4/D57-1 -> -0.1623772 | E64: =E4/E57-1 -> -0.19790813 | F64: =F4/F57-1 -> -0.18515973 | G64: =G4/G57-1 -> -0.17979557 | L64: 存量整体 | M64: =M4/D57-1 -> -0.13048711 | N64: =N4/E57-1 -> -0.15771196 | O64: =O4/F57-1 -> -0.13440679 | P64: =P4/G57-1 -> -0.13950707
C65: 仅电视端及APP业务 （含自营业务） | D65: =D5/D58-1 -> -0.17645557 | E65: =E5/E58-1 -> -0.21549096 | F65: =F5/F58-1 -> -0.21997394 | G65: =G5/G58-1 -> -0.20134804 | L65: 仅电视端及APP业务 （含自营业务） | M65: =M5/D58-1 -> -0.15325603 | N65: =N5/E58-1 -> -0.16918676 | O65: =O5/F58-1 -> -0.16141221 | P65: =P5/G58-1 -> -0.16036635
C66: 数据库营销 | D66: =D6/D59-1 -> -0.11508849 | E66: =E6/E59-1 -> -0.11114465 | F66: =F6/F59-1 -> 0.059272274 | G66: =G6/G59-1 -> -0.057341724 | L66: 数据库营销 | M66: =M6/D59-1 -> 0.0025700462 | N66: =N6/E59-1 -> -0.11114465 | O66: =O6/F59-1 -> 0.059272274 | P66: =P6/G59-1 -> -0.01160921
C67: 私域 | D67: =D7/D60-1 -> 0.19370523 | E67: =E7/E60-1 -> 0.0064389791 | F67: =F7/F60-1 -> -0.014595181 | G67: =G7/G60-1 -> 0.055723745 | L67: 私域 | M67: =M7/D60-1 -> 0.19370523 | N67: =N7/E60-1 -> 0.0064389791 | O67: =O7/F60-1 -> -0.014595181 | P67: =P7/G60-1 -> 0.055723745

Sheet 3. 移动端分月目标
A1: GMV
A2: 统计月份 | B2: GMV目标-总 | C2: GMV目标-自有供应链 | G2: 周 | H2: 日
A3: 46023 | B3: 35750000 | C3: 3200000 | D3: =C3*0.8/1.13 -> 2265486.7 | E3: =D3+D20 -> 5299226.5 | G3: =C3/31*7 -> 722580.65 | H3: =B3/31 -> 1153225.8
A4: 46054 | B4: 22750000 | C4: 2600000 | H4: =B4/28 -> 812500 | J4: 47854856 | K4: =B3+B4-J4 -> 10645144
A5: 46082 | B5: 32500000 | C5: 5800000 | E5: =B5/310000 -> 104.83871
A6: 46113 | B6: 52000000 | C6: 13500000 | D6: =B6/B5-1 -> 0.6 | E6: =B6/300000 -> 173.33333 | F6: =E6/E5-1 -> 0.65333333 | G6: 36683171 | H6: =B6/G6-1 -> 0.41754377
A7: 46143 | B7: 55250000 | C7: 12750000
A8: 46174 | B8: 61750000 | C8: 14250000
A9: 46204 | B9: 58500000 | C9: 15000000
A10: 46235 | B10: 61750000 | C10: 15000000
A11: 46266 | B11: 61750000 | C11: 15000000
A12: 46296 | B12: 55250000 | C12: 16750000
A13: 46327 | B13: 84500000 | C13: 21250000
A14: 46357 | B14: 68250000 | C14: 14900000
A15: 2026年 | B15: =SUM(B3:B14) -> 650000000 | C15: =SUM(C3:C14) -> 150000000
A18: 利润
A19: 统计月份 | B19: 利润目标-总 | C19: 利润目标-自有供应链
A20: 46023 | B20: 3721244.2 | C20: 687504.43 | D20: =B20-C20 -> 3033739.7
A21: 46054 | B21: 2604870.9 | C21: 558597.35
A22: 46082 | B22: 3721244.2 | C22: 1246101.8
A23: 46113 | B23: 5581866.2 | C23: 2900409.3
A24: 46143 | B24: 5953990.6 | C24: 2739275.5
A25: 46174 | B25: 6698239.5 | C25: 3061543.1
A26: 46204 | B26: 6698239.5 | C26: 3222677
A27: 46235 | B27: 7070363.9 | C27: 3222677
A28: 46266 | B28: 7070363.9 | C28: 3222677
A29: 46296 | B29: 6698239.5 | C29: 3598656
A30: 46327 | B30: 10047359 | C30: 4565459.1
A31: 46357 | B31: 8558861.6 | C31: 3201192.5
A32: 2026年 | B32: =SUM(B20:B31) -> 74424883 | C32: =SUM(C20:C31) -> 32226770
A35: 销售
A36: 统计月份 | B36: 利润目标-总 | C36: 利润目标-自有供应链
A37: 46023 | B37: 21092500 | C37: 2048000
A38: 46054 | B38: 13422500 | C38: 1664000
A39: 46082 | B39: 19175000 | C39: 3712000
A40: 46113 | B40: 30680000 | C40: 8640000
A41: 46143 | B41: 32597500 | C41: 8160000
A42: 46174 | B42: 36432500 | C42: 9120000
A43: 46204 | B43: 34515000 | C43: 9600000
A44: 46235 | B44: 36432500 | C44: 9600000
A45: 46266 | B45: 36432500 | C45: 9600000
A46: 46296 | B46: 32597500 | C46: 10720000
A47: 46327 | B47: 49855000 | C47: 13600000
A48: 46357 | B48: 40267500 | C48: 9536000
A49: 2026年 | B49: =SUM(B37:B48) -> 383500000 | C49: =SUM(C37:C48) -> 96000000

Sheet 4. 实际达成与同比
B3: 25年实际销售 | X3: 25年实际利润
B4: 销售金额 | C4: 1月 | D4: 2月 | E4: 3月 | F4: 4月 | G4: 5月 | H4: 6月 | I4: 7月 | J4: 8月 | K4: 9月 | L4: 10月 | M4: 11月 | N4: 12月 | O4: 合计 | P4: H1 | Q4: H2 | R4: Q1 | S4: Q2 | T4: Q3 | U4: Q4 | X4: 利润金额 | Y4: 1月 | Z4: 2月 | AA4: 3月 | AB4: 4月 | AC4: 5月 | AD4: 6月 | AE4: 7月 | AF4: 8月 | AG4: 9月 | AH4: 10月 | AI4: 11月 | AJ4: 12月 | AK4: 合计 | AL4: H1 | AM4: H2 | AN4: Q1 | AO4: Q2 | AP4: Q3 | AQ4: Q4
B5: 存量整体 | C5: 1.102224e+08 | D5: 83609413 | E5: 86799137 | F5: 86919721 | G5: 85535277 | H5: 80433401 | I5: 82719754 | J5: 76924778 | K5: 85138541 | L5: 92473955 | M5: 91194584 | N5: 84507816 | O5: 1.0464788e+09 | P5: 5.3351935e+08 | Q5: 5.1295943e+08 | R5: 2.8063095e+08 | S5: 2.528884e+08 | T5: 2.4478307e+08 | U5: 2.6817636e+08 | X5: 存量整体 | Y5: 26183689 | Z5: 18907276 | AA5: 21181039 | AB5: 20419943 | AC5: 19028404 | AD5: 19346421 | AE5: 18855792 | AF5: 17898504 | AG5: 18162053 | AH5: 17715843 | AI5: 21853011 | AJ5: 22971148 | AK5: 2.4252312e+08 | AL5: 1.2506677e+08 | AM5: 1.1745635e+08 | AN5: 66272004 | AO5: 58794768 | AP5: 54916349 | AQ5: 62540002
A6: 26年口径 | B6: 仅电视端及APP业务 （含自营业务） | C6: 93066095 | D6: 68875967 | E6: 72664094 | F6: 71559512 | G6: 73159842 | H6: 66716190 | I6: 67862810 | J6: 62344970 | K6: 65620601 | L6: 67768060 | M6: 68448763 | N6: 67923619 | O6: 8.4601052e+08 | P6: 4.460417e+08 | Q6: 3.9996882e+08 | R6: 2.3460616e+08 | S6: 2.1143554e+08 | T6: 1.9582838e+08 | U6: 2.0414044e+08 | W6: 26年口径 | X6: 仅电视端及APP业务 （含自营业务） | Y6: 23060801 | Z6: 16413199 | AA6: 18356698 | AB6: 17233521 | AC6: 16710974 | AD6: 16492398 | AE6: 16251029 | AF6: 15186116 | AG6: 15548110 | AH6: 14978563 | AI6: 17678212 | AJ6: 19991942 | AK6: 2.0790156e+08 | AL6: 1.0826759e+08 | AM6: 99633973 | AN6: 57830698 | AO6: 50436894 | AP6: 46985256 | AQ6: 52648718
A7: 26年口径 | B7: 数据库营销 | C7: 11875837 | D7: 9505244.6 | E7: 8448582.2 | F7: 10411125 | G7: 7751860 | H7: 8753480.6 | I7: 9067021.2 | J7: 7495744.8 | K7: 13999988 | L7: 18029060 | M7: 16780507 | N7: 8632591.5 | O7: 1.3075104e+08 | P7: 56746130 | Q7: 74004912 | R7: 29829664 | S7: 26916466 | T7: 30562754 | U7: 43442158 | W7: 26年口径 | X7: 数据库营销 | Y7: 2549751.2 | Z7: 1880081.8 | AA7: 2130051.2 | AB7: 2615080.4 | AC7: 1752152.4 | AD7: 2225886 | AE7: 1876419.1 | AF7: 1908652.7 | AG7: 2008057.6 | AH7: 1945294.6 | AI7: 3494718 | AJ7: 2180017.1 | AK7: 26566162 | AL7: 13153003 | AM7: 13413159 | AN7: 6559884.2 | AO7: 6593118.8 | AP7: 5793129.4 | AQ7: 7620029.7
A8: 26年口径 | B8: 私域 | C8: 5280469.7 | D8: 5228202.1 | E8: 5686460.7 | F8: 4949084.3 | G8: 4623575.5 | H8: 4963729.5 | I8: 5789922.8 | J8: 7084063.3 | K8: 5517952.4 | L8: 6676835 | M8: 5965314.6 | N8: 7951606.3 | O8: 69717216 | P8: 30731522 | Q8: 38985694 | R8: 16195133 | S8: 14536389 | T8: 18391938 | U8: 20593756 | W8: 26年口径 | X8: 私域 | Y8: 573137.28 | Z8: 613994.73 | AA8: 694290.26 | AB8: 571341.18 | AC8: 565277.8 | AD8: 628136.96 | AE8: 728343.65 | AF8: 803735.23 | AG8: 605885.04 | AH8: 791985.12 | AI8: 680080.68 | AJ8: 799188.63 | AK8: 8055396.6 | AL8: 3646178.2 | AM8: 4409218.3 | AN8: 1881422.3 | AO8: 1764755.9 | AP8: 2137963.9 | AQ8: 2271254.4
B9: 电视及APP-电视商品（含自营业务） | C9: 91060796 | D9: 71242893 | E9: 72887479 | F9: 72173433 | G9: 69886466 | H9: 65714355 | I9: 68868780 | J9: 65116614 | K9: 71528972 | L9: 79916867 | M9: 73733516 | N9: 68166470 | O9: 8.7029664e+08 | P9: 4.4296542e+08 | Q9: 4.2733122e+08 | R9: 2.3519117e+08 | S9: 2.0777425e+08 | T9: 2.0551437e+08 | U9: 2.2181685e+08 | X9: 电视及APP-电视商品（含自营业务） | Y9: 23141348 | Z9: 16740906 | AA9: 18651063 | AB9: 18127100 | AC9: 17050642 | AD9: 17242451 | AE9: 17060422 | AF9: 16235447 | AG9: 16150202 | AH9: 15755887 | AI9: 19418912 | AJ9: 18386453 | AK9: 2.1396083e+08 | AL9: 1.1095351e+08 | AM9: 1.0300732e+08 | AN9: 58533318 | AO9: 52420192 | AP9: 49446071 | AQ9: 53561252
B10: 电视及APP-电商商品 | C10: 16752497 | D10: 10504730 | E10: 11604644 | F10: 12473111 | G10: 13588685 | H10: 12776572 | I10: 11834622 | J10: 9796971.8 | K10: 11622005 | L10: 10625909 | M10: 15294616 | N10: 14523050 | O10: 1.5139741e+08 | P10: 77700239 | Q10: 73697173 | R10: 38861871 | S10: 38838368 | T10: 33253598 | U10: 40443575 | X10: 电视及APP-电商商品 | Y10: 2769275.6 | Z10: 1936495.7 | AA10: 2247014.9 | AB10: 2050038.4 | AC10: 1739691.9 | AD10: 1876888.2 | AE10: 1558920 | AF10: 1430264.5 | AG10: 1787154.4 | AH10: 1736339.4 | AI10: 2199376.9 | AJ10: 4376535.8 | AK10: 25707996 | AL10: 12619405 | AM10: 13088591 | AN10: 6952786.2 | AO10: 5666618.5 | AP10: 4776338.9 | AQ10: 8312252.1
B15: 26年销售目标 | X15: 26年利润目标
B16: 销售金额 | C16: 1月 | D16: 2月 | E16: 3月 | F16: 4月 | G16: 5月 | H16: 6月 | I16: 7月 | J16: 8月 | K16: 9月 | L16: 10月 | M16: 11月 | N16: 12月 | O16: 合计 | P16: H1 | Q16: H2 | R16: Q1 | S16: Q2 | T16: Q3 | U16: Q4 | X16: 利润金额 | Y16: 1月 | Z16: 2月 | AA16: 3月 | AB16: 4月 | AC16: 5月 | AD16: 6月 | AE16: 7月 | AF16: 8月 | AG16: 9月 | AH16: 10月 | AI16: 11月 | AJ16: 12月 | AK16: 合计 | AL16: H1 | AM16: H2 | AN16: Q1 | AO16: Q2 | AP16: Q3 | AQ16: Q4
B17: 存量整体 | C17: 99061446 | D17: 71731576 | E17: 79220420 | F17: 81951908 | G17: 78847804 | H17: 75920356 | I17: 77009398 | J17: 73330395 | K17: 74938092 | L17: 77288871 | M17: 83121007 | N17: 79375529 | O17: 9.517968e+08 | P17: 4.8673351e+08 | Q17: 4.6506329e+08 | R17: 2.5001344e+08 | S17: 2.3672007e+08 | T17: 2.2527788e+08 | U17: 2.3978541e+08 | X17: 存量整体 | Y17: 23226681 | Z17: 16184643 | AA17: 18883028 | AB17: 18605316 | AC17: 17245454 | AD17: 17507669 | AE17: 17209969 | AF17: 16413118 | AG17: 16708599 | AH17: 16115526 | AI17: 19654694 | AJ17: 19852334 | AK17: 2.1760703e+08 | AL17: 1.1165279e+08 | AM17: 1.0595424e+08 | AN17: 58294352 | AO17: 53358439 | AP17: 50331686 | AQ17: 55622554
A18: 26年口径 | B18: 仅电视端及APP业务 （含自营业务） | C18: 78968729 | D18: 58442847 | E18: 61657160 | F18: 60719897 | G18: 62077814 | H18: 56610227 | I18: 57583160 | J18: 52901146 | K18: 55680594 | L18: 57502763 | M18: 58008239 | N18: 57929538 | O18: 7.1808211e+08 | P18: 3.7847667e+08 | Q18: 3.3960544e+08 | R18: 1.9906874e+08 | S18: 1.7940794e+08 | T18: 1.661649e+08 | U18: 1.7344054e+08 | W18: 26年口径 | X18: 仅电视端及APP业务 （含自营业务） | Y18: 19601681 | Z18: 13951219 | AA18: 15859315 | AB18: 14891718 | AC18: 14441552 | AD18: 14253253 | AE18: 14045318 | AF18: 13127913 | AG18: 13439765 | AH18: 12949109 | AI18: 15267218 | AJ18: 16278970 | AK18: 1.7810703e+08 | AL18: 92998738 | AM18: 85108292 | AN18: 49412216 | AO18: 43586523 | AP18: 40612995 | AQ18: 44495298
A19: 26年口径 | B19: 数据库营销 | C19: 13874286 | D19: 7789072.9 | E19: 10709975 | F19: 13630878 | G19: 9249524.1 | H19: 10953384 | I19: 9736341.1 | J19: 9736341.1 | K19: 11196792 | L19: 9249524.1 | M19: 16064963 | N19: 11683609 | O19: 1.3387469e+08 | P19: 66207120 | Q19: 67667571 | R19: 32373334 | S19: 33833785 | T19: 30669474 | U19: 36998096 | W19: 26年口径 | X19: 数据库营销 | Y19: 2850000 | Z19: 1600000 | AA19: 2200000 | AB19: 2800000 | AC19: 1900000 | AD19: 2250000 | AE19: 2000000 | AF19: 2000000 | AG19: 2300000 | AH19: 1900000 | AI19: 3300000 | AJ19: 2400000 | AK19: 27500000 | AL19: 13600000 | AM19: 13900000 | AN19: 6650000 | AO19: 6950000 | AP19: 6300000 | AQ19: 7600000
A20: 26年口径 | B20: 私域 | C20: 6218431.4 | D20: 5499656 | E20: 6853285 | F20: 7601133.4 | G20: 7520466.1 | H20: 8356745.5 | I20: 9689897.1 | J20: 10692908 | K20: 8060705.5 | L20: 10536584 | M20: 9047805.7 | N20: 9762382 | O20: 99840000 | P20: 42049717 | Q20: 57790283 | R20: 18571372 | S20: 23478345 | T20: 28443511 | U20: 29346772 | W20: 26年口径 | X20: 私域 | Y20: 775000 | Z20: 633423.97 | AA20: 823712.13 | AB20: 913597.76 | AC20: 903902.17 | AD20: 1004416.5 | AE20: 1164651.1 | AF20: 1285205.3 | AG20: 968834.8 | AH20: 1266416.4 | AI20: 1087476.6 | AJ20: 1173363.2 | AK20: 12000000 | AL20: 5054052.6 | AM20: 6945947.4 | AN20: 2232136.1 | AO20: 2821916.5 | AP20: 3418691.2 | AQ20: 3527256.3
B21: 电视及APP-电视商品（含自营业务） | C21: =Y21*1.12/0.275 -> 85136343 | D21: =Z21*1.12/0.275 -> 59324074 | E21: =AA21*1.12/0.275 -> 69214879 | F21: =AB21*1.12/0.275 -> 68196939 | G21: =AC21*1.12/0.275 -> 63212428 | H21: =AD21*1.12/0.275 -> 64173566 | I21: =AE21*1.12/0.275 -> 63082358 | J21: =AF21*1.12/0.275 -> 60161538 | ... N21: =AJ21*1.12/0.275 -> 72767827 | O21: =SUM(C21:N21) -> 7.9762868e+08 | P21: =SUM(C21:H21) -> 4.0925823e+08 | Q21: =SUM(I21:N21) -> 3.8837045e+08 | R21: =SUM(C21:E21) -> 2.136753e+08 | S21: =SUM(F21:H21) -> 1.9558293e+08 | T21: =SUM(I21:K21) -> 1.8448851e+08 | U21: =SUM(L21:N21) -> 2.0388194e+08 | X21: 电视及APP-电视商品（含自营业务） | Y21: 20904013 | Z21: 14566179 | AA21: 16994725 | AB21: 16744784 | AC21: 15520909 | AD21: 15756902 | AE21: 15488972 | AF21: 14771806 | AG21: 15037739 | AH21: 14503973 | AI21: 17689225 | AJ21: 17867100 | AK21: 1.9584633e+08 | AL21: 1.0048751e+08 | AM21: 95358816 | AN21: 52464916 | AO21: 48022595 | AP21: 45298517 | AQ21: 50060298
B22: 电视及APP-电商商品 | C22: =C17-C21 -> 13925104 | D22: =D17-D21 -> 12407501 | E22: =E17-E21 -> 10005541 | F22: =F17-F21 -> 13754968 | G22: =G17-G21 -> 15635375 | H22: =H17-H21 -> 11746790 | I22: =I17-I21 -> 13927040 | J22: =J17-J21 -> 13168857 | ... N22: =N17-N21 -> 6607702.3 | O22: =SUM(C22:N22) -> 1.5416812e+08 | P22: =SUM(C22:H22) -> 77475280 | Q22: =SUM(I22:N22) -> 76692842 | R22: =SUM(C22:E22) -> 36338146 | S22: =SUM(F22:H22) -> 41137134 | T22: =SUM(I22:K22) -> 40789377 | U22: =SUM(L22:N22) -> 35903465 | X22: 电视及APP-电商商品 | Y22: 2322668.1 | Z22: 1618464.3 | AA22: 1888302.8 | AB22: 1860531.6 | AC22: 1724545.4 | AD22: 1750766.9 | AE22: 1720996.9 | AF22: 1641311.8 | AG22: 1670859.9 | AH22: 1611552.6 | AI22: 1965469.4 | AJ22: 1985233.4 | AK22: 21760703 | AL22: 11165279 | AM22: 10595424 | AN22: 5829435.2 | AO22: 5335843.9 | AP22: 5033168.6 | AQ22: 5562255.4
B27: 26年销售实际 | X27: 26年利润实际
B28: 销售金额 | C28: 1月 | D28: 2月 | E28: 3月 | F28: 4月 | G28: 5月 | H28: 6月 | I28: 7月 | J28: 8月 | K28: 9月 | L28: 10月 | M28: 11月 | N28: 12月 | O28: 合计 | P28: H1 | Q28: H2 | R28: Q1 | S28: Q2 | T28: Q3 | U28: Q4 | X28: 利润金额 | Y28: 1月 | Z28: 2月 | AA28: 3月 | AB28: 4月 | AC28: 5月 | AD28: 6月 | AE28: 7月 | AF28: 8月 | AG28: 9月 | AH28: 10月 | AI28: 11月 | AJ28: 12月 | AK28: 合计 | AL28: H1 | AM28: H2 | AN28: Q1 | AO28: Q2 | AP28: Q3 | AQ28: Q4
B29: 存量整体 | C29: =SUM(C30:C32) -> 82505226 | D29: =SUM(D30:D32) -> 0 | E29: =SUM(E30:E32) -> 0 | F29: =SUM(F30:F32) -> 0 | G29: =SUM(G30:G32) -> 0 | H29: =SUM(H30:H32) -> 0 | I29: =SUM(I30:I32) -> 0 | J29: =SUM(J30:J32) -> 0 | ... N29: =SUM(N30:N32) -> 0 | O29: =SUM(C29:N29) -> 82505226 | P29: =SUM(C29:H29) -> 82505226 | Q29: =SUM(I29:N29) -> 0 | R29: =SUM(C29:E29) -> 82505226 | S29: =SUM(F29:H29) -> 0 | T29: =SUM(I29:K29) -> 0 | U29: =SUM(L29:N29) -> 0 | X29: 存量整体 | Y29: =SUM(Y30:Y32) -> 20488757 | Z29: =SUM(Z30:Z32) -> 0 | AA29: =SUM(AA30:AA32) -> 0 | AB29: =SUM(AB30:AB32) -> 0 | AC29: =SUM(AC30:AC32) -> 0 | AD29: =SUM(AD30:AD32) -> 0 | AE29: =SUM(AE30:AE32) -> 0 | AF29: =SUM(AF30:AF32) -> 0 | ... AJ29: =SUM(AJ30:AJ32) -> 0 | AK29: =SUM(Y29:AJ29) -> 20488757 | AL29: =SUM(Y29:AD29) -> 20488757 | AM29: =SUM(AE29:AJ29) -> 0 | AN29: =SUM(Y29:AA29) -> 20488757 | AO29: =SUM(AB29:AD29) -> 0 | AP29: =SUM(AE29:AG29) -> 0 | AQ29: =SUM(AH29:AJ29) -> 0
A30: 26年口径 | B30: 仅电视端及APP业务 （含自营业务） | C30: =C35+C36-C31-C38 -> 64087736 | D30: =D35+D36-D31-D38 -> 0 | E30: =E35+E36-E31-E38 -> 0 | F30: =F35+F36-F31-F38 -> 0 | G30: =G35+G36-G31-G38 -> 0 | H30: =H35+H36-H31-H38 -> 0 | I30: =I35+I36-I31-I38 -> 0 | J30: =J35+J36-J31-J38 -> 0 | ... N30: =N35+N36-N31-N38 -> 0 | O30: =SUM(C30:N30) -> 64087736 | P30: =SUM(C30:H30) -> 64087736 | Q30: =SUM(I30:N30) -> 0 | R30: =SUM(C30:E30) -> 64087736 | S30: =SUM(F30:H30) -> 0 | T30: =SUM(I30:K30) -> 0 | U30: =SUM(L30:N30) -> 0 | W30: 26年口径 | X30: 仅电视端及APP业务 （含自营业务） | Y30: =Y35+Y36-Y31-Y38 -> 16774409 | Z30: =Z35+Z36-Z31-Z38 -> 0 | AA30: =AA35+AA36-AA31-AA38 -> 0 | AB30: =AB35+AB36-AB31-AB38 -> 0 | AC30: =AC35+AC36-AC31-AC38 -> 0 | AD30: =AD35+AD36-AD31-AD38 -> 0 | AE30: =AE35+AE36-AE31-AE38 -> 0 | AF30: =AF35+AF36-AF31-AF38 -> 0 | ... AJ30: =AJ35+AJ36-AJ31-AJ38 -> 0 | AK30: =SUM(Y30:AJ30) -> 16774409 | AL30: =SUM(Y30:AD30) -> 16774409 | AM30: =SUM(AE30:AJ30) -> 0 | AN30: =SUM(Y30:AA30) -> 16774409 | AO30: =SUM(AB30:AD30) -> 0 | AP30: =SUM(AE30:AG30) -> 0 | AQ30: =SUM(AH30:AJ30) -> 0
A31: 26年口径 | B31: 数据库营销 | C31: 11219452 | O31: =SUM(C31:N31) -> 11219452 | P31: =SUM(C31:H31) -> 11219452 | Q31: =SUM(I31:N31) -> 0 | R31: =SUM(C31:E31) -> 11219452 | S31: =SUM(F31:H31) -> 0 | T31: =SUM(I31:K31) -> 0 | U31: =SUM(L31:N31) -> 0 | W31: 26年口径 | X31: 数据库营销 | Y31: 2901472 | AK31: =SUM(Y31:AJ31) -> 2901472 | AL31: =SUM(Y31:AD31) -> 2901472 | AM31: =SUM(AE31:AJ31) -> 0 | AN31: =SUM(Y31:AA31) -> 2901472 | AO31: =SUM(AB31:AD31) -> 0 | AP31: =SUM(AE31:AG31) -> 0 | AQ31: =SUM(AH31:AJ31) -> 0
A32: 26年口径 | B32: 私域 | C32: =C37+C38 -> 7198038.3 | D32: =D37+D38 -> 0 | E32: =E37+E38 -> 0 | F32: =F37+F38 -> 0 | G32: =G37+G38 -> 0 | H32: =H37+H38 -> 0 | I32: =I37+I38 -> 0 | J32: =J37+J38 -> 0 | ... N32: =N37+N38 -> 0 | O32: =SUM(C32:N32) -> 7198038.3 | P32: =SUM(C32:H32) -> 7198038.3 | Q32: =SUM(I32:N32) -> 0 | R32: =SUM(C32:E32) -> 7198038.3 | S32: =SUM(F32:H32) -> 0 | T32: =SUM(I32:K32) -> 0 | U32: =SUM(L32:N32) -> 0 | W32: 26年口径 | X32: 私域 | Y32: =Y37+Y38 -> 812875.4 | Z32: =Z37+Z38 -> 0 | AA32: =AA37+AA38 -> 0 | AB32: =AB37+AB38 -> 0 | AC32: =AC37+AC38 -> 0 | AD32: =AD37+AD38 -> 0 | AE32: =AE37+AE38 -> 0 | AF32: =AF37+AF38 -> 0 | ... AJ32: =AJ37+AJ38 -> 0 | AK32: =SUM(Y32:AJ32) -> 812875.4 | AL32: =SUM(Y32:AD32) -> 812875.4 | AM32: =SUM(AE32:AJ32) -> 0 | AN32: =SUM(Y32:AA32) -> 812875.4 | AO32: =SUM(AB32:AD32) -> 0 | AP32: =SUM(AE32:AG32) -> 0 | AQ32: =SUM(AH32:AJ32) -> 0
B33: 电视及APP-电视商品（含自营业务） | C33: =C36+C39 -> 70175174 | D33: =D36+D39 -> 0 | E33: =E36+E39 -> 0 | F33: =F36+F39 -> 0 | G33: =G36+G39 -> 0 | H33: =H36+H39 -> 0 | I33: =I36+I39 -> 0 | J33: =J36+J39 -> 0 | ... N33: =N36+N39 -> 0 | O33: =SUM(C33:N33) -> 70175174 | P33: =SUM(C33:H33) -> 70175174 | Q33: =SUM(I33:N33) -> 0 | R33: =SUM(C33:E33) -> 70175174 | S33: =SUM(F33:H33) -> 0 | T33: =SUM(I33:K33) -> 0 | U33: =SUM(L33:N33) -> 0 | X33: 电视及APP-电视商品（含自营业务） | Y33: =Y36+Y39 -> 18599164 | Z33: =Z36+Z39 -> 0 | AA33: =AA36+AA39 -> 0 | AB33: =AB36+AB39 -> 0 | AC33: =AC36+AC39 -> 0 | AD33: =AD36+AD39 -> 0 | AE33: =AE36+AE39 -> 0 | AF33: =AF36+AF39 -> 0 | ... AJ33: =AJ36+AJ39 -> 0 | AK33: =SUM(Y33:AJ33) -> 18599164 | AL33: =SUM(Y33:AD33) -> 18599164 | AM33: =SUM(AE33:AJ33) -> 0 | AN33: =SUM(Y33:AA33) -> 18599164 | AO33: =SUM(AB33:AD33) -> 0 | AP33: =SUM(AE33:AG33) -> 0 | AQ33: =SUM(AH33:AJ33) -> 0
B34: 电视及APP-电商商品 | C34: 10410390 | O34: =SUM(C34:N34) -> 10410390 | P34: =SUM(C34:H34) -> 10410390 | Q34: =SUM(I34:N34) -> 0 | R34: =SUM(C34:E34) -> 10410390 | S34: =SUM(F34:H34) -> 0 | T34: =SUM(I34:K34) -> 0 | U34: =SUM(L34:N34) -> 0 | X34: 电视及APP-电商商品 | Y34: 1666302.9 | AK34: =SUM(Y34:AJ34) -> 1666302.9 | AL34: =SUM(Y34:AD34) -> 1666302.9 | AM34: =SUM(AE34:AJ34) -> 0 | AN34: =SUM(Y34:AA34) -> 1666302.9 | AO34: =SUM(AB34:AD34) -> 0 | AP34: =SUM(AE34:AG34) -> 0 | AQ34: =SUM(AH34:AJ34) -> 0
B35: P1 | C35: 78894668 | O35: =SUM(C35:N35) -> 78894668 | P35: =SUM(C35:H35) -> 78894668 | Q35: =SUM(I35:N35) -> 0 | R35: =SUM(C35:E35) -> 78894668 | S35: =SUM(F35:H35) -> 0 | T35: =SUM(I35:K35) -> 0 | U35: =SUM(L35:N35) -> 0 | X35: P1 | Y35: 20094261 | AK35: =SUM(Y35:AJ35) -> 20094261 | AL35: =SUM(Y35:AD35) -> 20094261 | AM35: =SUM(AE35:AJ35) -> 0 | AN35: =SUM(Y35:AA35) -> 20094261 | AO35: =SUM(AB35:AD35) -> 0 | AP35: =SUM(AE35:AG35) -> 0 | AQ35: =SUM(AH35:AJ35) -> 0
B36: 自营业务 | C36: 1690897 | O36: =SUM(C36:N36) -> 1690897 | P36: =SUM(C36:H36) -> 1690897 | Q36: =SUM(I36:N36) -> 0 | R36: =SUM(C36:E36) -> 1690897 | S36: =SUM(F36:H36) -> 0 | T36: =SUM(I36:K36) -> 0 | U36: =SUM(L36:N36) -> 0 | X36: 自营业务 | Y36: 171206.6 | AK36: =SUM(Y36:AJ36) -> 171206.6 | AL36: =SUM(Y36:AD36) -> 171206.6 | AM36: =SUM(AE36:AJ36) -> 0 | AN36: =SUM(Y36:AA36) -> 171206.6 | AO36: =SUM(AB36:AD36) -> 0 | AP36: =SUM(AE36:AG36) -> 0 | AQ36: =SUM(AH36:AJ36) -> 0
B37: 私域-第三方 | C37: 1919660.5 | O37: =SUM(C37:N37) -> 1919660.5 | P37: =SUM(C37:H37) -> 1919660.5 | Q37: =SUM(I37:N37) -> 0 | R37: =SUM(C37:E37) -> 1919660.5 | S37: =SUM(F37:H37) -> 0 | T37: =SUM(I37:K37) -> 0 | U37: =SUM(L37:N37) -> 0 | X37: 私域-第三方 | Y37: 223289.28 | AK37: =SUM(Y37:AJ37) -> 223289.28 | AL37: =SUM(Y37:AD37) -> 223289.28 | AM37: =SUM(AE37:AJ37) -> 0 | AN37: =SUM(Y37:AA37) -> 223289.28 | AO37: =SUM(AB37:AD37) -> 0 | AP37: =SUM(AE37:AG37) -> 0 | AQ37: =SUM(AH37:AJ37) -> 0
B38: 私域-东购 | C38: 5278377.8 | O38: =SUM(C38:N38) -> 5278377.8 | P38: =SUM(C38:H38) -> 5278377.8 | Q38: =SUM(I38:N38) -> 0 | R38: =SUM(C38:E38) -> 5278377.8 | S38: =SUM(F38:H38) -> 0 | T38: =SUM(I38:K38) -> 0 | U38: =SUM(L38:N38) -> 0 | X38: 私域-东购 | Y38: 589586.12 | AK38: =SUM(Y38:AJ38) -> 589586.12 | AL38: =SUM(Y38:AD38) -> 589586.12 | AM38: =SUM(AE38:AJ38) -> 0 | AN38: =SUM(Y38:AA38) -> 589586.12 | AO38: =SUM(AB38:AD38) -> 0 | AP38: =SUM(AE38:AG38) -> 0 | AQ38: =SUM(AH38:AJ38) -> 0
B39: ERP电视商品（不含自营业务） | C39: 68484277 | O39: =SUM(C39:N39) -> 68484277 | P39: =SUM(C39:H39) -> 68484277 | Q39: =SUM(I39:N39) -> 0 | R39: =SUM(C39:E39) -> 68484277 | S39: =SUM(F39:H39) -> 0 | T39: =SUM(I39:K39) -> 0 | U39: =SUM(L39:N39) -> 0 | X39: ERP电视商品（不含自营业务） | Y39: 18427958 | AK39: =SUM(Y39:AJ39) -> 18427958 | AL39: =SUM(Y39:AD39) -> 18427958 | AM39: =SUM(AE39:AJ39) -> 0 | AN39: =SUM(Y39:AA39) -> 18427958 | AO39: =SUM(AB39:AD39) -> 0 | AP39: =SUM(AE39:AG39) -> 0 | AQ39: =SUM(AH39:AJ39) -> 0
B44: 26年销售达成率 | X44: 26年利润达成率
B45: 销售金额 | C45: 1月 | D45: 2月 | E45: 3月 | F45: 4月 | G45: 5月 | H45: 6月 | I45: 7月 | J45: 8月 | K45: 9月 | L45: 10月 | M45: 11月 | N45: 12月 | O45: 合计 | P45: H1 | Q45: H2 | R45: Q1 | S45: Q2 | T45: Q3 | U45: Q4 | X45: 利润金额 | Y45: 1月 | Z45: 2月 | AA45: 3月 | AB45: 4月 | AC45: 5月 | AD45: 6月 | AE45: 7月 | AF45: 8月 | AG45: 9月 | AH45: 10月 | AI45: 11月 | AJ45: 12月 | AK45: 合计 | AL45: H1 | AM45: H2 | AN45: Q1 | AO45: Q2 | AP45: Q3 | AQ45: Q4
B46: 存量整体 | C46: =IFERROR(C29/C17,"") -> 0.83286918 | D46: =IFERROR(D29/D17,"") -> 0 | E46: =IFERROR(E29/E17,"") -> 0 | F46: =IFERROR(F29/F17,"") -> 0 | G46: =IFERROR(G29/G17,"") -> 0 | H46: =IFERROR(H29/H17,"") -> 0 | I46: =IFERROR(I29/I17,"") -> 0 | J46: =IFERROR(J29/J17,"") -> 0 | ... U46: =IFERROR(U29/U17,"") -> 0 | X46: 存量整体 | Y46: =IFERROR(Y29/Y17,"") -> 0.8821216 | Z46: =IFERROR(Z29/Z17,"") -> 0 | AA46: =IFERROR(AA29/AA17,"") -> 0 | AB46: =IFERROR(AB29/AB17,"") -> 0 | AC46: =IFERROR(AC29/AC17,"") -> 0 | AD46: =IFERROR(AD29/AD17,"") -> 0 | AE46: =IFERROR(AE29/AE17,"") -> 0 | AF46: =IFERROR(AF29/AF17,"") -> 0 | ... AQ46: =IFERROR(AQ29/AQ17,"") -> 0
A47: 26年口径 | B47: 仅电视端及APP业务 （含自营业务） | C47: =IFERROR(C30/C18,"") -> 0.8115584 | D47: =IFERROR(D30/D18,"") -> 0 | E47: =IFERROR(E30/E18,"") -> 0 | F47: =IFERROR(F30/F18,"") -> 0 | G47: =IFERROR(G30/G18,"") -> 0 | H47: =IFERROR(H30/H18,"") -> 0 | I47: =IFERROR(I30/I18,"") -> 0 | J47: =IFERROR(J30/J18,"") -> 0 | ... U47: =IFERROR(U30/U18,"") -> 0 | W47: 26年口径 | X47: 仅电视端及APP业务 （含自营业务） | Y47: =IFERROR(Y30/Y18,"") -> 0.85576383 | Z47: =IFERROR(Z30/Z18,"") -> 0 | AA47: =IFERROR(AA30/AA18,"") -> 0 | AB47: =IFERROR(AB30/AB18,"") -> 0 | AC47: =IFERROR(AC30/AC18,"") -> 0 | AD47: =IFERROR(AD30/AD18,"") -> 0 | AE47: =IFERROR(AE30/AE18,"") -> 0 | AF47: =IFERROR(AF30/AF18,"") -> 0 | ... AQ47: =IFERROR(AQ30/AQ18,"") -> 0
A48: 26年口径 | B48: 数据库营销 | C48: =IFERROR(C31/C19,"") -> 0.80865074 | D48: =IFERROR(D31/D19,"") -> 0 | E48: =IFERROR(E31/E19,"") -> 0 | F48: =IFERROR(F31/F19,"") -> 0 | G48: =IFERROR(G31/G19,"") -> 0 | H48: =IFERROR(H31/H19,"") -> 0 | I48: =IFERROR(I31/I19,"") -> 0 | J48: =IFERROR(J31/J19,"") -> 0 | ... U48: =IFERROR(U31/U19,"") -> 0 | W48: 26年口径 | X48: 数据库营销 | Y48: =IFERROR(Y31/Y19,"") -> 1.0180604 | Z48: =IFERROR(Z31/Z19,"") -> 0 | AA48: =IFERROR(AA31/AA19,"") -> 0 | AB48: =IFERROR(AB31/AB19,"") -> 0 | AC48: =IFERROR(AC31/AC19,"") -> 0 | AD48: =IFERROR(AD31/AD19,"") -> 0 | AE48: =IFERROR(AE31/AE19,"") -> 0 | AF48: =IFERROR(AF31/AF19,"") -> 0 | ... AQ48: =IFERROR(AQ31/AQ19,"") -> 0
A49: 26年口径 | B49: 私域 | C49: =IFERROR(C32/C20,"") -> 1.1575328 | D49: =IFERROR(D32/D20,"") -> 0 | E49: =IFERROR(E32/E20,"") -> 0 | F49: =IFERROR(F32/F20,"") -> 0 | G49: =IFERROR(G32/G20,"") -> 0 | H49: =IFERROR(H32/H20,"") -> 0 | I49: =IFERROR(I32/I20,"") -> 0 | J49: =IFERROR(J32/J20,"") -> 0 | ... U49: =IFERROR(U32/U20,"") -> 0 | W49: 26年口径 | X49: 私域 | Y49: =IFERROR(Y32/Y20,"") -> 1.0488715 | Z49: =IFERROR(Z32/Z20,"") -> 0 | AA49: =IFERROR(AA32/AA20,"") -> 0 | AB49: =IFERROR(AB32/AB20,"") -> 0 | AC49: =IFERROR(AC32/AC20,"") -> 0 | AD49: =IFERROR(AD32/AD20,"") -> 0 | AE49: =IFERROR(AE32/AE20,"") -> 0 | AF49: =IFERROR(AF32/AF20,"") -> 0 | ... AQ49: =IFERROR(AQ32/AQ20,"") -> 0
B50: 电视及APP-电视商品（含自营业务） | C50: =IFERROR(C33/C21,"") -> 0.82426813 | D50: =IFERROR(D33/D21,"") -> 0 | E50: =IFERROR(E33/E21,"") -> 0 | F50: =IFERROR(F33/F21,"") -> 0 | G50: =IFERROR(G33/G21,"") -> 0 | H50: =IFERROR(H33/H21,"") -> 0 | I50: =IFERROR(I33/I21,"") -> 0 | J50: =IFERROR(J33/J21,"") -> 0 | ... U50: =IFERROR(U33/U21,"") -> 0 | X50: 电视及APP-电视商品（含自营业务） | Y50: =IFERROR(Y33/Y21,"") -> 0.88974133 | Z50: =IFERROR(Z33/Z21,"") -> 0 | AA50: =IFERROR(AA33/AA21,"") -> 0 | AB50: =IFERROR(AB33/AB21,"") -> 0 | AC50: =IFERROR(AC33/AC21,"") -> 0 | AD50: =IFERROR(AD33/AD21,"") -> 0 | AE50: =IFERROR(AE33/AE21,"") -> 0 | AF50: =IFERROR(AF33/AF21,"") -> 0 | ... AQ50: =IFERROR(AQ33/AQ21,"") -> 0
B51: 电视及APP-电商商品 | C51: =IFERROR(C34/C22,"") -> 0.74759877 | D51: =IFERROR(D34/D22,"") -> 0 | E51: =IFERROR(E34/E22,"") -> 0 | F51: =IFERROR(F34/F22,"") -> 0 | G51: =IFERROR(G34/G22,"") -> 0 | H51: =IFERROR(H34/H22,"") -> 0 | I51: =IFERROR(I34/I22,"") -> 0 | J51: =IFERROR(J34/J22,"") -> 0 | ... U51: =IFERROR(U34/U22,"") -> 0 | X51: 电视及APP-电商商品 | Y51: =IFERROR(Y34/Y22,"") -> 0.71740896 | Z51: =IFERROR(Z34/Z22,"") -> 0 | AA51: =IFERROR(AA34/AA22,"") -> 0 | AB51: =IFERROR(AB34/AB22,"") -> 0 | AC51: =IFERROR(AC34/AC22,"") -> 0 | AD51: =IFERROR(AD34/AD22,"") -> 0 | AE51: =IFERROR(AE34/AE22,"") -> 0 | AF51: =IFERROR(AF34/AF22,"") -> 0 | ... AQ51: =IFERROR(AQ34/AQ22,"") -> 0
B56: 26年销售同比 | X56: 26年利润同比
B57: 销售金额 | C57: 1月 | D57: 2月 | E57: 3月 | F57: 4月 | G57: 5月 | H57: 6月 | I57: 7月 | J57: 8月 | K57: 9月 | L57: 10月 | M57: 11月 | N57: 12月 | O57: 合计 | P57: H1 | Q57: H2 | R57: Q1 | S57: Q2 | T57: Q3 | U57: Q4 | X57: 利润金额 | Y57: 1月 | Z57: 2月 | AA57: 3月 | AB57: 4月 | AC57: 5月 | AD57: 6月 | AE57: 7月 | AF57: 8月 | AG57: 9月 | AH57: 10月 | AI57: 11月 | AJ57: 12月 | AK57: 合计 | AL57: H1 | AM57: H2 | AN57: Q1 | AO57: Q2 | AP57: Q3 | AQ57: Q4
B58: 存量整体 | C58: =IFERROR(C29/C5-1,"") -> -0.25146591 | D58: =IFERROR(D29/D5-1,"") -> -1 | E58: =IFERROR(E29/E5-1,"") -> -1 | F58: =IFERROR(F29/F5-1,"") -> -1 | G58: =IFERROR(G29/G5-1,"") -> -1 | H58: =IFERROR(H29/H5-1,"") -> -1 | I58: =IFERROR(I29/I5-1,"") -> -1 | J58: =IFERROR(J29/J5-1,"") -> -1 | ... U58: =IFERROR(U29/U5-1,"") -> -1 | X58: 存量整体 | Y58: =IFERROR(Y29/Y5-1,"") -> -0.21749924 | Z58: =IFERROR(Z29/Z5-1,"") -> -1 | AA58: =IFERROR(AA29/AA5-1,"") -> -1 | AB58: =IFERROR(AB29/AB5-1,"") -> -1 | AC58: =IFERROR(AC29/AC5-1,"") -> -1 | AD58: =IFERROR(AD29/AD5-1,"") -> -1 | AE58: =IFERROR(AE29/AE5-1,"") -> -1 | AF58: =IFERROR(AF29/AF5-1,"") -> -1 | ... AQ58: =IFERROR(AQ29/AQ5-1,"") -> -1
A59: 26年口径 | B59: 仅电视端及APP业务 （含自营业务） | C59: =IFERROR(C30/C6-1,"") -> -0.31137397 | D59: =IFERROR(D30/D6-1,"") -> -1 | E59: =IFERROR(E30/E6-1,"") -> -1 | F59: =IFERROR(F30/F6-1,"") -> -1 | G59: =IFERROR(G30/G6-1,"") -> -1 | H59: =IFERROR(H30/H6-1,"") -> -1 | I59: =IFERROR(I30/I6-1,"") -> -1 | J59: =IFERROR(J30/J6-1,"") -> -1 | ... U59: =IFERROR(U30/U6-1,"") -> -1 | W59: 26年口径 | X59: 仅电视端及APP业务 （含自营业务） | Y59: =IFERROR(Y30/Y6-1,"") -> -0.27260074 | Z59: =IFERROR(Z30/Z6-1,"") -> -1 | AA59: =IFERROR(AA30/AA6-1,"") -> -1 | AB59: =IFERROR(AB30/AB6-1,"") -> -1 | AC59: =IFERROR(AC30/AC6-1,"") -> -1 | AD59: =IFERROR(AD30/AD6-1,"") -> -1 | AE59: =IFERROR(AE30/AE6-1,"") -> -1 | AF59: =IFERROR(AF30/AF6-1,"") -> -1 | ... AQ59: =IFERROR(AQ30/AQ6-1,"") -> -1
A60: 26年口径 | B60: 数据库营销 | C60: =IFERROR(C31/C7-1,"") -> -0.055270688 | D60: =IFERROR(D31/D7-1,"") -> -1 | E60: =IFERROR(E31/E7-1,"") -> -1 | F60: =IFERROR(F31/F7-1,"") -> -1 | G60: =IFERROR(G31/G7-1,"") -> -1 | H60: =IFERROR(H31/H7-1,"") -> -1 | I60: =IFERROR(I31/I7-1,"") -> -1 | J60: =IFERROR(J31/J7-1,"") -> -1 | ... U60: =IFERROR(U31/U7-1,"") -> -1 | W60: 26年口径 | X60: 数据库营销 | Y60: =IFERROR(Y31/Y7-1,"") -> 0.13794318 | Z60: =IFERROR(Z31/Z7-1,"") -> -1 | AA60: =IFERROR(AA31/AA7-1,"") -> -1 | AB60: =IFERROR(AB31/AB7-1,"") -> -1 | AC60: =IFERROR(AC31/AC7-1,"") -> -1 | AD60: =IFERROR(AD31/AD7-1,"") -> -1 | AE60: =IFERROR(AE31/AE7-1,"") -> -1 | AF60: =IFERROR(AF31/AF7-1,"") -> -1 | ... AQ60: =IFERROR(AQ31/AQ7-1,"") -> -1
A61: 26年口径 | B61: 私域 | C61: =IFERROR(C32/C8-1,"") -> 0.36314358 | D61: =IFERROR(D32/D8-1,"") -> -1 | E61: =IFERROR(E32/E8-1,"") -> -1 | F61: =IFERROR(F32/F8-1,"") -> -1 | G61: =IFERROR(G32/G8-1,"") -> -1 | H61: =IFERROR(H32/H8-1,"") -> -1 | I61: =IFERROR(I32/I8-1,"") -> -1 | J61: =IFERROR(J32/J8-1,"") -> -1 | ... U61: =IFERROR(U32/U8-1,"") -> -1 | W61: 26年口径 | X61: 私域 | Y61: =IFERROR(Y32/Y8-1,"") -> 0.41829092 | Z61: =IFERROR(Z32/Z8-1,"") -> -1 | AA61: =IFERROR(AA32/AA8-1,"") -> -1 | AB61: =IFERROR(AB32/AB8-1,"") -> -1 | AC61: =IFERROR(AC32/AC8-1,"") -> -1 | AD61: =IFERROR(AD32/AD8-1,"") -> -1 | AE61: =IFERROR(AE32/AE8-1,"") -> -1 | AF61: =IFERROR(AF32/AF8-1,"") -> -1 | ... AQ61: =IFERROR(AQ32/AQ8-1,"") -> -1
B62: 电视及APP-电视商品（含自营业务） | C62: =IFERROR(C33/C9-1,"") -> -0.22935909 | D62: =IFERROR(D33/D9-1,"") -> -1 | E62: =IFERROR(E33/E9-1,"") -> -1 | F62: =IFERROR(F33/F9-1,"") -> -1 | G62: =IFERROR(G33/G9-1,"") -> -1 | H62: =IFERROR(H33/H9-1,"") -> -1 | I62: =IFERROR(I33/I9-1,"") -> -1 | J62: =IFERROR(J33/J9-1,"") -> -1 | ... U62: =IFERROR(U33/U9-1,"") -> -1 | X62: 电视及APP-电视商品（含自营业务） | Y62: =IFERROR(Y33/Y9-1,"") -> -0.19628002 | Z62: =IFERROR(Z33/Z9-1,"") -> -1 | AA62: =IFERROR(AA33/AA9-1,"") -> -1 | AB62: =IFERROR(AB33/AB9-1,"") -> -1 | AC62: =IFERROR(AC33/AC9-1,"") -> -1 | AD62: =IFERROR(AD33/AD9-1,"") -> -1 | AE62: =IFERROR(AE33/AE9-1,"") -> -1 | AF62: =IFERROR(AF33/AF9-1,"") -> -1 | ... AQ62: =IFERROR(AQ33/AQ9-1,"") -> -1
B63: 电视及APP-电商商品 | C63: =IFERROR(C34/C10-1,"") -> -0.3785768 | D63: =IFERROR(D34/D10-1,"") -> -1 | E63: =IFERROR(E34/E10-1,"") -> -1 | F63: =IFERROR(F34/F10-1,"") -> -1 | G63: =IFERROR(G34/G10-1,"") -> -1 | H63: =IFERROR(H34/H10-1,"") -> -1 | I63: =IFERROR(I34/I10-1,"") -> -1 | J63: =IFERROR(J34/J10-1,"") -> -1 | ... U63: =IFERROR(U34/U10-1,"") -> -1 | X63: 电视及APP-电商商品 | Y63: =IFERROR(Y34/Y10-1,"") -> -0.39828925 | Z63: =IFERROR(Z34/Z10-1,"") -> -1 | AA63: =IFERROR(AA34/AA10-1,"") -> -1 | AB63: =IFERROR(AB34/AB10-1,"") -> -1 | AC63: =IFERROR(AC34/AC10-1,"") -> -1 | AD63: =IFERROR(AD34/AD10-1,"") -> -1 | AE63: =IFERROR(AE34/AE10-1,"") -> -1 | AF63: =IFERROR(AF34/AF10-1,"") -> -1 | ... AQ63: =IFERROR(AQ34/AQ10-1,"") -> -1

Sheet 年初目标及同比
B3: 25年实际销售 | X3: 25年实际利润
B4: 销售金额 | C4: 1月 | D4: 2月 | E4: 3月 | F4: 4月 | G4: 5月 | H4: 6月 | I4: 7月 | J4: 8月 | K4: 9月 | L4: 10月 | M4: 11月 | N4: 12月 | O4: 合计 | P4: H1 | Q4: H2 | R4: Q1 | S4: Q2 | T4: Q3 | U4: Q4 | X4: 利润金额 | Y4: 1月 | Z4: 2月 | AA4: 3月 | AB4: 4月 | AC4: 5月 | AD4: 6月 | AE4: 7月 | AF4: 8月 | AG4: 9月 | AH4: 10月 | AI4: 11月 | AJ4: 12月 | AK4: 合计 | AL4: H1 | AM4: H2 | AN4: Q1 | AO4: Q2 | AP4: Q3 | AQ4: Q4
B5: 存量整体 | C5: 1.102224e+08 | D5: 83609413 | E5: 86799137 | F5: 86919721 | G5: 85535277 | H5: 80433401 | I5: 82719754 | J5: 76924778 | K5: 85138541 | L5: 92473955 | M5: 91194584 | N5: 84507816 | O5: 1.0464788e+09 | P5: 5.3351935e+08 | Q5: 5.1295943e+08 | R5: 2.8063095e+08 | S5: 2.528884e+08 | T5: 2.4478307e+08 | U5: 2.6817636e+08 | X5: 存量整体 | Y5: 26183689 | Z5: 18907276 | AA5: 21181039 | AB5: 20419943 | AC5: 19028404 | AD5: 19346421 | AE5: 18855792 | AF5: 17898504 | AG5: 18162053 | AH5: 17715843 | AI5: 21853011 | AJ5: 22971148 | AK5: 2.4252312e+08 | AL5: 1.2506677e+08 | AM5: 1.1745635e+08 | AN5: 66272004 | AO5: 58794768 | AP5: 54916349 | AQ5: 62540002
A6: 26年口径 | B6: 仅电视端及APP业务 （含自营业务） | C6: 93066095 | D6: 68875967 | E6: 72664094 | F6: 71559512 | G6: 73159842 | H6: 66716190 | I6: 67862810 | J6: 62344970 | K6: 65620601 | L6: 67768060 | M6: 68448763 | N6: 67923619 | O6: 8.4601052e+08 | P6: 4.460417e+08 | Q6: 3.9996882e+08 | R6: 2.3460616e+08 | S6: 2.1143554e+08 | T6: 1.9582838e+08 | U6: 2.0414044e+08 | W6: 26年口径 | X6: 仅电视端及APP业务 （含自营业务） | Y6: 23060801 | Z6: 16413199 | AA6: 18356698 | AB6: 17233521 | AC6: 16710974 | AD6: 16492398 | AE6: 16251029 | AF6: 15186116 | AG6: 15548110 | AH6: 14978563 | AI6: 17678212 | AJ6: 19991942 | AK6: 2.0790156e+08 | AL6: 1.0826759e+08 | AM6: 99633973 | AN6: 57830698 | AO6: 50436894 | AP6: 46985256 | AQ6: 52648718
A7: 26年口径 | B7: 数据库营销 | C7: 11875837 | D7: 9505244.6 | E7: 8448582.2 | F7: 10411125 | G7: 7751860 | H7: 8753480.6 | I7: 9067021.2 | J7: 7495744.8 | K7: 13999988 | L7: 18029060 | M7: 16780507 | N7: 8632591.5 | O7: 1.3075104e+08 | P7: 56746130 | Q7: 74004912 | R7: 29829664 | S7: 26916466 | T7: 30562754 | U7: 43442158 | W7: 26年口径 | X7: 数据库营销 | Y7: 2549751.2 | Z7: 1880081.8 | AA7: 2130051.2 | AB7: 2615080.4 | AC7: 1752152.4 | AD7: 2225886 | AE7: 1876419.1 | AF7: 1908652.7 | AG7: 2008057.6 | AH7: 1945294.6 | AI7: 3494718 | AJ7: 2180017.1 | AK7: 26566162 | AL7: 13153003 | AM7: 13413159 | AN7: 6559884.2 | AO7: 6593118.8 | AP7: 5793129.4 | AQ7: 7620029.7
A8: 26年口径 | B8: 私域 | C8: 5280469.7 | D8: 5228202.1 | E8: 5686460.7 | F8: 4949084.3 | G8: 4623575.5 | H8: 4963729.5 | I8: 5789922.8 | J8: 7084063.3 | K8: 5517952.4 | L8: 6676835 | M8: 5965314.6 | N8: 7951606.3 | O8: 69717216 | P8: 30731522 | Q8: 38985694 | R8: 16195133 | S8: 14536389 | T8: 18391938 | U8: 20593756 | W8: 26年口径 | X8: 私域 | Y8: 573137.28 | Z8: 613994.73 | AA8: 694290.26 | AB8: 571341.18 | AC8: 565277.8 | AD8: 628136.96 | AE8: 728343.65 | AF8: 803735.23 | AG8: 605885.04 | AH8: 791985.12 | AI8: 680080.68 | AJ8: 799188.63 | AK8: 8055396.6 | AL8: 3646178.2 | AM8: 4409218.3 | AN8: 1881422.3 | AO8: 1764755.9 | AP8: 2137963.9 | AQ8: 2271254.4
B9: 电视及APP-电视商品（含自营业务） | C9: 91060796 | D9: 71242893 | E9: 72887479 | F9: 72173433 | G9: 69886466 | H9: 65714355 | I9: 68868780 | J9: 65116614 | K9: 71528972 | L9: 79916867 | M9: 73733516 | N9: 68166470 | O9: 8.7029664e+08 | P9: 4.4296542e+08 | Q9: 4.2733122e+08 | R9: 2.3519117e+08 | S9: 2.0777425e+08 | T9: 2.0551437e+08 | U9: 2.2181685e+08 | X9: 电视及APP-电视商品（含自营业务） | Y9: 23141348 | Z9: 16740906 | AA9: 18651063 | AB9: 18127100 | AC9: 17050642 | AD9: 17242451 | AE9: 17060422 | AF9: 16235447 | AG9: 16150202 | AH9: 15755887 | AI9: 19418912 | AJ9: 18386453 | AK9: 2.1396083e+08 | AL9: 1.1095351e+08 | AM9: 1.0300732e+08 | AN9: 58533318 | AO9: 52420192 | AP9: 49446071 | AQ9: 53561252
B10: 电视及APP-电商商品 | C10: 16752497 | D10: 10504730 | E10: 11604644 | F10: 12473111 | G10: 13588685 | H10: 12776572 | I10: 11834622 | J10: 9796971.8 | K10: 11622005 | L10: 10625909 | M10: 15294616 | N10: 14523050 | O10: 1.5139741e+08 | P10: 77700239 | Q10: 73697173 | R10: 38861871 | S10: 38838368 | T10: 33253598 | U10: 40443575 | X10: 电视及APP-电商商品 | Y10: 2769275.6 | Z10: 1936495.7 | AA10: 2247014.9 | AB10: 2050038.4 | AC10: 1739691.9 | AD10: 1876888.2 | AE10: 1558920 | AF10: 1430264.5 | AG10: 1787154.4 | AH10: 1736339.4 | AI10: 2199376.9 | AJ10: 4376535.8 | AK10: 25707996 | AL10: 12619405 | AM10: 13088591 | AN10: 6952786.2 | AO10: 5666618.5 | AP10: 4776338.9 | AQ10: 8312252.1
AD14: =57.6-52.5 -> 5.1
B15: 26年年初销售目标 | X15: 26年年初利润目标 | AD15: =AD21/30 -> 525230.08
B16: 销售金额 | C16: 1月 | D16: 2月 | E16: 3月 | F16: 4月 | G16: 5月 | H16: 6月 | I16: 7月 | J16: 8月 | K16: 9月 | L16: 10月 | M16: 11月 | N16: 12月 | O16: 合计 | P16: H1 | Q16: H2 | R16: Q1 | S16: Q2 | T16: Q3 | U16: Q4 | X16: 利润金额 | Y16: 1月 | Z16: 2月 | AA16: 3月 | AB16: 4月 | AC16: 5月 | AD16: 6月 | AE16: 7月 | AF16: 8月 | AG16: 9月 | AH16: 10月 | AI16: 11月 | AJ16: 12月 | AK16: 合计 | AL16: H1 | AM16: H2 | AN16: Q1 | AO16: Q2 | AP16: Q3 | AQ16: Q4
B17: 存量整体 | C17: 99061446 | D17: 71731576 | E17: 79220420 | F17: 81951908 | G17: 78847804 | H17: 75920356 | I17: 77009398 | J17: 73330395 | K17: 74938092 | L17: 77288871 | M17: 83121007 | N17: 79375529 | O17: 9.517968e+08 | P17: 4.8673351e+08 | Q17: 4.6506329e+08 | R17: 2.5001344e+08 | S17: 2.3672007e+08 | T17: 2.2527788e+08 | U17: 2.3978541e+08 | X17: 存量整体 | Y17: 23226681 | Z17: 16184643 | AA17: 18883028 | AB17: 18605316 | AC17: 17245454 | AD17: 17507669 | AE17: 17209969 | AF17: 16413118 | AG17: 16708599 | AH17: 16115526 | AI17: 19654694 | AJ17: 19852334 | AK17: 2.1760703e+08 | AL17: 1.1165279e+08 | AM17: 1.0595424e+08 | AN17: 58294352 | AO17: 53358439 | AP17: 50331686 | AQ17: 55622554
A18: 26年口径 | B18: 仅电视端及APP业务 （含自营业务） | C18: 78968729 | D18: 58442847 | E18: 61657160 | F18: 60719897 | G18: 62077814 | H18: 56610227 | I18: 57583160 | J18: 52901146 | K18: 55680594 | L18: 57502763 | M18: 58008239 | N18: 57929538 | O18: 7.1808211e+08 | P18: 3.7847667e+08 | Q18: 3.3960544e+08 | R18: 1.9906874e+08 | S18: 1.7940794e+08 | T18: 1.661649e+08 | U18: 1.7344054e+08 | W18: 26年口径 | X18: 仅电视端及APP业务 （含自营业务） | Y18: 19601681 | Z18: 13951219 | AA18: 15859315 | AB18: 14891718 | AC18: 14441552 | AD18: 14253253 | AE18: 14045318 | AF18: 13127913 | AG18: 13439765 | AH18: 12949109 | AI18: 15267218 | AJ18: 16278970 | AK18: 1.7810703e+08 | AL18: 92998738 | AM18: 85108292 | AN18: 49412216 | AO18: 43586523 | AP18: 40612995 | AQ18: 44495298
A19: 26年口径 | B19: 数据库营销 | C19: 13874286 | D19: 7789072.9 | E19: 10709975 | F19: 13630878 | G19: 9249524.1 | H19: 10953384 | I19: 9736341.1 | J19: 9736341.1 | K19: 11196792 | L19: 9249524.1 | M19: 16064963 | N19: 11683609 | O19: 1.3387469e+08 | P19: 66207120 | Q19: 67667571 | R19: 32373334 | S19: 33833785 | T19: 30669474 | U19: 36998096 | W19: 26年口径 | X19: 数据库营销 | Y19: 2850000 | Z19: 1600000 | AA19: 2200000 | AB19: 2800000 | AC19: 1900000 | AD19: 2250000 | AE19: 2000000 | AF19: 2000000 | AG19: 2300000 | AH19: 1900000 | AI19: 3300000 | AJ19: 2400000 | AK19: 27500000 | AL19: 13600000 | AM19: 13900000 | AN19: 6650000 | AO19: 6950000 | AP19: 6300000 | AQ19: 7600000
A20: 26年口径 | B20: 私域 | C20: 6218431.4 | D20: 5499656 | E20: 6853285 | F20: 7601133.4 | G20: 7520466.1 | H20: 8356745.5 | I20: 9689897.1 | J20: 10692908 | K20: 8060705.5 | L20: 10536584 | M20: 9047805.7 | N20: 9762382 | O20: 99840000 | P20: 42049717 | Q20: 57790283 | R20: 18571372 | S20: 23478345 | T20: 28443511 | U20: 29346772 | W20: 26年口径 | X20: 私域 | Y20: 775000 | Z20: 633423.97 | AA20: 823712.13 | AB20: 913597.76 | AC20: 903902.17 | AD20: 1004416.5 | AE20: 1164651.1 | AF20: 1285205.3 | AG20: 968834.8 | AH20: 1266416.4 | AI20: 1087476.6 | AJ20: 1173363.2 | AK20: 12000000 | AL20: 5054052.6 | AM20: 6945947.4 | AN20: 2232136.1 | AO20: 2821916.5 | AP20: 3418691.2 | AQ20: 3527256.3
B21: 电视及APP-电视商品（含自营业务） | C21: 85136343 | D21: 59324074 | E21: 69214879 | F21: 68196939 | G21: 63212428 | H21: 64173566 | I21: 63082358 | J21: 60161538 | K21: 61244611 | L21: 59070727 | M21: 72043389 | N21: 72767827 | O21: 7.9762868e+08 | P21: 4.0925823e+08 | Q21: 3.8837045e+08 | R21: 2.136753e+08 | S21: 1.9558293e+08 | T21: 1.8448851e+08 | U21: 2.0388194e+08 | X21: 电视及APP-电视商品（含自营业务） | Y21: 20904013 | Z21: 14566179 | AA21: 16994725 | AB21: 16744784 | AC21: 15520909 | AD21: 15756902 | AE21: 15488972 | AF21: 14771806 | AG21: 15037739 | AH21: 14503973 | AI21: 17689225 | AJ21: 17867100 | AK21: 1.9584633e+08 | AL21: 1.0048751e+08 | AM21: 95358816 | AN21: 52464916 | AO21: 48022595 | AP21: 45298517 | AQ21: 50060298
B22: 电视及APP-电商商品 | C22: 13925104 | D22: 12407501 | E22: 10005541 | F22: 13754968 | G22: 15635375 | H22: 11746790 | I22: 13927040 | J22: 13168857 | K22: 13693480 | L22: 18218144 | M22: 11077618 | N22: 6607702.3 | O22: 1.5416812e+08 | P22: 77475280 | Q22: 76692842 | R22: 36338146 | S22: 41137134 | T22: 40789377 | U22: 35903465 | X22: 电视及APP-电商商品 | Y22: 2322668.1 | Z22: 1618464.3 | AA22: 1888302.8 | AB22: 1860531.6 | AC22: 1724545.4 | AD22: 1750766.9 | AE22: 1720996.9 | AF22: 1641311.8 | AG22: 1670859.9 | AH22: 1611552.6 | AI22: 1965469.4 | AJ22: 1985233.4 | AK22: 21760703 | AL22: 11165279 | AM22: 10595424 | AN22: 5829435.2 | AO22: 5335843.9 | AP22: 5033168.6 | AQ22: 5562255.4
B27: 26年年初销售目标同比 | X27: 26年年初利润目标同比
B28: 销售金额 | C28: 1月 | D28: 2月 | E28: 3月 | F28: 4月 | G28: 5月 | H28: 6月 | I28: 7月 | J28: 8月 | K28: 9月 | L28: 10月 | M28: 11月 | N28: 12月 | O28: 合计 | P28: H1 | Q28: H2 | R28: Q1 | S28: Q2 | T28: Q3 | U28: Q4 | X28: 利润金额 | Y28: 1月 | Z28: 2月 | AA28: 3月 | AB28: 4月 | AC28: 5月 | AD28: 6月 | AE28: 7月 | AF28: 8月 | AG28: 9月 | AH28: 10月 | AI28: 11月 | AJ28: 12月 | AK28: 合计 | AL28: H1 | AM28: H2 | AN28: Q1 | AO28: Q2 | AP28: Q3 | AQ28: Q4
B29: 存量整体 | C29: =IFERROR(C17/C5-1,"") -> -0.10125851 | D29: =IFERROR(D17/D5-1,"") -> -0.1420634 | E29: =IFERROR(E17/E5-1,"") -> -0.087313271 | F29: =IFERROR(F17/F5-1,"") -> -0.057154042 | G29: =IFERROR(G17/G5-1,"") -> -0.078183806 | H29: =IFERROR(H17/H5-1,"") -> -0.056109085 | I29: =IFERROR(I17/I5-1,"") -> -0.069032553 | J29: =IFERROR(J17/J5-1,"") -> -0.046725952 | ... U29: =IFERROR(U17/U5-1,"") -> -0.10586671 | X29: 存量整体 | Y29: =IFERROR(Y17/Y5-1,"") -> -0.11293323 | Z29: =IFERROR(Z17/Z5-1,"") -> -0.14399919 | AA29: =IFERROR(AA17/AA5-1,"") -> -0.10849381 | AB29: =IFERROR(AB17/AB5-1,"") -> -0.088865443 | AC29: =IFERROR(AC17/AC5-1,"") -> -0.093699391 | AD29: =IFERROR(AD17/AD5-1,"") -> -0.095043516 | AE29: =IFERROR(AE17/AE5-1,"") -> -0.087284769 | AF29: =IFERROR(AF17/AF5-1,"") -> -0.082989397 | ... AQ29: =IFERROR(AQ17/AQ5-1,"") -> -0.11060837
A30: 26年口径 | B30: 仅电视端及APP业务 （含自营业务） | C30: =IFERROR(C18/C6-1,"") -> -0.15147693 | D30: =IFERROR(D18/D6-1,"") -> -0.15147693 | E30: =IFERROR(E18/E6-1,"") -> -0.15147693 | F30: =IFERROR(F18/F6-1,"") -> -0.15147693 | G30: =IFERROR(G18/G6-1,"") -> -0.15147693 | H30: =IFERROR(H18/H6-1,"") -> -0.15147693 | I30: =IFERROR(I18/I6-1,"") -> -0.15147693 | J30: =IFERROR(J18/J6-1,"") -> -0.15147693 | ... U30: =IFERROR(U18/U6-1,"") -> -0.15038619 | W30: 26年口径 | X30: 仅电视端及APP业务 （含自营业务） | Y30: =IFERROR(Y18/Y6-1,"") -> -0.15 | Z30: =IFERROR(Z18/Z6-1,"") -> -0.15 | AA30: =IFERROR(AA18/AA6-1,"") -> -0.13604747 | AB30: =IFERROR(AB18/AB6-1,"") -> -0.13588653 | AC30: =IFERROR(AC18/AC6-1,"") -> -0.13580428 | AD30: =IFERROR(AD18/AD6-1,"") -> -0.13576833 | AE30: =IFERROR(AE18/AE6-1,"") -> -0.13572751 | AF30: =IFERROR(AF18/AF6-1,"") -> -0.13553192 | ... AQ30: =IFERROR(AQ18/AQ6-1,"") -> -0.15486455
A31: 26年口径 | B31: 数据库营销 | C31: =IFERROR(C19/C7-1,"") -> 0.16827855 | D31: =IFERROR(D19/D7-1,"") -> -0.18054998 | E31: =IFERROR(E19/E7-1,"") -> 0.26766539 | F31: =IFERROR(F19/F7-1,"") -> 0.30926077 | G31: =IFERROR(G19/G7-1,"") -> 0.19320061 | H31: =IFERROR(H19/H7-1,"") -> 0.25131753 | I31: =IFERROR(I19/I7-1,"") -> 0.073819162 | J31: =IFERROR(J19/J7-1,"") -> 0.29891577 | ... U31: =IFERROR(U19/U7-1,"") -> -0.1483366 | W31: 26年口径 | X31: 数据库营销 | Y31: =IFERROR(Y19/Y7-1,"") -> 0.11775612 | Z31: =IFERROR(Z19/Z7-1,"") -> -0.1489732 | AA31: =IFERROR(AA19/AA7-1,"") -> 0.032839023 | AB31: =IFERROR(AB19/AB7-1,"") -> 0.070712778 | AC31: =IFERROR(AC19/AC7-1,"") -> 0.08438056 | AD31: =IFERROR(AD19/AD7-1,"") -> 0.010833439 | AE31: =IFERROR(AE19/AE7-1,"") -> 0.065859967 | AF31: =IFERROR(AF19/AF7-1,"") -> 0.047859571 | ... AQ31: =IFERROR(AQ19/AQ7-1,"") -> -0.0026285593
A32: 26年口径 | B32: 私域 | C32: =IFERROR(C20/C8-1,"") -> 0.17762847 | D32: =IFERROR(D20/D8-1,"") -> 0.051921076 | E32: =IFERROR(E20/E8-1,"") -> 0.2051934 | F32: =IFERROR(F20/F8-1,"") -> 0.53586663 | G32: =IFERROR(G20/G8-1,"") -> 0.62654769 | H32: =IFERROR(H20/H8-1,"") -> 0.68356183 | I32: =IFERROR(I20/I8-1,"") -> 0.67357966 | J32: =IFERROR(J20/J8-1,"") -> 0.50943147 | ... U32: =IFERROR(U20/U8-1,"") -> 0.42503252 | W32: 26年口径 | X32: 私域 | Y32: =IFERROR(Y20/Y8-1,"") -> 0.35220658 | Z32: =IFERROR(Z20/Z8-1,"") -> 0.03164398 | AA32: =IFERROR(AA20/AA8-1,"") -> 0.18640889 | AB32: =IFERROR(AB20/AB8-1,"") -> 0.59904063 | AC32: =IFERROR(AC20/AC8-1,"") -> 0.59904063 | AD32: =IFERROR(AD20/AD8-1,"") -> 0.59904063 | AE32: =IFERROR(AE20/AE8-1,"") -> 0.59904063 | AF32: =IFERROR(AF20/AF8-1,"") -> 0.59904063 | ... AQ32: =IFERROR(AQ20/AQ8-1,"") -> 0.55299918
B33: 电视及APP-电视商品（含自营业务） | C33: =IFERROR(C21/C9-1,"") -> -0.065060413 | D33: =IFERROR(D21/D9-1,"") -> -0.16729836 | E33: =IFERROR(E21/E9-1,"") -> -0.050387258 | F33: =IFERROR(F21/F9-1,"") -> -0.055096366 | G33: =IFERROR(G21/G9-1,"") -> -0.09549828 | H33: =IFERROR(H21/H9-1,"") -> -0.023446761 | I33: =IFERROR(I21/I9-1,"") -> -0.084020977 | J33: =IFERROR(J21/J9-1,"") -> -0.076095413 | ... U33: =IFERROR(U21/U9-1,"") -> -0.08085459 | X33: 电视及APP-电视商品（含自营业务） | Y33: =IFERROR(Y21/Y9-1,"") -> -0.096681303 | Z33: =IFERROR(Z21/Z9-1,"") -> -0.129905 | AA33: =IFERROR(AA21/AA9-1,"") -> -0.088806661 | AB33: =IFERROR(AB21/AB9-1,"") -> -0.076256861 | AC33: =IFERROR(AC21/AC9-1,"") -> -0.089717024 | AD33: =IFERROR(AD21/AD9-1,"") -> -0.086156462 | AE33: =IFERROR(AE21/AE9-1,"") -> -0.092110865 | AF33: =IFERROR(AF21/AF9-1,"") -> -0.090150948 | ... AQ33: =IFERROR(AQ21/AQ9-1,"") -> -0.065363551
B34: 电视及APP-电商商品 | C34: =IFERROR(C22/C10-1,"") -> -0.16877445 | D34: =IFERROR(D22/D10-1,"") -> 0.18113475 | E34: =IFERROR(E22/E10-1,"") -> -0.13779855 | F34: =IFERROR(F22/F10-1,"") -> 0.10276969 | G34: =IFERROR(G22/G10-1,"") -> 0.15061724 | H34: =IFERROR(H22/H10-1,"") -> -0.080599266 | I34: =IFERROR(I22/I10-1,"") -> 0.17680482 | J34: =IFERROR(J22/J10-1,"") -> 0.34417624 | ... U34: =IFERROR(U22/U10-1,"") -> -0.11225788 | X34: 电视及APP-电商商品 | Y34: =IFERROR(Y22/Y10-1,"") -> -0.16127233 | Z34: =IFERROR(Z22/Z10-1,"") -> -0.16423035 | AA34: =IFERROR(AA22/AA10-1,"") -> -0.15963942 | AB34: =IFERROR(AB22/AB10-1,"") -> -0.092440623 | AC34: =IFERROR(AC22/AC10-1,"") -> -0.0087064162 | AD34: =IFERROR(AD22/AD10-1,"") -> -0.067197005 | AE34: =IFERROR(AE22/AE10-1,"") -> 0.1039674 | AF34: =IFERROR(AF22/AF10-1,"") -> 0.14755823 | ... AQ34: =IFERROR(AQ22/AQ10-1,"") -> -0.33083654

Sheet 【只看单月】滚动目标及同比 (5-12月)
B3: 25年实际销售 | R3: 25年实际利润
B4: 销售金额 | C4: 1月 | D4: 2月 | E4: 3月 | F4: 4月 | G4: 5月 | H4: 6月 | I4: 7月 | J4: 8月 | K4: 9月 | L4: 10月 | M4: 11月 | N4: 12月 | O4: 合计 | R4: 利润金额 | S4: 1月 | T4: 2月 | U4: 3月 | V4: 4月 | W4: 5月 | X4: 6月 | Y4: 7月 | Z4: 8月 | AA4: 9月 | AB4: 10月 | AC4: 11月 | AD4: 12月 | AE4: 合计
B5: 存量整体 | C5: 1.102224e+08 | D5: 83609413 | E5: 86799137 | F5: 86919721 | G5: 85535277 | H5: 80433401 | I5: 82719754 | J5: 76924778 | K5: 85138541 | L5: 92473955 | M5: 91194584 | N5: 84507816 | O5: 1.0464788e+09 | R5: 存量整体 | S5: 26183689 | T5: 18907276 | U5: 21181039 | V5: 20419943 | W5: 19028404 | X5: 19346421 | Y5: 18855792 | Z5: 17898504 | AA5: 18162053 | AB5: 17715843 | AC5: 21853011 | AD5: 22971148 | AE5: 2.4252312e+08
A6: 26年口径 | B6: 仅电视端及APP业务 （含自营业务） | C6: 93066095 | D6: 68875967 | E6: 72664094 | F6: 71559512 | G6: 73159842 | H6: 66716190 | I6: 67862810 | J6: 62344970 | K6: 65620601 | L6: 67768060 | M6: 68448763 | N6: 67923619 | O6: 8.4601052e+08 | Q6: 26年口径 | R6: 仅电视端及APP业务 （含自营业务） | S6: 23060801 | T6: 16413199 | U6: 18356698 | V6: 17233521 | W6: 16710974 | X6: 16492398 | Y6: 16251029 | Z6: 15186116 | AA6: 15548110 | AB6: 14978563 | AC6: 17678212 | AD6: 19991942 | AE6: 2.0790156e+08
A7: 26年口径 | B7: 数据库营销 | C7: 11875837 | D7: 9505244.6 | E7: 8448582.2 | F7: 10411125 | G7: 7751860 | H7: 8753480.6 | I7: 9067021.2 | J7: 7495744.8 | K7: 13999988 | L7: 18029060 | M7: 16780507 | N7: 8632591.5 | O7: 1.3075104e+08 | Q7: 26年口径 | R7: 数据库营销 | S7: 2549751.2 | T7: 1880081.8 | U7: 2130051.2 | V7: 2615080.4 | W7: 1752152.4 | X7: 2225886 | Y7: 1876419.1 | Z7: 1908652.7 | AA7: 2008057.6 | AB7: 1945294.6 | AC7: 3494718 | AD7: 2180017.1 | AE7: 26566162
A8: 26年口径 | B8: 私域 | C8: 5280469.7 | D8: 5228202.1 | E8: 5686460.7 | F8: 4949084.3 | G8: 4623575.5 | H8: 4963729.5 | I8: 5789922.8 | J8: 7084063.3 | K8: 5517952.4 | L8: 6676835 | M8: 5965314.6 | N8: 7951606.3 | O8: 69717216 | Q8: 26年口径 | R8: 私域 | S8: 573137.28 | T8: 613994.73 | U8: 694290.26 | V8: 571341.18 | W8: 565277.8 | X8: 628136.96 | Y8: 728343.65 | Z8: 803735.23 | AA8: 605885.04 | AB8: 791985.12 | AC8: 680080.68 | AD8: 799188.63 | AE8: 8055396.6
B9: 电视及APP-电视商品（含自营业务） | C9: 91060796 | D9: 71242893 | E9: 72887479 | F9: 72173433 | G9: 69886466 | H9: 65714355 | I9: 68868780 | J9: 65116614 | K9: 71528972 | L9: 79916867 | M9: 73733516 | N9: 68166470 | O9: 8.7029664e+08 | R9: 电视及APP-电视商品（含自营业务） | S9: 23141348 | T9: 16740906 | U9: 18651063 | V9: 18127100 | W9: 17050642 | X9: 17242451 | Y9: 17060422 | Z9: 16235447 | AA9: 16150202 | AB9: 15755887 | AC9: 19418912 | AD9: 18386453 | AE9: 2.1396083e+08
B10: 电视及APP-电商商品 | C10: 16752497 | D10: 10504730 | E10: 11604644 | F10: 12473111 | G10: 13588685 | H10: 12776572 | I10: 11834622 | J10: 9796971.8 | K10: 11622005 | L10: 10625909 | M10: 15294616 | N10: 14523050 | O10: 1.5139741e+08 | R10: 电视及APP-电商商品 | S10: 2769275.6 | T10: 1936495.7 | U10: 2247014.9 | V10: 2050038.4 | W10: 1739691.9 | X10: 1876888.2 | Y10: 1558920 | Z10: 1430264.5 | AA10: 1787154.4 | AB10: 1736339.4 | AC10: 2199376.9 | AD10: 4376535.8 | AE10: 25707996
B15: 26年滚动销售目标 | R15: 26年滚动利润目标
B16: 销售金额 | C16: 1月 | D16: 2月 | E16: 3月 | F16: 4月 | G16: 5月 | H16: 6月 | I16: 7月 | J16: 8月 | K16: 9月 | L16: 10月 | M16: 11月 | N16: 12月 | O16: 合计 | R16: 利润金额 | S16: 1月 | T16: 2月 | U16: 3月 | V16: 4月 | W16: 5月 | X16: 6月 | Y16: 7月 | Z16: 8月 | AA16: 9月 | AB16: 10月 | AC16: 11月 | AD16: 12月 | AE16: 合计
B17: 存量整体 | C17: 99061446 | D17: 71731576 | E17: 80431467 | F17: 84784065 | G17: 83749195 | H17: 83438533 | I17: 78186645 | J17: 74451400 | K17: 76083674 | L17: 78470390 | M17: 84391682 | N17: 80588947 | O17: 9.6373605e+08 | R17: 存量整体 | S17: 23226681 | T17: 16184643 | U17: 19171693 | V17: 19248293 | W17: 18317478 | X17: 19241404 | Y17: 17473058 | Z17: 16664026 | AA17: 16964025 | AB17: 16361885 | AC17: 19955157 | AD17: 20155817 | AE17: 2.2033112e+08
A18: 26年口径 | B18: 仅电视端及APP业务 （含自营业务） | C18: 78968729 | D18: 58442847 | E18: 62863086 | F18: 63325154 | G18: 66899785 | H18: 63444597 | I18: 58709404 | J18: 53935816 | K18: 56769626 | L18: 58627434 | M18: 59142797 | N18: 59062556 | O18: 7.2943919e+08 | Q18: 26年口径 | R18: 仅电视端及APP业务 （含自营业务） | S18: 19601681 | T18: 13951219 | U18: 16169501 | V18: 15530664 | W18: 15563318 | X18: 15974002 | Y18: 14320024 | Z18: 13384676 | AA18: 13702627 | AB18: 13202375 | AC18: 15565823 | AD18: 16597364 | AE18: 1.809343e+08
A19: 26年口径 | B19: 数据库营销 | C19: 13874286 | D19: 7789072.9 | E19: 10709975 | F19: 13630878 | G19: 9249524.1 | H19: 10953384 | I19: 9736341.1 | J19: 9736341.1 | K19: 11196792 | L19: 9249524.1 | M19: 16064963 | N19: 11683609 | O19: 1.3387469e+08 | Q19: 26年口径 | R19: 数据库营销 | S19: 2850000 | T19: 1600000 | U19: 2200000 | V19: 2800000 | W19: 1900000 | X19: 2250000 | Y19: 2000000 | Z19: 2000000 | AA19: 2300000 | AB19: 1900000 | AC19: 3300000 | AD19: 2400000 | AE19: 27500000
A20: 26年口径 | B20: 私域 | C20: 6218431.4 | D20: 5499656 | E20: 6853285 | F20: 7650771.9 | G20: 7683206.6 | H20: 8688312.6 | I20: 9689897.1 | J20: 10692908 | K20: 8060705.5 | L20: 10536584 | M20: 9047805.7 | N20: 9762382 | O20: 99840000 | Q20: 26年口径 | R20: 私域 | S20: 775000 | T20: 633423.97 | U20: 823712.13 | V20: 919563.93 | W20: 923462.33 | X20: 1044268.3 | Y20: 1164651.1 | Z20: 1285205.3 | AA20: 968834.8 | AB20: 1266416.4 | AC20: 1087476.6 | AD20: 1173363.2 | AE20: 12000000
B21: 电视及APP-电视商品（含自营业务） | C21: 85136343 | D21: 59324074 | E21: 70209602 | F21: 70374603 | G21: 67096023 | H21: 70341858 | I21: 63988947 | J21: 61026151 | K21: 62124789 | L21: 59919663 | M21: 73078762 | N21: 73813611 | O21: 8.070157e+08 | R21: 电视及APP-电视商品（含自营业务） | S21: 20904013 | T21: 14566179 | U21: 17238965 | V21: 17279478 | W21: 16474470 | X21: 17271438 | Y21: 15711572 | Z21: 14984099 | AA21: 15253855 | AB21: 14712417 | AC21: 17943446 | AD21: 18123878 | AE21: 1.9815118e+08
B22: 电视及APP-电商商品 | C22: 13925104 | D22: 12407501 | E22: 10374085 | F22: 14848693 | G22: 17264769 | H22: 13832791 | I22: 14440028 | J22: 13653918 | K22: 14197865 | L22: 18889190 | M22: 11485651 | N22: 6851090.1 | O22: 1.5887681e+08 | R22: 电视及APP-电商商品 | S22: 2322668.1 | T22: 1618464.3 | U22: 1957856.4 | V22: 2008471.5 | W22: 1904263.7 | X22: 2061669 | Y22: 1784388 | Z22: 1701767.8 | AA22: 1732404.3 | AB22: 1670912.4 | AC22: 2037865.4 | AD22: 2058357.4 | AE22: 22417068
B27: 26年滚动销售目标同比 | R27: 26年滚动利润目标同比
B28: 销售金额 | C28: 1月 | D28: 2月 | E28: 3月 | F28: 4月 | G28: 5月 | H28: 6月 | I28: 7月 | J28: 8月 | K28: 9月 | L28: 10月 | M28: 11月 | N28: 12月 | O28: 合计 | R28: 利润金额 | S28: 1月 | T28: 2月 | U28: 3月 | V28: 4月 | W28: 5月 | X28: 6月 | Y28: 7月 | Z28: 8月 | AA28: 9月 | AB28: 10月 | AC28: 11月 | AD28: 12月 | AE28: 合计
B29: 存量整体 | C29: =IFERROR(C17/C5-1,"") -> -0.10125851 | D29: =IFERROR(D17/D5-1,"") -> -0.1420634 | E29: =IFERROR(E17/E5-1,"") -> -0.073360981 | F29: =IFERROR(F17/F5-1,"") -> -0.024570446 | G29: =IFERROR(G17/G5-1,"") -> -0.020881238 | H29: =IFERROR(H17/H5-1,"") -> 0.037361744 | I29: =IFERROR(I17/I5-1,"") -> -0.054800806 | J29: =IFERROR(J17/J5-1,"") -> -0.032153203 | ... O29: =IFERROR(O17/O5-1,"") -> -0.079067761 | R29: 存量整体 | S29: =IFERROR(S17/S5-1,"") -> -0.11293323 | T29: =IFERROR(T17/T5-1,"") -> -0.14399919 | U29: =IFERROR(U17/U5-1,"") -> -0.094865305 | V29: =IFERROR(V17/V5-1,"") -> -0.057377754 | W29: =IFERROR(W17/W5-1,"") -> -0.037361313 | X29: =IFERROR(X17/X5-1,"") -> -0.0054282526 | Y29: =IFERROR(Y17/Y5-1,"") -> -0.073332044 | Z29: =IFERROR(Z17/Z5-1,"") -> -0.068971009 | ... AE29: =IFERROR(AE17/AE5-1,"") -> -0.0915047
A30: 26年口径 | B30: 仅电视端及APP业务 （含自营业务） | C30: =IFERROR(C18/C6-1,"") -> -0.15147693 | D30: =IFERROR(D18/D6-1,"") -> -0.15147693 | E30: =IFERROR(E18/E6-1,"") -> -0.13488104 | F30: =IFERROR(F18/F6-1,"") -> -0.11507006 | G30: =IFERROR(G18/G6-1,"") -> -0.085566841 | H30: =IFERROR(H18/H6-1,"") -> -0.049037476 | I30: =IFERROR(I18/I6-1,"") -> -0.13488104 | J30: =IFERROR(J18/J6-1,"") -> -0.13488104 | ... O30: =IFERROR(O18/O6-1,"") -> -0.13778946 | Q30: 26年口径 | R30: 仅电视端及APP业务 （含自营业务） | S30: =IFERROR(S18/S6-1,"") -> -0.15 | T30: =IFERROR(T18/T6-1,"") -> -0.15 | U30: =IFERROR(U18/U6-1,"") -> -0.1191498 | V30: =IFERROR(V18/V6-1,"") -> -0.098810741 | W30: =IFERROR(W18/W6-1,"") -> -0.068676804 | X30: =IFERROR(X18/X6-1,"") -> -0.031432435 | Y30: =IFERROR(Y18/Y6-1,"") -> -0.11882358 | Z30: =IFERROR(Z18/Z6-1,"") -> -0.11862416 | ... AE30: =IFERROR(AE18/AE6-1,"") -> -0.12971169
A31: 26年口径 | B31: 数据库营销 | C31: =IFERROR(C19/C7-1,"") -> 0.16827855 | D31: =IFERROR(D19/D7-1,"") -> -0.18054998 | E31: =IFERROR(E19/E7-1,"") -> 0.26766539 | F31: =IFERROR(F19/F7-1,"") -> 0.30926077 | G31: =IFERROR(G19/G7-1,"") -> 0.19320061 | H31: =IFERROR(H19/H7-1,"") -> 0.25131753 | I31: =IFERROR(I19/I7-1,"") -> 0.073819162 | J31: =IFERROR(J19/J7-1,"") -> 0.29891577 | ... O31: =IFERROR(O19/O7-1,"") -> 0.023890046 | Q31: 26年口径 | R31: 数据库营销 | S31: =IFERROR(S19/S7-1,"") -> 0.11775612 | T31: =IFERROR(T19/T7-1,"") -> -0.1489732 | U31: =IFERROR(U19/U7-1,"") -> 0.032839023 | V31: =IFERROR(V19/V7-1,"") -> 0.070712778 | W31: =IFERROR(W19/W7-1,"") -> 0.08438056 | X31: =IFERROR(X19/X7-1,"") -> 0.010833439 | Y31: =IFERROR(Y19/Y7-1,"") -> 0.065859967 | Z31: =IFERROR(Z19/Z7-1,"") -> 0.047859571 | ... AE31: =IFERROR(AE19/AE7-1,"") -> 0.035151404
A32: 26年口径 | B32: 私域 | C32: =IFERROR(C20/C8-1,"") -> 0.17762847 | D32: =IFERROR(D20/D8-1,"") -> 0.051921076 | E32: =IFERROR(E20/E8-1,"") -> 0.2051934 | F32: =IFERROR(F20/F8-1,"") -> 0.54589647 | G32: =IFERROR(G20/G8-1,"") -> 0.66174568 | H32: =IFERROR(H20/H8-1,"") -> 0.75035981 | I32: =IFERROR(I20/I8-1,"") -> 0.67357966 | J32: =IFERROR(J20/J8-1,"") -> 0.50943147 | ... O32: =IFERROR(O20/O8-1,"") -> 0.43207095 | Q32: 26年口径 | R32: 私域 | S32: =IFERROR(S20/S8-1,"") -> 0.35220658 | T32: =IFERROR(T20/T8-1,"") -> 0.03164398 | U32: =IFERROR(U20/U8-1,"") -> 0.18640889 | V32: =IFERROR(V20/V8-1,"") -> 0.60948303 | W32: =IFERROR(W20/W8-1,"") -> 0.63364338 | X32: =IFERROR(X20/X8-1,"") -> 0.66248511 | Y32: =IFERROR(Y20/Y8-1,"") -> 0.59904063 | Z32: =IFERROR(Z20/Z8-1,"") -> 0.59904063 | ... AE32: =IFERROR(AE20/AE8-1,"") -> 0.48968457
B33: 电视及APP-电视商品（含自营业务） | C33: =IFERROR(C21/C9-1,"") -> -0.065060413 | D33: =IFERROR(D21/D9-1,"") -> -0.16729836 | E33: =IFERROR(E21/E9-1,"") -> -0.036739881 | F33: =IFERROR(F21/F9-1,"") -> -0.024923713 | G33: =IFERROR(G21/G9-1,"") -> -0.039928229 | H33: =IFERROR(H21/H9-1,"") -> 0.070418458 | I33: =IFERROR(I21/I9-1,"") -> -0.070856967 | J33: =IFERROR(J21/J9-1,"") -> -0.062817501 | ... O33: =IFERROR(O21/O9-1,"") -> -0.072711922 | R33: 电视及APP-电视商品（含自营业务） | S33: =IFERROR(S21/S9-1,"") -> -0.096681303 | T33: =IFERROR(T21/T9-1,"") -> -0.129905 | U33: =IFERROR(U21/U9-1,"") -> -0.075711429 | V33: =IFERROR(V21/V9-1,"") -> -0.046759904 | W33: =IFERROR(W21/W9-1,"") -> -0.033791789 | X33: =IFERROR(X21/X9-1,"") -> 0.001681169 | Y33: =IFERROR(Y21/Y9-1,"") -> -0.07906312 | Z33: =IFERROR(Z21/Z9-1,"") -> -0.077075035 | ... AE33: =IFERROR(AE21/AE9-1,"") -> -0.073890429
B34: 电视及APP-电商商品 | C34: =IFERROR(C22/C10-1,"") -> -0.16877445 | D34: =IFERROR(D22/D10-1,"") -> 0.18113475 | E34: =IFERROR(E22/E10-1,"") -> -0.10604027 | F34: =IFERROR(F22/F10-1,"") -> 0.19045629 | G34: =IFERROR(G22/G10-1,"") -> 0.27052534 | H34: =IFERROR(H22/H10-1,"") -> 0.082668374 | I34: =IFERROR(I22/I10-1,"") -> 0.22015119 | J34: =IFERROR(J22/J10-1,"") -> 0.39368756 | ... O34: =IFERROR(O22/O10-1,"") -> 0.049402406 | R34: 电视及APP-电商商品 | S34: =IFERROR(S22/S10-1,"") -> -0.16127233 | T34: =IFERROR(T22/T10-1,"") -> -0.16423035 | U34: =IFERROR(U22/U10-1,"") -> -0.12868562 | V34: =IFERROR(V22/V10-1,"") -> -0.020276145 | W34: =IFERROR(W22/W10-1,"") -> 0.094598249 | X34: =IFERROR(X22/X10-1,"") -> 0.098450615 | Y34: =IFERROR(Y22/Y10-1,"") -> 0.14463088 | Z34: =IFERROR(Z22/Z10-1,"") -> 0.18982733 | ... AE34: =IFERROR(AE22/AE10-1,"") -> -0.12801183

Sheet 6-12月滚动目标计算过程
B2: 26年年初利润目标 | Y2: 26年年初毛利率目标
B3: 利润金额 | C3: 1月 | D3: 2月 | E3: 3月 | F3: 4月 | G3: 5月 | H3: 6月 | I3: 7月 | J3: 8月 | K3: 9月 | L3: 10月 | M3: 11月 | N3: 12月 | O3: 合计 | P3: H1 | Q3: H2 | R3: Q1 | S3: Q2 | T3: Q3 | U3: Q4 | V3: 1-4月缺口 | X3: 税率 | Y3: 利润金额 | Z3: 1月 | AA3: 2月 | AB3: 3月 | AC3: 4月 | AD3: 5月 | AE3: 6月 | AF3: 7月 | AG3: 8月 | AH3: 9月 | AI3: 10月 | AJ3: 11月 | AK3: 12月 | AL3: 合计 | AM3: H1 | AN3: H2 | AO3: Q1 | AP3: Q2 | AQ3: Q3 | AR3: Q4
B4: 存量整体 | C4: 23226681 | D4: 16184643 | E4: 18883028 | F4: 18605316 | G4: 17245454 | H4: 17507669 | I4: 17209969 | J4: 16413118 | K4: 16708599 | L4: 16115526 | M4: 19654694 | N4: 19852334 | O4: 2.1760703e+08 | P4: 1.1165279e+08 | Q4: 1.0595424e+08 | R4: 58294352 | S4: 53358439 | T4: 50331686 | U4: 55622554 | V4: -12226081 | X4: 1.12 | Y4: 存量整体 | Z4: ='4. 实际达成与同比'!Y17*'6-12月滚动目标计算过程'!$X4/'4. 实际达成与同比'!C17 -> 0.2626035 | AA4: ='4. 实际达成与同比'!Z17*'6-12月滚动目标计算过程'!$X4/'4. 实际达成与同比'!D17 -> 0.25270323 | AB4: ='4. 实际达成与同比'!AA17*'6-12月滚动目标计算过程'!$X4/'4. 实际达成与同比'!E17 -> 0.26696388 | AC4: ='4. 实际达成与同比'!AB17*'6-12月滚动目标计算过程'!$X4/'4. 实际达成与同比'!F17 -> 0.25427051 | AD4: ='4. 实际达成与同比'!AC17*'6-12月滚动目标计算过程'!$X4/'4. 实际达成与同比'!G17 -> 0.24496445 | AE4: ='4. 实际达成与同比'!AD17*'6-12月滚动目标计算过程'!$X4/'4. 实际达成与同比'!H17 -> 0.25827842 | AF4: ='4. 实际达成与同比'!AE17*'6-12月滚动目标计算过程'!$X4/'4. 实际达成与同比'!I17 -> 0.25029627 | AG4: ='4. 实际达成与同比'!AF17*'6-12月滚动目标计算过程'!$X4/'4. 实际达成与同比'!J17 -> 0.25068312 | ... AR4: ='4. 实际达成与同比'!AQ17*'6-12月滚动目标计算过程'!$X4/'4. 实际达成与同比'!U17 -> 0.25980422
B5: 仅电视端及APP业务 （含自营业务） | C5: 19601681 | D5: 13951219 | E5: 15859315 | F5: 14891718 | G5: 14441552 | H5: 14253253 | I5: 14045318 | J5: 13127913 | K5: 13439765 | L5: 12949109 | M5: 15267218 | N5: 16278970 | O5: 1.7810703e+08 | P5: 92998738 | Q5: 85108292 | R5: 49412216 | S5: 43586523 | T5: 40612995 | U5: 44495298 | V5: -11995599 | X5: 1.12 | Y5: 仅电视端及APP业务 （含自营业务） | Z5: ='4. 实际达成与同比'!Y18*'6-12月滚动目标计算过程'!$X5/'4. 实际达成与同比'!C18 -> 0.27800729 | AA5: ='4. 实际达成与同比'!Z18*'6-12月滚动目标计算过程'!$X5/'4. 实际达成与同比'!D18 -> 0.26736147 | AB5: ='4. 实际达成与同比'!AA18*'6-12月滚动目标计算过程'!$X5/'4. 实际达成与同比'!E18 -> 0.28808387 | AC5: ='4. 实际达成与同比'!AB18*'6-12月滚动目标计算过程'!$X5/'4. 实际达成与同比'!F18 -> 0.27468301 | AD5: ='4. 实际达成与同比'!AC18*'6-12月滚动目标计算过程'!$X5/'4. 实际达成与同比'!G18 -> 0.26055264 | AE5: ='4. 实际达成与同比'!AD18*'6-12月滚动目标计算过程'!$X5/'4. 实际达成与同比'!H18 -> 0.28199221 | AF5: ='4. 实际达成与同比'!AE18*'6-12月滚动目标计算过程'!$X5/'4. 实际达成与同比'!I18 -> 0.27318327 | AG5: ='4. 实际达成与同比'!AF18*'6-12月滚动目标计算过程'!$X5/'4. 实际达成与同比'!J18 -> 0.27793845 | ... AR5: ='4. 实际达成与同比'!AQ18*'6-12月滚动目标计算过程'!$X5/'4. 实际达成与同比'!U18 -> 0.28733036
B6: 数据库营销 | C6: 2850000 | D6: 1600000 | E6: 2200000 | F6: 2800000 | G6: 1900000 | H6: 2250000 | I6: 2000000 | J6: 2000000 | K6: 2300000 | L6: 1900000 | M6: 3300000 | N6: 2400000 | O6: 27500000 | P6: 13600000 | Q6: 13900000 | R6: 6650000 | S6: 6950000 | T6: 6300000 | U6: 7600000 | X6: 1.12 | Y6: 数据库营销 | Z6: ='4. 实际达成与同比'!Y19*'6-12月滚动目标计算过程'!$X6/'4. 实际达成与同比'!C19 -> 0.23006589 | AA6: ='4. 实际达成与同比'!Z19*'6-12月滚动目标计算过程'!$X6/'4. 实际达成与同比'!D19 -> 0.23006589 | AB6: ='4. 实际达成与同比'!AA19*'6-12月滚动目标计算过程'!$X6/'4. 实际达成与同比'!E19 -> 0.23006589 | AC6: ='4. 实际达成与同比'!AB19*'6-12月滚动目标计算过程'!$X6/'4. 实际达成与同比'!F19 -> 0.23006589 | AD6: ='4. 实际达成与同比'!AC19*'6-12月滚动目标计算过程'!$X6/'4. 实际达成与同比'!G19 -> 0.23006589 | AE6: ='4. 实际达成与同比'!AD19*'6-12月滚动目标计算过程'!$X6/'4. 实际达成与同比'!H19 -> 0.23006589 | AF6: ='4. 实际达成与同比'!AE19*'6-12月滚动目标计算过程'!$X6/'4. 实际达成与同比'!I19 -> 0.23006589 | AG6: ='4. 实际达成与同比'!AF19*'6-12月滚动目标计算过程'!$X6/'4. 实际达成与同比'!J19 -> 0.23006589 | ... AR6: ='4. 实际达成与同比'!AQ19*'6-12月滚动目标计算过程'!$X6/'4. 实际达成与同比'!U19 -> 0.23006589
B7: 私域 | C7: 775000 | D7: 633423.97 | E7: 823712.13 | F7: 913597.76 | G7: 903902.17 | H7: 1004416.5 | I7: 1164651.1 | J7: 1285205.3 | K7: 968834.8 | L7: 1266416.4 | M7: 1087476.6 | N7: 1173363.2 | O7: 12000000 | P7: 5054052.6 | Q7: 6945947.4 | R7: 2232136.1 | S7: 2821916.5 | T7: 3418691.2 | U7: 3527256.3 | V7: -315443.29 | X7: 1.12 | Y7: 私域 | Z7: ='4. 实际达成与同比'!Y20*'6-12月滚动目标计算过程'!$X7/'4. 实际达成与同比'!C20 -> 0.13958504 | AA7: ='4. 实际达成与同比'!Z20*'6-12月滚动目标计算过程'!$X7/'4. 实际达成与同比'!D20 -> 0.12899622 | AB7: ='4. 实际达成与同比'!AA20*'6-12月滚动目标计算过程'!$X7/'4. 实际达成与同比'!E20 -> 0.13461538 | AC7: ='4. 实际达成与同比'!AB20*'6-12月滚动目标计算过程'!$X7/'4. 实际达成与同比'!F20 -> 0.13461538 | AD7: ='4. 实际达成与同比'!AC20*'6-12月滚动目标计算过程'!$X7/'4. 实际达成与同比'!G20 -> 0.13461538 | AE7: ='4. 实际达成与同比'!AD20*'6-12月滚动目标计算过程'!$X7/'4. 实际达成与同比'!H20 -> 0.13461538 | AF7: ='4. 实际达成与同比'!AE20*'6-12月滚动目标计算过程'!$X7/'4. 实际达成与同比'!I20 -> 0.13461538 | AG7: ='4. 实际达成与同比'!AF20*'6-12月滚动目标计算过程'!$X7/'4. 实际达成与同比'!J20 -> 0.13461538 | ... AR7: ='4. 实际达成与同比'!AQ20*'6-12月滚动目标计算过程'!$X7/'4. 实际达成与同比'!U20 -> 0.13461538
B8: 电视及APP-电视商品（含自营业务） | C8: 20904013 | D8: 14566179 | E8: 16994725 | F8: 16744784 | G8: 15520909 | H8: 15756902 | I8: 15488972 | J8: 14771806 | K8: 15037739 | L8: 14503973 | M8: 17689225 | N8: 17867100 | O8: 1.9584633e+08 | P8: 1.0048751e+08 | Q8: 95358816 | R8: 52464916 | S8: 48022595 | T8: 45298517 | U8: 50060298 | V8: -10680320 | X8: 1.12 | Y8: 电视及APP-电视商品（含自营业务） | Z8: ='4. 实际达成与同比'!Y21*'6-12月滚动目标计算过程'!$X8/'4. 实际达成与同比'!C21 -> 0.275 | AA8: ='4. 实际达成与同比'!Z21*'6-12月滚动目标计算过程'!$X8/'4. 实际达成与同比'!D21 -> 0.275 | AB8: ='4. 实际达成与同比'!AA21*'6-12月滚动目标计算过程'!$X8/'4. 实际达成与同比'!E21 -> 0.275 | AC8: ='4. 实际达成与同比'!AB21*'6-12月滚动目标计算过程'!$X8/'4. 实际达成与同比'!F21 -> 0.275 | AD8: ='4. 实际达成与同比'!AC21*'6-12月滚动目标计算过程'!$X8/'4. 实际达成与同比'!G21 -> 0.275 | AE8: ='4. 实际达成与同比'!AD21*'6-12月滚动目标计算过程'!$X8/'4. 实际达成与同比'!H21 -> 0.275 | AF8: ='4. 实际达成与同比'!AE21*'6-12月滚动目标计算过程'!$X8/'4. 实际达成与同比'!I21 -> 0.275 | AG8: ='4. 实际达成与同比'!AF21*'6-12月滚动目标计算过程'!$X8/'4. 实际达成与同比'!J21 -> 0.275 | ... AR8: ='4. 实际达成与同比'!AQ21*'6-12月滚动目标计算过程'!$X8/'4. 实际达成与同比'!U21 -> 0.275
B9: 电视及APP-电商商品 | C9: 2322668.1 | D9: 1618464.3 | E9: 1888302.8 | F9: 1860531.6 | G9: 1724545.4 | H9: 1750766.9 | I9: 1720996.9 | J9: 1641311.8 | K9: 1670859.9 | L9: 1611552.6 | M9: 1965469.4 | N9: 1985233.4 | O9: 21760703 | P9: 11165279 | Q9: 10595424 | R9: 5829435.2 | S9: 5335843.9 | T9: 5033168.6 | U9: 5562255.4 | V9: -2192442.7 | X9: 1.12 | Y9: 电视及APP-电商商品 | Z9: ='4. 实际达成与同比'!Y22*'6-12月滚动目标计算过程'!$X9/'4. 实际达成与同比'!C22 -> 0.18681284 | AA9: ='4. 实际达成与同比'!Z22*'6-12月滚动目标计算过程'!$X9/'4. 实际达成与同比'!D22 -> 0.1460955 | AB9: ='4. 实际达成与同比'!AA22*'6-12月滚动目标计算过程'!$X9/'4. 实际达成与同比'!E22 -> 0.21137278 | AC9: ='4. 实际达成与同比'!AB22*'6-12月滚动目标计算过程'!$X9/'4. 实际达成与同比'!F22 -> 0.15149401 | AD9: ='4. 实际达成与同比'!AC22*'6-12月滚动目标计算过程'!$X9/'4. 实际达成与同比'!G22 -> 0.12353339 | AE9: ='4. 实际达成与同比'!AD22*'6-12月滚动目标计算过程'!$X9/'4. 实际达成与同比'!H22 -> 0.16692722 | AF9: ='4. 实际达成与同比'!AE22*'6-12月滚动目标计算过程'!$X9/'4. 实际达成与同比'!I22 -> 0.13840101 | AG9: ='4. 实际达成与同比'!AF22*'6-12月滚动目标计算过程'!$X9/'4. 实际达成与同比'!J22 -> 0.13959216 | ... AR9: ='4. 实际达成与同比'!AQ22*'6-12月滚动目标计算过程'!$X9/'4. 实际达成与同比'!U22 -> 0.17351323
A10: GMV | B10: 移动端 | C10: 35750000 | D10: 22750000 | E10: 32500000 | F10: 52000000 | G10: 55250000 | H10: 61750000 | I10: 58500000 | J10: 61750000 | K10: 61750000 | L10: 55250000 | M10: 84500000 | N10: 68250000 | O10: =SUM(C10:N10) -> 650000000 | P10: =SUM(C10:H10) -> 260000000 | Q10: =SUM(I10:N10) -> 390000000 | R10: =SUM(C10:E10) -> 91000000 | S10: =SUM(F10:H10) -> 169000000 | T10: =SUM(I10:K10) -> 182000000 | U10: =SUM(L10:N10) -> 208000000 | V10: -41233383
B12: 滚动月度占比 | H12: 6月 | I12: 7月 | J12: 8月 | K12: 9月 | L12: 10月 | M12: 11月 | N12: 12月
B13: 存量整体 | H13: =H4/$V13 -> 0.14180624 | I13: =I4/$V13 -> 0.13939497 | J13: =J4/$V13 -> 0.13294074 | K13: =K4/$V13 -> 0.13533404 | L13: =L4/$V13 -> 0.13053035 | M13: =M4/$V13 -> 0.15919642 | N13: =N4/$V13 -> 0.16079724 | V13: =SUM(H4:N4) -> 1.2346191e+08
B14: 仅电视端及APP业务 （含自营业务） | H14: =H5/$V14 -> 0.14344838 | I14: =I5/$V14 -> 0.14135567 | J14: =J5/$V14 -> 0.13212267 | K14: =K5/$V14 -> 0.13526123 | L14: =L5/$V14 -> 0.13032315 | M14: =M5/$V14 -> 0.15365318 | N14: =N5/$V14 -> 0.16383572 | V14: =SUM(H5:N5) -> 99361545
B15: 数据库营销 | H15: =H6/$V15 -> 0.13931889 | I15: =I6/$V15 -> 0.12383901 | J15: =J6/$V15 -> 0.12383901 | K15: =K6/$V15 -> 0.14241486 | L15: =L6/$V15 -> 0.11764706 | M15: =M6/$V15 -> 0.20433437 | N15: =N6/$V15 -> 0.14860681 | V15: =SUM(H6:N6) -> 16150000
B16: 私域 | H16: =H7/$V16 -> 0.12633592 | I16: =I7/$V16 -> 0.14649029 | J16: =J7/$V16 -> 0.16165364 | K16: =K7/$V16 -> 0.12186043 | L16: =L7/$V16 -> 0.15929037 | M16: =M7/$V16 -> 0.13678325 | N16: =N7/$V16 -> 0.1475861 | V16: =SUM(H7:N7) -> 7950364
B17: 电视及APP-电视商品（含自营业务） | H17: =H8/$V17 -> 0.14180624 | I17: =I8/$V17 -> 0.13939497 | J17: =J8/$V17 -> 0.13294074 | K17: =K8/$V17 -> 0.13533404 | L17: =L8/$V17 -> 0.13053035 | M17: =M8/$V17 -> 0.15919642 | N17: =N8/$V17 -> 0.16079724 | V17: =SUM(H8:N8) -> 1.1111572e+08
B18: 电视及APP-电商商品 | H18: =H9/$V18 -> 0.14180624 | I18: =I9/$V18 -> 0.13939497 | J18: =J9/$V18 -> 0.13294074 | K18: =K9/$V18 -> 0.13533404 | L18: =L9/$V18 -> 0.13053035 | M18: =M9/$V18 -> 0.15919642 | N18: =N9/$V18 -> 0.16079724 | V18: =SUM(H9:N9) -> 12346191
B19: 移动端 | H19: =H10/$V19 -> 0.13669065 | I19: =I10/$V19 -> 0.1294964 | J19: =J10/$V19 -> 0.13669065 | K19: =K10/$V19 -> 0.13669065 | L19: =L10/$V19 -> 0.12230216 | M19: =M10/$V19 -> 0.18705036 | N19: =N10/$V19 -> 0.15107914 | V19: =SUM(H10:N10) -> 451750000
B21: 缺口分摊 | H21: 6月 | I21: 7月 | J21: 8月 | K21: 9月 | L21: 10月 | M21: 11月 | N21: 12月 | V21: 日均增加
B22: 存量整体 | H22: =H13*ABS($V4) -> 1733734.6 | I22: =I13*ABS($V4) -> 1704254.2 | J22: =J13*ABS($V4) -> 1625344.3 | K22: =K13*ABS($V4) -> 1654605 | L22: =L13*ABS($V4) -> 1595874.6 | M22: =M13*ABS($V4) -> 1946348.4 | N22: =N13*ABS($V4) -> 1965920.1 | V22: =H22/30 -> 57791.154
B23: 仅电视端及APP业务 （含自营业务） | H23: =H14*ABS($V5) -> 1720749.2 | I23: =I14*ABS($V5) -> 1695645.9 | J23: =J14*ABS($V5) -> 1584890.5 | K23: =K14*ABS($V5) -> 1622539.4 | L23: =L14*ABS($V5) -> 1563304.2 | M23: =M14*ABS($V5) -> 1843161.9 | N23: =N14*ABS($V5) -> 1965307.6 | V23: =H23/30 -> 57358.307
B24: 数据库营销 | H24: =H15*ABS($V6) -> 0 | I24: =I15*ABS($V6) -> 0 | J24: =J15*ABS($V6) -> 0 | K24: =K15*ABS($V6) -> 0 | L24: =L15*ABS($V6) -> 0 | M24: =M15*ABS($V6) -> 0 | N24: =N15*ABS($V6) -> 0
B25: 私域 | H25: =H16*ABS($V7) -> 39851.818 | I25: =I16*ABS($V7) -> 46209.379 | J25: =J16*ABS($V7) -> 50992.558 | K25: =K16*ABS($V7) -> 38440.057 | L25: =L16*ABS($V7) -> 50247.078 | M25: =M16*ABS($V7) -> 43147.36 | N25: =N16*ABS($V7) -> 46555.046 | V25: =H25/30 -> 1328.3939
B26: 电视及APP-电视商品（含自营业务） | H26: =H17*ABS($V8) -> 1514536.1 | I26: =I17*ABS($V8) -> 1488782.9 | J26: =J17*ABS($V8) -> 1419849.7 | K26: =K17*ABS($V8) -> 1445410.9 | L26: =L17*ABS($V8) -> 1394105.9 | M26: =M17*ABS($V8) -> 1700268.8 | N26: =N17*ABS($V8) -> 1717365.9 | V26: =H26/30 -> 50484.535
B27: 电视及APP-电商商品 | H27: =H18*ABS($V9) -> 310902.06 | I27: =I18*ABS($V9) -> 305615.48 | J27: =J18*ABS($V9) -> 291464.97 | K27: =K18*ABS($V9) -> 296712.14 | L27: =L18*ABS($V9) -> 286180.31 | M27: =M18*ABS($V9) -> 349029.04 | N27: =N18*ABS($V9) -> 352538.73 | V27: =H27/30 -> 10363.402
B28: 移动端 | H28: =H19*ABS($V10) -> 5636217.8 | I28: =I19*ABS($V10) -> 5339574.8 | J28: =J19*ABS($V10) -> 5636217.8 | K28: =K19*ABS($V10) -> 5636217.8 | L28: =L19*ABS($V10) -> 5042931.7 | M28: =M19*ABS($V10) -> 7712719.1 | N28: =N19*ABS($V10) -> 6229503.9
B32: 26年滚动利润目标 | Y32: 26年滚动销售目标（根据目标毛利率反推）
B33: 利润金额 | C33: 1月 | D33: 2月 | E33: 3月 | F33: 4月 | G33: 5月 | H33: 6月 | I33: 7月 | J33: 8月 | K33: 9月 | L33: 10月 | M33: 11月 | N33: 12月 | O33: 合计 | P33: H1 | Q33: H2 | R33: Q1 | S33: Q2 | T33: Q3 | U33: Q4 | V33: 差异check | X33: 税率 | Y33: 利润金额 | Z33: 1月 | AA33: 2月 | AB33: 3月 | AC33: 4月 | AD33: 5月 | AE33: 6月 | AF33: 7月 | AG33: 8月 | AH33: 9月 | AI33: 10月 | AJ33: 11月 | AK33: 12月 | AL33: 合计 | AM33: H1 | AN33: H2 | AO33: Q1 | AP33: Q2 | AQ33: Q3 | AR33: Q4 | AT33: 日均增加
B34: 存量整体 | C34: =C4+C22 -> 23226681 | D34: =D4+D22 -> 16184643 | E34: 19171693 | F34: 19248293 | G34: 18317478 | H34: =H4+H22 -> 19241404 | I34: =I4+I22 -> 18914223 | J34: =J4+J22 -> 18038462 | K34: =K4+K22 -> 18363204 | L34: =L4+L22 -> 17711400 | M34: =M4+M22 -> 21601043 | N34: =N4+N22 -> 21818254 | O34: =SUM(C34:N34) -> 2.3183678e+08 | P34: =SUM(C34:H34) -> 1.1539019e+08 | Q34: =SUM(I34:N34) -> 1.1644659e+08 | R34: =SUM(C34:E34) -> 58583017 | S34: =SUM(F34:H34) -> 56807174 | T34: =SUM(I34:K34) -> 55315889 | U34: =SUM(L34:N34) -> 61130697 | V34: =O34-O4 -> 14229748 | X34: 1.12 | Y34: 存量整体 | Z34: =C34*$X34/Z4 -> 99061446 | AA34: =D34*$X34/AA4 -> 71731576 | AB34: =E34*$X34/AB4 -> 80431467 | AC34: =F34*$X34/AC4 -> 84784065 | AD34: =G34*$X34/AD4 -> 83749195 | AE34: =H34*$X34/AE4 -> 83438533 | AF34: =I34*$X34/AF4 -> 84635419 | AG34: =J34*$X34/AG4 -> 80592095 | ... AK34: =N34*$X34/AK4 -> 87235862 | AL34: =SUM(Z34:AK34) -> 1.0143135e+09 | AM34: =SUM(Z34:AE34) -> 5.0319628e+08 | AN34: =SUM(AF34:AK34) -> 5.1111719e+08 | AO34: =SUM(Z34:AB34) -> 2.5122449e+08 | AP34: =SUM(AC34:AE34) -> 2.5197179e+08 | AQ34: =SUM(AF34:AH34) -> 2.4758651e+08 | AR34: =SUM(AI34:AK34) -> 2.6353067e+08 | AT34: =AE34/30 -> 2781284.4
B35: 仅电视端及APP业务 （含自营业务） | C35: =C5+C23 -> 19601681 | D35: =D5+D23 -> 13951219 | E35: 16169501 | F35: 15530664 | G35: 15563318 | H35: =H5+H23 -> 15974002 | I35: =I5+I23 -> 15740963 | J35: =J5+J23 -> 14712803 | K35: =K5+K23 -> 15062304 | L35: =L5+L23 -> 14512414 | M35: =M5+M23 -> 17110380 | N35: =N5+N23 -> 18244278 | O35: =SUM(C35:N35) -> 1.9217353e+08 | P35: =SUM(C35:H35) -> 96790385 | Q35: =SUM(I35:N35) -> 95383142 | R35: =SUM(C35:E35) -> 49722401 | S35: =SUM(F35:H35) -> 47067984 | T35: =SUM(I35:K35) -> 45516071 | U35: =SUM(L35:N35) -> 49867071 | V35: =O35-O5 -> 14066496 | X35: 1.12 | Y35: 仅电视端及APP业务 （含自营业务） | Z35: =C35*$X35/Z5 -> 78968729 | AA35: =D35*$X35/AA5 -> 58442847 | AB35: =E35*$X35/AB5 -> 62863086 | AC35: =F35*$X35/AC5 -> 63325154 | AD35: =G35*$X35/AD5 -> 66899785 | AE35: =H35*$X35/AE5 -> 63444597 | AF35: =I35*$X35/AF5 -> 64534989 | AG35: =J35*$X35/AG5 -> 59287730 | ... AK35: =N35*$X35/AK5 -> 64923184 | AL35: =SUM(Z35:AK35) -> 7.745491e+08 | AM35: =SUM(Z35:AE35) -> 3.939442e+08 | AN35: =SUM(AF35:AK35) -> 3.8060491e+08 | AO35: =SUM(Z35:AB35) -> 2.0027466e+08 | AP35: =SUM(AC35:AE35) -> 1.9366954e+08 | AQ35: =SUM(AF35:AH35) -> 1.8622545e+08 | AR35: =SUM(AI35:AK35) -> 1.9437946e+08 | AT35: =AE35/30 -> 2114819.9
B36: 数据库营销 | C36: =C6+C24 -> 2850000 | D36: =D6+D24 -> 1600000 | E36: 2200000 | F36: 2800000 | G36: 1900000 | H36: =H6+H24 -> 2250000 | I36: =I6+I24 -> 2000000 | J36: =J6+J24 -> 2000000 | K36: =K6+K24 -> 2300000 | L36: =L6+L24 -> 1900000 | M36: =M6+M24 -> 3300000 | N36: =N6+N24 -> 2400000 | O36: =SUM(C36:N36) -> 27500000 | P36: =SUM(C36:H36) -> 13600000 | Q36: =SUM(I36:N36) -> 13900000 | R36: =SUM(C36:E36) -> 6650000 | S36: =SUM(F36:H36) -> 6950000 | T36: =SUM(I36:K36) -> 6300000 | U36: =SUM(L36:N36) -> 7600000 | V36: =O36-O6 -> 0 | X36: 1.12 | Y36: 数据库营销 | Z36: =C36*$X36/Z6 -> 13874286 | AA36: =D36*$X36/AA6 -> 7789072.9 | AB36: =E36*$X36/AB6 -> 10709975 | AC36: =F36*$X36/AC6 -> 13630878 | AD36: =G36*$X36/AD6 -> 9249524.1 | AE36: =H36*$X36/AE6 -> 10953384 | AF36: =I36*$X36/AF6 -> 9736341.1 | AG36: =J36*$X36/AG6 -> 9736341.1 | ... AK36: =N36*$X36/AK6 -> 11683609 | AL36: =SUM(Z36:AK36) -> 1.3387469e+08 | AM36: =SUM(Z36:AE36) -> 66207120 | AN36: =SUM(AF36:AK36) -> 67667571 | AO36: =SUM(Z36:AB36) -> 32373334 | AP36: =SUM(AC36:AE36) -> 33833785 | AQ36: =SUM(AF36:AH36) -> 30669474 | AR36: =SUM(AI36:AK36) -> 36998096 | AT36: =AE36/30 -> 365112.79
B37: 私域 | C37: =C7+C25 -> 775000 | D37: =D7+D25 -> 633423.97 | E37: 823712.13 | F37: 919563.93 | G37: 923462.33 | H37: =H7+H25 -> 1044268.3 | I37: =I7+I25 -> 1210860.5 | J37: =J7+J25 -> 1336197.8 | K37: =K7+K25 -> 1007274.9 | L37: =L7+L25 -> 1316663.5 | M37: =M7+M25 -> 1130624 | N37: =N7+N25 -> 1219918.3 | O37: =SUM(C37:N37) -> 12340970 | P37: =SUM(C37:H37) -> 5119430.7 | Q37: =SUM(I37:N37) -> 7221538.9 | R37: =SUM(C37:E37) -> 2232136.1 | S37: =SUM(F37:H37) -> 2887294.6 | T37: =SUM(I37:K37) -> 3554333.2 | U37: =SUM(L37:N37) -> 3667205.7 | V37: =O37-O7 -> 340969.63 | X37: 1.12 | Y37: 私域 | Z37: =C37*$X37/Z7 -> 6218431.4 | AA37: =D37*$X37/AA7 -> 5499656 | AB37: =E37*$X37/AB7 -> 6853285 | AC37: =F37*$X37/AC7 -> 7650771.9 | AD37: =G37*$X37/AD7 -> 7683206.6 | AE37: =H37*$X37/AE7 -> 8688312.6 | AF37: =I37*$X37/AF7 -> 10074359 | AG37: =J37*$X37/AG7 -> 11117166 | ... AK37: =N37*$X37/AK7 -> 10149720 | AL37: =SUM(Z37:AK37) -> 1.0267687e+08 | AM37: =SUM(Z37:AE37) -> 42593664 | AN37: =SUM(AF37:AK37) -> 60083204 | AO37: =SUM(Z37:AB37) -> 18571372 | AP37: =SUM(AC37:AE37) -> 24022291 | AQ37: =SUM(AF37:AH37) -> 29572052 | AR37: =SUM(AI37:AK37) -> 30511152 | AT37: =AE37/30 -> 289610.42
B38: 电视及APP-电视商品（含自营业务） | C38: =C8+C26 -> 20904013 | D38: =D8+D26 -> 14566179 | E38: 17238965 | F38: 17279478 | G38: 16474470 | H38: =H8+H26 -> 17271438 | I38: =I8+I26 -> 16977755 | J38: =J8+J26 -> 16191656 | K38: =K8+K26 -> 16483150 | L38: =L8+L26 -> 15898079 | M38: =M8+M26 -> 19389494 | N38: =N8+N26 -> 19584466 | O38: =SUM(C38:N38) -> 2.0825914e+08 | P38: =SUM(C38:H38) -> 1.0373454e+08 | Q38: =SUM(I38:N38) -> 1.045246e+08 | R38: =SUM(C38:E38) -> 52709156 | S38: =SUM(F38:H38) -> 51025387 | T38: =SUM(I38:K38) -> 49652561 | U38: =SUM(L38:N38) -> 54872039 | V38: =O38-O8 -> 12412816 | X38: 1.12 | Y38: 电视及APP-电视商品（含自营业务） | Z38: =C38*$X38/Z8 -> 85136343 | AA38: =D38*$X38/AA8 -> 59324074 | AB38: =E38*$X38/AB8 -> 70209602 | AC38: =F38*$X38/AC8 -> 70374603 | AD38: =G38*$X38/AD8 -> 67096023 | AE38: =H38*$X38/AE8 -> 70341858 | AF38: =I38*$X38/AF8 -> 69145764 | AG38: =J38*$X38/AG8 -> 65944199 | ... AK38: =N38*$X38/AK8 -> 79762190 | AL38: =SUM(Z38:AK38) -> 8.4818269e+08 | AM38: =SUM(Z38:AE38) -> 4.224825e+08 | AN38: =SUM(AF38:AK38) -> 4.2570019e+08 | AO38: =SUM(Z38:AB38) -> 2.1467002e+08 | AP38: =SUM(AC38:AE38) -> 2.0781248e+08 | AQ38: =SUM(AF38:AH38) -> 2.0222134e+08 | AR38: =SUM(AI38:AK38) -> 2.2347885e+08 | AT38: =AE38/30 -> 2344728.6
B39: 电视及APP-电商商品 | C39: =C9+C27 -> 2322668.1 | D39: =D9+D27 -> 1618464.3 | E39: 1957856.4 | F39: 2008471.5 | G39: 1904263.7 | H39: =H9+H27 -> 2061669 | I39: =I9+I27 -> 2026612.3 | J39: =J9+J27 -> 1932776.8 | K39: =K9+K27 -> 1967572.1 | L39: =L9+L27 -> 1897732.9 | M39: =M9+M27 -> 2314498.5 | N39: =N9+N27 -> 2337772.1 | O39: =SUM(C39:N39) -> 24350358 | P39: =SUM(C39:H39) -> 11873393 | Q39: =SUM(I39:N39) -> 12476965 | R39: =SUM(C39:E39) -> 5898988.8 | S39: =SUM(F39:H39) -> 5974404.2 | T39: =SUM(I39:K39) -> 5926961.2 | U39: =SUM(L39:N39) -> 6550003.5 | V39: =O39-O9 -> 2589654.6 | X39: 1.12 | Y39: 电视及APP-电商商品 | Z39: =C39*$X39/Z9 -> 13925104 | AA39: =D39*$X39/AA9 -> 12407501 | AB39: =E39*$X39/AB9 -> 10374085 | AC39: =F39*$X39/AC9 -> 14848693 | AD39: =G39*$X39/AD9 -> 17264769 | AE39: =H39*$X39/AE9 -> 13832791 | AF39: =I39*$X39/AF9 -> 16400211 | AG39: =J39*$X39/AG9 -> 15507389 | ... AK39: =N39*$X39/AK9 -> 7781101.4 | AL39: =SUM(Z39:AK39) -> 1.7296494e+08 | AM39: =SUM(Z39:AE39) -> 82652942 | AN39: =SUM(AF39:AK39) -> 90311995 | AO39: =SUM(Z39:AB39) -> 36706690 | AP39: =SUM(AC39:AE39) -> 45946253 | AQ39: =SUM(AF39:AH39) -> 48032775 | AR39: =SUM(AI39:AK39) -> 42279220 | AT39: =AE39/30 -> 461093.03
A40: GMV | B40: 移动端 | C40: =C10+C28 -> 35750000 | D40: =D10+D28 -> 22750000 | E40: 32868553 | F40: 52990246 | G40: 56809414 | H40: =H10+H28 -> 67386218 | I40: =I10+I28 -> 63839575 | J40: =J10+J28 -> 67386218 | K40: =K10+K28 -> 67386218 | L40: =L10+L28 -> 60292932 | M40: =M10+M28 -> 92212719 | N40: =N10+N28 -> 74479504 | O40: =SUM(C40:N40) -> 6.941516e+08 | P40: =SUM(C40:H40) -> 2.6855443e+08 | Q40: =SUM(I40:N40) -> 4.2559717e+08 | R40: =SUM(C40:E40) -> 91368553 | S40: =SUM(F40:H40) -> 1.7718588e+08 | T40: =SUM(I40:K40) -> 1.9861201e+08 | U40: =SUM(L40:N40) -> 2.2698515e+08 | V40: =O40-O10 -> 44151596
B42: 滚动标较年初标 提升% | E42: 提升百分比
B43: 存量整体 | E43: =E34/E4-1 -> 0.015287052 | F43: =F34/F4-1 -> 0.034558769 | G43: 0.062162683 | H43: =H34/H4-1 -> 0.099027152
B44: 仅电视端及APP业务 （含自营业务） | E44: =E35/E5-1 -> 0.019558564 | F44: =F35/F5-1 -> 0.04290616 | G44: 0.077676247 | H44: =H35/H5-1 -> 0.12072677
B45: 数据库营销 | E45: =E36/E6-1 -> 0 | F45: =F36/F6-1 -> 0 | G45: 0 | H45: =H36/H6-1 -> 0
B46: 私域 | E46: =E37/E7-1 -> 0 | F46: =F37/F7-1 -> 0.0065304132 | G46: 0.02163969 | H46: =H37/H7-1 -> 0.039676585
B47: 电视及APP-电视商品（含自营业务） | E47: =E38/E8-1 -> 0.014371518 | F47: =F38/F8-1 -> 0.031931991 | G47: 0.061437198 | H47: =H38/H8-1 -> 0.096118895
B48: 电视及APP-电商商品 | E48: =E39/E9-1 -> 0.03683395 | F48: =F39/F9-1 -> 0.079514883 | G48: 0.10421198 | H48: =H39/H9-1 -> 0.1775805
B49: 移动端 | E49: =E40/E10-1 -> 0.011340097 | F49: =F40/F10-1 -> 0.019043191 | G49: 0.028224686 | H49: =H40/H10-1 -> 0.091274782

Sheet PPT 用滚动表
I1: 当月天数 | J1: 30 | L1: 5月滚动目标 | M1: 同期6月实际
B2: 东方购物 | C2: 6月目标 | D2: 环比目标 | E2: 6月日均标 | F2: 日均目标环比 | G2: 同比实际 | H2: 责任人
B3: 东方购物 | C3: 19241404 | D3: =C3/L3-1 -> 0.05043959 | E3: =C3/$J$1 -> 641380.13 | F3: =E3/(L3/30)-1 -> 0.05043959 | G3: =C3/M3-1 -> -0.0054282526 | L3: 18317478 | M3: 19346421
B4: 电视及APP-电视商品 （含自营业务） | C4: 17271438 | D4: =C4/L4-1 -> 0.048375975 | E4: =C4/$J$1 -> 575714.62 | F4: =E4/(L4/30)-1 -> 0.048375975 | G4: =C4/M4-1 -> 0.001681169 | H4: 张凌云 (温佳敏) | L4: 16474470 | M4: 17242451
B5: 电视及APP-电商商品 | C5: 2061669 | D5: =C5/L5-1 -> 0.082659398 | E5: =C5/$J$1 -> 68722.3 | F5: =E5/(L5/30)-1 -> 0.082659398 | G5: =C5/M5-1 -> 0.098450615 | H5: 张凌云 | L5: 1904263.7 | M5: 1876888.2
B6: 仅电视端及APP业务 （含自营业务） | C6: 15974002 | D6: =C6/L6-1 -> 0.026387976 | E6: =C6/$J$1 -> 532466.73 | F6: =E6/(L6/30)-1 -> 0.026387976 | G6: =C6/M6-1 -> -0.031432435 | H6: 曹俊 (温佳敏) | L6: 15563318 | M6: 16492398
B7: 数据库营销 | C7: 2250000 | D7: =C7/L7-1 -> 0.18421053 | E7: =C7/$J$1 -> 75000 | F7: =E7/(L7/30)-1 -> 0.18421053 | G7: =C7/M7-1 -> 0.010833439 | H7: 赵鹤/王涛 | L7: 1900000 | M7: 2225886
B8: 私域 | C8: 1044268.3 | D8: =C8/L8-1 -> 0.13081855 | E8: =C8/$J$1 -> 34808.945 | F8: =E8/(L8/30)-1 -> 0.13081855 | G8: =C8/M8-1 -> 0.66248511 | H8: 张音祺 | L8: 923462.33 | M8: 628136.96
B9: 白玉兰直播间 | C9: 6月目标 | D9: 环比目标 | E9: 6月日均标 | F9: 日均目标环比 | G9: 同比实际 | H9: 责任人
B10: GMV | C10: 61750000 | D10: =C10/L10-1 -> 0.11764706 | E10: =C10/$J$1 -> 2058333.3 | F10: =E10/(L10/30)-1 -> 0.11764706 | G10: =C10/M10-1 -> 0.44699952 | H10: 许震威 | L10: 55250000 | M10: 42674513

Sheet 邮件
B3: 按“2026年东方购物存量业务目标方案”，在年初计划标基础上，现将1-4月利润差额滚动计入6-12月。
B5: 考虑1-4月利润缺口后，6月滚动利润目标如下：
B7: （1）当月存量利润目标滚动增加 173.4万元，较年初计划标提升 9.9%。其中：电视及APP业务当月增加 172.1万元；私域当月增加 4.0万元；
B8: （2）日均利润目标，存量日均 64.1万元（每日增加 5.8万元）。其中：电视及APP日均 53.2万元（每日增加 5.7万元）；数据库营销日均 7.5万元；私域日均 3.5万元（每日增加 1328元）；
B10: 6月滚动目标（计入1-4月利润缺口）
B11: 东方购物 | C11: 6月目标 | D11: 环比5月滚动标 | E11: 6月日均标 | F11: 日均目标环比5月 | G11: 同比去年实际 | H11: 6月日均销售标 | I11: 同比去年实际 | J11: 责任人 | K11: 备注
B12: 东方购物 | C12: 19241404 | D12: 0.05043959 | E12: 641380.13 | F12: 0.05043959 | G12: -0.0054282526 | H12: 2781284.4 | I12: 0.037361744 | K12: 滚动
B13: 电视商品（含自营业务） | C13: 17271438 | D13: 0.048375975 | E13: 575714.62 | F13: 0.048375975 | G13: 0.001681169 | H13: 2344728.6 | I13: 0.070418458 | J13: 张凌云 (温佳敏) | K13: 滚动
B14: 电商商品 | C14: 2061669 | D14: 0.082659398 | E14: 68722.3 | F14: 0.082659398 | G14: 0.098450615 | H14: 461093.03 | I14: 0.082668374 | J14: 张凌云 | K14: 滚动
B15: 电视端及APP业务 （含自营业务） | C15: 15974002 | D15: 0.026387976 | E15: 532466.73 | F15: 0.026387976 | G15: -0.031432435 | H15: 2114819.9 | I15: -0.049037476 | J15: 曹俊 (温佳敏) | K15: 滚动
B16: 数据库营销 | C16: 2250000 | D16: 0.18421053 | E16: 75000 | F16: 0.18421053 | G16: 0.010833439 | H16: 365112.79 | I16: 0.25131753 | J16: 赵鹤/王涛 | K16: -
B17: 私域 | C17: 1044268.3 | D17: 0.13081855 | E17: 34808.945 | F17: 0.13081855 | G17: 0.66248511 | H17: 289610.42 | I17: 0.75035981 | J17: 张音祺 | K17: 滚动
B19: 6月期间，所有利润业绩追踪将按滚动目标进行统计。滚动目标，中心内下沉方案，由部门负责人依据业务实际情况进行调整。
B21: 以上，请各位领导知晓。如有任何问题，请随时沟通，谢谢！

Sheet 25年月度raw
B1: 2025年销售目标 | X1: 2025年利润目标 | AT1: 2025年目标毛利率
B2: 销售金额 | C2: 1月 | D2: 2月 | E2: 3月 | F2: 4月 | G2: 5月 | H2: 6月 | I2: 7月 | J2: 8月 | K2: 9月 | L2: 10月 | M2: 11月 | N2: 12月 | O2: 合计 | P2: H1 | Q2: H2 | R2: Q1 | S2: Q2 | T2: Q3 | U2: Q4 | X2: 销售利润 | Y2: 1月 | Z2: 2月 | AA2: 3月 | AB2: 4月 | AC2: 5月 | AD2: 6月 | AE2: 7月 | AF2: 8月 | AG2: 9月 | AH2: 10月 | AI2: 11月 | AJ2: 12月 | AK2: 合计 | AL2: H1 | AM2: H2 | AN2: Q1 | AO2: Q2 | AP2: Q3 | AQ2: Q4 | AR2: 1-11月目标 | AS2: 参考税率 | AT2: 毛利率 | AU2: 1月 | AV2: 2月 | AW2: 3月 | AX2: 4月 | AY2: 5月 | AZ2: 6月 | BA2: 7月 | BB2: 8月 | BC2: 9月 | BD2: 10月 | BE2: 11月 | BF2: 12月 | BG2: 合计 | BH2: H1 | BI2: H2 | BJ2: Q1 | BK2: Q2 | BL2: Q3 | BM2: Q4
B3: 存量合计 | C3: 1.2738837e+08 | D3: 85534047 | E3: 94239615 | F3: 91836917 | G3: 84118517 | H3: 81521373 | I3: 84049738 | J3: 86148065 | K3: 85154688 | L3: 87882600 | M3: 1.0197869e+08 | N3: 1.0383854e+08 | O3: 1.1136912e+09 | P3: =SUM(C3:H3) -> 5.6463884e+08 | Q3: =SUM(I3:N3) -> 5.4905233e+08 | R3: =SUM(C3:E3) -> 3.0716203e+08 | S3: =SUM(F3:H3) -> 2.5747681e+08 | T3: =SUM(I3:K3) -> 2.5535249e+08 | U3: =SUM(L3:N3) -> 2.9369983e+08 | X3: 存量合计 | Y3: 29005816 | Z3: 18711086 | AA3: 20581139 | AB3: 20983851 | AC3: 19170313 | AD3: 19119063 | AE3: 18493962 | AF3: 19086307 | AG3: 18941758 | AH3: 19345425 | AI3: 23671327 | AJ3: 24015704 | AK3: 2.5112575e+08 | AL3: =SUM(Y3:AD3) -> 1.2757127e+08 | AM3: =SUM(AE3:AJ3) -> 1.2355448e+08 | AN3: =SUM(Y3:AA3) -> 68298042 | AO3: =SUM(AB3:AD3) -> 59273227 | AP3: =SUM(AE3:AG3) -> 56522026 | AQ3: =SUM(AH3:AJ3) -> 67032456 | AR3: =SUM(Y3:AI3) -> 2.2711005e+08 | AS3: 1.12 | AT3: 存量合计 | AU3: =Y3*1.12/C3 -> 0.25501947 | AV3: =Z3*1.12/D3 -> 0.24500672 | AW3: =AA3*1.12/E3 -> 0.24459858 | AX3: =AB3*1.12/F3 -> 0.25590922 | AY3: =AC3*1.12/G3 -> 0.25524405 | AZ3: =AD3*1.12/H3 -> 0.26267161 | BA3: =AE3*1.12/I3 -> 0.24644023 | BB3: =AF3*1.12/J3 -> 0.24813864 | ... BM3: =AQ3*1.12/U3 -> 0.25562272
B4: 电视端及APP业务 （含自营业务） | C4: 1.2403475e+08 | D4: 82829808 | E4: 91090450 | F4: 88308163 | G4: 80969840 | H4: 78277273 | I4: 81113373 | J4: 82913117 | K4: 81801592 | L4: 84439244 | M4: 97973276 | N4: 99940276 | O4: 1.0736912e+09 | P4: =SUM(C4:H4) -> 5.4551029e+08 | Q4: =SUM(I4:N4) -> 5.2818088e+08 | R4: =SUM(C4:E4) -> 2.9795501e+08 | S4: =SUM(F4:H4) -> 2.4755528e+08 | T4: =SUM(I4:K4) -> 2.4582808e+08 | U4: =SUM(L4:N4) -> 2.8235279e+08 | X4: 电视端及APP业务 （含自营业务） | Y4: 28645816 | Z4: 18418389 | AA4: 20212409 | AB4: 20593967 | AC4: 18790456 | AD4: 18770947 | AE4: 18132278 | AF4: 18686307 | AG4: 18522034 | AH4: 18922926 | AI4: 23220671 | AJ4: 23566696 | AK4: 2.4648289e+08 | AL4: =SUM(Y4:AD4) -> 1.2543198e+08 | AM4: =SUM(AE4:AJ4) -> 1.2105091e+08 | AN4: =SUM(Y4:AA4) -> 67276613 | AO4: =SUM(AB4:AD4) -> 58155370 | AP4: =SUM(AE4:AG4) -> 55340619 | AQ4: =SUM(AH4:AJ4) -> 65710292 | AR4: =SUM(Y4:AI4) -> 2.229162e+08 | AS4: 1.12 | AT4: 电视端及APP业务 （含自营业务） | AU4: =Y4*1.12/C4 -> 0.25866391 | AV4: =Z4*1.12/D4 -> 0.24904796 | AW4: =AA4*1.12/E4 -> 0.24852109 | AX4: =AB4*1.12/F4 -> 0.26119039 | AY4: =AC4*1.12/G4 -> 0.25991543 | AZ4: =AD4*1.12/H4 -> 0.26857681 | BA4: =AE4*1.12/I4 -> 0.25036749 | BB4: =AF4*1.12/J4 -> 0.2524168 | ... BM4: =AQ4*1.12/U4 -> 0.26065096
B5: 电视商品 （含自营业务） | C5: 1.0039486e+08 | D5: 67207084 | E5: 73891482 | F5: 71663194 | G5: 65703962 | H5: 63558636 | I5: 65907430 | J5: 67402668 | K5: 66353311 | L5: 68493914 | M5: 79465401 | N5: 81049050 | O5: 8.71091e+08 | P5: =SUM(C5:H5) -> 4.4241922e+08 | Q5: =SUM(I5:N5) -> 4.2867177e+08 | R5: =SUM(C5:E5) -> 2.4149343e+08 | S5: =SUM(F5:H5) -> 2.0092579e+08 | T5: =SUM(I5:K5) -> 1.9966341e+08 | U5: =SUM(L5:N5) -> 2.2900837e+08 | X5: 电视商品 （含自营业务） | Y5: 25036443 | Z5: 16112983 | AA5: 17680785 | AB5: 18016483 | AC5: 16438390 | AD5: 16424522 | AE5: 15871299 | AF5: 16359118 | AG5: 16201558 | AH5: 16552467 | AI5: 20310277 | AJ5: 20611912 | AK5: 2.1561624e+08 | AL5: =SUM(Y5:AD5) -> 1.0970961e+08 | AM5: =SUM(AE5:AJ5) -> 1.0590663e+08 | AN5: =SUM(Y5:AA5) -> 58830212 | AO5: =SUM(AB5:AD5) -> 50879395 | AP5: =SUM(AE5:AG5) -> 48431975 | AQ5: =SUM(AH5:AJ5) -> 57474656 | AR5: =SUM(Y5:AI5) -> 1.9500433e+08 | AS5: 1.12 | AT5: 电视商品 （含自营业务） | AU5: =Y5*1.12/C5 -> 0.27930529 | AV5: =Z5*1.12/D5 -> 0.26852142 | AW5: =AA5*1.12/E5 -> 0.26799407 | AX5: =AB5*1.12/F5 -> 0.28157357 | AY5: =AC5*1.12/G5 -> 0.28021137 | AZ5: =AD5*1.12/H5 -> 0.2894251 | BA5: =AE5*1.12/I5 -> 0.26970942 | BB5: =AF5*1.12/J5 -> 0.27183215 | ... BM5: =AQ5*1.12/U5 -> 0.28108849
B6: 数据库营销 | C6: 11811974 | D6: 6975715.7 | E6: 10161091 | F6: 10179773 | G6: 7414080.3 | H6: 9520356.6 | I6: 5242451.1 | J6: 5538231.8 | K6: 8015284.5 | L6: 10890354 | M6: 10966638 | N6: 9640319.2 | O6: 1.0635627e+08 | P6: =SUM(C6:H6) -> 56062990 | Q6: =SUM(I6:N6) -> 50293279 | R6: =SUM(C6:E6) -> 28948780 | S6: =SUM(F6:H6) -> 27114210 | T6: =SUM(I6:K6) -> 18795967 | U6: =SUM(L6:N6) -> 31497312 | X6: 数据库营销 | Y6: 2148000 | Z6: 1390000 | AA6: 2077000 | AB6: 2338000 | AC6: 1600000 | AD6: 2255000 | AE6: 1261000 | AF6: 1364000 | AG6: 1424000 | AH6: 1651000 | AI6: 2286000 | AJ6: 1734000 | AK6: 21528000 | AL6: =SUM(Y6:AD6) -> 11808000 | AM6: =SUM(AE6:AJ6) -> 9720000 | AN6: =SUM(Y6:AA6) -> 5615000 | AO6: =SUM(AB6:AD6) -> 6193000 | AP6: =SUM(AE6:AG6) -> 4049000 | AQ6: =SUM(AH6:AJ6) -> 5671000 | AR6: =SUM(Y6:AI6) -> 19794000 | AS6: 1.12 | AT6: 数据库营销 | AU6: =Y6*1.12/C6 -> 0.20367129 | AV6: =Z6*1.12/D6 -> 0.22317423 | AW6: =AA6*1.12/E6 -> 0.22893606 | AX6: =AB6*1.12/F6 -> 0.25723167 | AY6: =AC6*1.12/G6 -> 0.24170226 | AZ6: =AD6*1.12/H6 -> 0.26528418 | BA6: =AE6*1.12/I6 -> 0.2694007 | BB6: =AF6*1.12/J6 -> 0.27584256 | ... BM6: =AQ6*1.12/U6 -> 0.20165277
B7: 私域 | C7: 4603617.4 | D7: 3821384.7 | E7: 5065831.4 | F7: 5880973.7 | G7: 5667562.2 | H7: 5755848.1 | I7: 5519698.7 | J7: 5984947.9 | K7: 6269763.1 | L7: 6526689.4 | M7: 7255416.7 | N7: 7648266.5 | O7: 70000000 | P7: =SUM(C7:H7) -> 30795218 | Q7: =SUM(I7:N7) -> 39204782 | R7: =SUM(C7:E7) -> 13490834 | S7: =SUM(F7:H7) -> 17304384 | T7: =SUM(I7:K7) -> 17774410 | U7: =SUM(L7:N7) -> 21430373 | X7: 私域 | Y7: 499464.29 | Z7: 417339.34 | AA7: 582576.07 | AB7: 652324.83 | AC7: 660892.48 | AD7: 628355.38 | AE7: 649909.8 | AF7: 706821.43 | AG7: 745140.67 | AH7: 766510.72 | AI7: 813263.95 | AJ7: 867401.05 | AK7: 7990000 | AL7: =SUM(Y7:AD7) -> 3440952.4 | AM7: =SUM(AE7:AJ7) -> 4549047.6 | AN7: =SUM(Y7:AA7) -> 1499379.7 | AO7: =SUM(AB7:AD7) -> 1941572.7 | AP7: =SUM(AE7:AG7) -> 2101871.9 | AQ7: =SUM(AH7:AJ7) -> 2447175.7 | AR7: =SUM(Y7:AI7) -> 7122598.9 | AS7: 1.12 | AT7: 私域 | AU7: =Y7*1.12/C7 -> 0.12151314 | AV7: =Z7*1.12/D7 -> 0.12231693 | AW7: =AA7*1.12/E7 -> 0.12880121 | AX7: =AB7*1.12/F7 -> 0.12423178 | AY7: =AC7*1.12/G7 -> 0.13060281 | AZ7: =AD7*1.12/H7 -> 0.12226835 | BA7: =AE7*1.12/I7 -> 0.13187295 | BB7: =AF7*1.12/J7 -> 0.13227183 | ... BM7: =AQ7*1.12/U7 -> 0.12789497
B8: 私域第三方 | C8: 3353617.4 | D8: 2704238.6 | E8: 3149164.7 | F8: 3528754.3 | G8: 3148676.2 | H8: 3244099.7 | I8: 2936365.4 | J8: 3234947.9 | K8: 3353096.5 | L8: 3443356.1 | M8: 4005416.7 | N8: 3898266.5 | O8: 40000000 | P8: =SUM(C8:H8) -> 19128551 | Q8: =SUM(I8:N8) -> 20871449 | R8: =SUM(C8:E8) -> 9207020.7 | S8: =SUM(F8:H8) -> 9921530.1 | T8: =SUM(I8:K8) -> 9524409.8 | U8: =SUM(L8:N8) -> 11347039 | X8: 私域第三方 | Y8: 360000 | Z8: 292697.74 | AA8: 368730.83 | AB8: 389884.35 | AC8: 379856.76 | AD8: 348116.03 | AE8: 361683.61 | AF8: 400000 | AG8: 419724 | AH8: 422498.81 | AI8: 450656.81 | AJ8: 449008.2 | AK8: 4642857.1 | AL8: =SUM(Y8:AD8) -> 2139285.7 | AM8: =SUM(AE8:AJ8) -> 2503571.4 | AN8: =SUM(Y8:AA8) -> 1021428.6 | AO8: =SUM(AB8:AD8) -> 1117857.1 | AP8: =SUM(AE8:AG8) -> 1181407.6 | AQ8: =SUM(AH8:AJ8) -> 1322163.8 | AR8: =SUM(Y8:AI8) -> 4193848.9 | AS8: 1.12 | AT8: 私域第三方 | AU8: =Y8*1.12/C8 -> 0.12022838 | AV8: =Z8*1.12/D8 -> 0.12122506 | AW8: =AA8*1.12/E8 -> 0.13113907 | AX8: =AB8*1.12/F8 -> 0.12374635 | AY8: =AC8*1.12/G8 -> 0.13511697 | AZ8: =AD8*1.12/H8 -> 0.12018433 | BA8: =AE8*1.12/I8 -> 0.13795478 | BB8: =AF8*1.12/J8 -> 0.13848755 | ... BM8: =AQ8*1.12/U8 -> 0.13050307
X9: 电商商品 | Y9: =Y4-Y5 -> 3609372.8 | Z9: =Z4-Z5 -> 2305405.1 | AA9: =AA4-AA5 -> 2531623.6 | AB9: =AB4-AB5 -> 2577483.7 | AC9: =AC4-AC5 -> 2352065.8 | AD9: =AD4-AD5 -> 2346425 | AE9: =AE4-AE5 -> 2260979.3 | AF9: =AF4-AF5 -> 2327189 | ... AQ9: =AQ4-AQ5 -> 8235636.2 | AR9: =SUM(Y9:AI9) -> 27911872
X10: 移动端 目标GMV | Y10: 16000000 | Z10: 16000000 | AA10: 18000000 | AB10: 22000000 | AC10: 28000000 | AD10: 32000000 | AE10: 33000000 | AF10: 35000000 | AG10: 40000000 | AH10: 36000000 | AI10: 74000000 | AJ10: 50000000 | AK10: =SUM(Y10:AJ10) -> 400000000
B11: 2025年实际 | X11: 2025年实际 | AT11: 2025年实际
B12: 销售金额 | C12: 1月 | D12: 2月 | E12: 3月 | F12: 4月 | G12: 5月 | H12: 6月 | I12: 7月 | J12: 8月 | K12: 9月 | L12: 10月 | M12: 11月 | N12: 12月 | O12: 合计 | P12: H1 | Q12: H2 | R12: Q1 | S12: Q2 | T12: Q3 | U12: Q4 | X12: 销售利润 | Y12: 1月 | Z12: 2月 | AA12: 3月 | AB12: 4月 | AC12: 5月 | AD12: 6月 | AE12: 7月 | AF12: 8月 | AG12: 9月 | AH12: 10月 | AI12: 11月 | AJ12: 12月 | AK12: 合计 | AL12: H1 | AM12: H2 | AN12: Q1 | AO12: Q2 | AP12: Q3 | AQ12: Q4 | AR12: 1.1-11.20月缺口 | AS12: 参考税率 | AT12: 毛利率 | AU12: 1月 | AV12: 2月 | AW12: 3月 | AX12: 4月 | AY12: 5月 | AZ12: 6月 | BA12: 7月 | BB12: 8月 | BC12: 9月 | BD12: 10月 | BE12: 11月 | BF12: 12月 | BG12: 合计 | BH12: H1 | BI12: H2 | BJ12: Q1 | BK12: Q2 | BL12: Q3 | BM12: Q4
B13: 存量合计 | C13: =C14+C18 -> 1.102224e+08 | D13: =D14+D18 -> 83609413 | E13: =E14+E18 -> 86799137 | F13: =F14+F18 -> 86919721 | G13: =G14+G18 -> 85535277 | H13: =H14+H18 -> 80433401 | I13: =I14+I18 -> 82719754 | J13: =J14+J18 -> 76924778 | ... N13: =N14+N18 -> 0 | O13: =SUM(C13:N13) -> 9.6188597e+08 | P13: =SUM(C13:H13) -> 5.3351935e+08 | Q13: =SUM(I13:N13) -> 4.2836662e+08 | R13: =SUM(C13:E13) -> 2.8063095e+08 | S13: =SUM(F13:H13) -> 2.528884e+08 | T13: =SUM(I13:K13) -> 2.4478307e+08 | U13: =SUM(L13:N13) -> 1.8358355e+08 | X13: 存量合计 | Y13: =Y14+Y18 -> 26183689 | Z13: =Z14+Z18 -> 18907276 | AA13: =AA14+AA18 -> 21181039 | AB13: =AB14+AB18 -> 20419943 | AC13: =AC14+AC18 -> 19028404 | AD13: =AD14+AD18 -> 19346421 | AE13: =AE14+AE18 -> 18855792 | AF13: =AF14+AF18 -> 17898504 | ... AJ13: =AJ14+AJ18 -> 0 | AK13: =SUM(Y13:AJ13) -> 2.1954316e+08 | AL13: =SUM(Y13:AD13) -> 1.2506677e+08 | AM13: =SUM(AE13:AJ13) -> 94476388 | AN13: =SUM(Y13:AA13) -> 66272004 | AO13: =SUM(AB13:AD13) -> 58794768 | AP13: =SUM(AE13:AG13) -> 54916349 | AQ13: =SUM(AH13:AJ13) -> 39560039 | AR13: =IF(AK13-AR3<0,AK13-AR3,0) -> -7566886.5 | AS13: 1.12 | AT13: 存量合计 | AU13: =IFERROR(Y13*1.12/C13,"") -> 0.26605964 | AV13: =IFERROR(Z13*1.12/D13,"") -> 0.2532747 | AW13: =IFERROR(AA13*1.12/E13,"") -> 0.27330645 | AX13: =IFERROR(AB13*1.12/F13,"") -> 0.26312022 | AY13: =IFERROR(AC13*1.12/G13,"") -> 0.24915816 | AZ13: =IFERROR(AD13*1.12/H13,"") -> 0.26939047 | BA13: =IFERROR(AE13*1.12/I13,"") -> 0.25530162 | BB13: =IFERROR(AF13*1.12/J13,"") -> 0.26059646 | ... BM13: =IFERROR(AQ13*1.12/U13,"") -> 0.24134648
B14: 电视端及APP业务 （含自营业务） | C14: 1.0781329e+08 | D14: 81747623 | E14: 84492124 | F14: 84646543 | G14: 83475150 | H14: 78490927 | I14: 80703402 | J14: 74913585 | K14: 83150977 | L14: 90542776 | M14: 88943142 | O14: =SUM(C14:N14) -> 9.3891954e+08 | P14: =SUM(C14:H14) -> 5.2066566e+08 | Q14: =SUM(I14:N14) -> 418253882 | R14: =SUM(C14:E14) -> 2.7405304e+08 | S14: =SUM(F14:H14) -> 246612620 | T14: =SUM(I14:K14) -> 238767964 | U14: =SUM(L14:N14) -> 179485918 | X14: 电视端及APP业务 （含自营业务） | Y14: 25910624 | Z14: 18677402 | AA14: 20898078 | AB14: 20177139 | AC14: 18790332 | AD14: 19119339 | AE14: 18619342 | AF14: 17665712 | AG14: 17937357 | AH14: 17492227 | AI14: 21609474 | AK14: =SUM(Y14:AJ14) -> 2.1689703e+08 | AL14: =SUM(Y14:AD14) -> 1.2357291e+08 | AM14: =SUM(AE14:AJ14) -> 93324112 | AN14: =SUM(Y14:AA14) -> 65486104 | AO14: =SUM(AB14:AD14) -> 58086810 | AP14: =SUM(AE14:AG14) -> 54222411 | AQ14: =SUM(AH14:AJ14) -> 39101701 | AR14: =IF(AK14-AR4<0,AK14-AR4,0) -> -6019171.2 | AS14: 1.12 | AT14: 电视端及APP业务 （含自营业务） | AU14: =IFERROR(Y14*1.12/C14,"") -> 0.2691681 | AV14: =IFERROR(Z14*1.12/D14,"") -> 0.25589356 | AW14: =IFERROR(AA14*1.12/E14,"") -> 0.2770181 | AX14: =IFERROR(AB14*1.12/F14,"") -> 0.26697364 | AY14: =IFERROR(AC14*1.12/G14,"") -> 0.25211302 | AZ14: =IFERROR(AD14*1.12/H14,"") -> 0.272817 | BA14: =IFERROR(AE14*1.12/I14,"") -> 0.25839882 | BB14: =IFERROR(AF14*1.12/J14,"") -> 0.26411227 | ... BM14: =IFERROR(AQ14*1.12/U14,"") -> 0.24399633
B15: 电视商品 （含自营业务） | C15: 91060796 | D15: 71242893 | E15: 72887479 | F15: 72173433 | G15: 69886466 | H15: 65714355 | I15: 68868780 | J15: 65116614 | K15: 71528972 | L15: 79916867 | M15: 73648526 | O15: =SUM(C15:N15) -> 8.0204518e+08 | P15: =SUM(C15:H15) -> 4.4296542e+08 | Q15: =SUM(I15:N15) -> 3.5907976e+08 | R15: =SUM(C15:E15) -> 2.3519117e+08 | S15: =SUM(F15:H15) -> 2.0777425e+08 | T15: =SUM(I15:K15) -> 2.0551437e+08 | U15: =SUM(L15:N15) -> 1.5356539e+08 | X15: 电视商品 （含自营业务） | Y15: 23141348 | Z15: 16740906 | AA15: 18651063 | AB15: 18127100 | AC15: 17050642 | AD15: 17242451 | AE15: 17060422 | AF15: 16235447 | AG15: 16150202 | AH15: 15755887 | AI15: 19410097 | AK15: =SUM(Y15:AJ15) -> 1.9556557e+08 | AL15: =SUM(Y15:AD15) -> 1.1095351e+08 | AM15: =SUM(AE15:AJ15) -> 84612055 | AN15: =SUM(Y15:AA15) -> 58533318 | AO15: =SUM(AB15:AD15) -> 52420192 | AP15: =SUM(AE15:AG15) -> 49446071 | AQ15: =SUM(AH15:AJ15) -> 35165984 | AR15: =IF(AK15-AR5<0,AK15-AR5,0) -> 0 | AS15: 1.12 | AT15: 电视商品 （含自营业务） | AU15: =IFERROR(Y15*1.12/C15,"") -> 0.28462644 | AV15: =IFERROR(Z15*1.12/D15,"") -> 0.26318155 | AW15: =IFERROR(AA15*1.12/E15,"") -> 0.28659505 | AX15: =IFERROR(AB15*1.12/F15,"") -> 0.28129952 | AY15: =IFERROR(AC15*1.12/G15,"") -> 0.27325346 | AZ15: =IFERROR(AD15*1.12/H15,"") -> 0.29387103 | BA15: =IFERROR(AE15*1.12/I15,"") -> 0.27745043 | BB15: =IFERROR(AF15*1.12/J15,"") -> 0.27924826 | ... BM15: =IFERROR(AQ15*1.12/U15,"") -> 0.25647642
B16: 数据库营销 | C16: 11875837 | D16: 9505244.6 | E16: 8448582.2 | F16: 10411125 | G16: 7751860 | H16: 8753480.6 | I16: 9067021.2 | J16: 7495744.8 | K16: 13999988 | L16: 18029060 | M16: 16780507 | O16: =SUM(C16:N16) -> 1.2211845e+08 | P16: =SUM(C16:H16) -> 56746130 | Q16: =SUM(I16:N16) -> 65372320 | R16: =SUM(C16:E16) -> 29829664 | S16: =SUM(F16:H16) -> 26916466 | T16: =SUM(I16:K16) -> 30562754 | U16: =SUM(L16:N16) -> 34809567 | X16: 数据库营销 | Y16: 2549751.2 | Z16: 1880081.8 | AA16: 2130051.2 | AB16: 2615080.4 | AC16: 1752152.4 | AD16: 2225886 | AE16: 1876419.1 | AF16: 1908652.7 | AG16: 2008057.6 | AH16: 1945294.6 | AI16: 3494718 | AK16: =SUM(Y16:AJ16) -> 24386145 | AL16: =SUM(Y16:AD16) -> 13153003 | AM16: =SUM(AE16:AJ16) -> 11233142 | AN16: =SUM(Y16:AA16) -> 6559884.2 | AO16: =SUM(AB16:AD16) -> 6593118.8 | AP16: =SUM(AE16:AG16) -> 5793129.4 | AQ16: =SUM(AH16:AJ16) -> 5440012.6 | AR16: =IF(AK16-AR6<0,AK16-AR6,0) -> 0 | AS16: 1.12 | AT16: 数据库营销 | AU16: =IFERROR(Y16*1.12/C16,"") -> 0.24046484 | AV16: =IFERROR(Z16*1.12/D16,"") -> 0.22152945 | AW16: =IFERROR(AA16*1.12/E16,"") -> 0.28237369 | AX16: =IFERROR(AB16*1.12/F16,"") -> 0.28132311 | AY16: =IFERROR(AC16*1.12/G16,"") -> 0.25315353 | AZ16: =IFERROR(AD16*1.12/H16,"") -> 0.28480012 | BA16: =IFERROR(AE16*1.12/I16,"") -> 0.23178388 | BB16: =IFERROR(AF16*1.12/J16,"") -> 0.28518727 | ... BM16: =IFERROR(AQ16*1.12/U16,"") -> 0.17503275
B17: 私域 | C17: 5280469.7 | D17: 5228202.1 | E17: 5686460.7 | F17: 4949084.3 | G17: 4623575.5 | H17: 4963729.5 | I17: 5789922.8 | J17: 7084063.3 | K17: 5517952.4 | L17: 6676835 | M17: 5965314.6 | O17: =SUM(C17:N17) -> 61765610 | P17: =SUM(C17:H17) -> 30731522 | Q17: =SUM(I17:N17) -> 31034088 | R17: =SUM(C17:E17) -> 16195133 | S17: =SUM(F17:H17) -> 14536389 | T17: =SUM(I17:K17) -> 18391938 | U17: =SUM(L17:N17) -> 12642150 | X17: 私域 | Y17: 573137.28 | Z17: 613994.73 | AA17: 694290.26 | AB17: 571341.18 | AC17: 565277.8 | AD17: 628136.96 | AE17: 728343.65 | AF17: 803735.23 | AG17: 605885.04 | AH17: 791985.12 | AI17: 680080.68 | AK17: =SUM(Y17:AJ17) -> 7256207.9 | AL17: =SUM(Y17:AD17) -> 3646178.2 | AM17: =SUM(AE17:AJ17) -> 3610029.7 | AN17: =SUM(Y17:AA17) -> 1881422.3 | AO17: =SUM(AB17:AD17) -> 1764755.9 | AP17: =SUM(AE17:AG17) -> 2137963.9 | AQ17: =SUM(AH17:AJ17) -> 1472065.8 | AR17: =IF(AK17-AR7<0,AK17-AR7,0) -> 0 | AS17: 1.12 | AT17: 私域 | AU17: =IFERROR(Y17*1.12/C17,"") -> 0.12156376 | AV17: =IFERROR(Z17*1.12/D17,"") -> 0.13153166 | AW17: =IFERROR(AA17*1.12/E17,"") -> 0.13674676 | AX17: =IFERROR(AB17*1.12/F17,"") -> 0.12929707 | AY17: =IFERROR(AC17*1.12/G17,"") -> 0.13693107 | AZ17: =IFERROR(AD17*1.12/H17,"") -> 0.14173081 | BA17: =IFERROR(AE17*1.12/I17,"") -> 0.14089046 | BB17: =IFERROR(AF17*1.12/J17,"") -> 0.12707163 | ... BM17: =IFERROR(AQ17*1.12/U17,"") -> 0.13041403
B18: 私域第三方 | C18: 2409109.3 | D18: 1861790.4 | E18: 2307012.9 | F18: 2273177.9 | G18: 2060127.2 | H18: 1942473.6 | I18: 2016351.9 | J18: 2011193.3 | K18: 1987563.9 | L18: 1931179.4 | M18: 2166452.5 | O18: =SUM(C18:N18) -> 22966432 | P18: =SUM(C18:H18) -> 12853691 | Q18: =SUM(I18:N18) -> 10112741 | R18: =SUM(C18:E18) -> 6577912.6 | S18: =SUM(F18:H18) -> 6275778.7 | T18: =SUM(I18:K18) -> 6015109.1 | U18: =SUM(L18:N18) -> 4097631.8 | X18: 私域第三方 | Y18: 273065.38 | Z18: 229873.77 | AA18: 282960.64 | AB18: 242804.11 | AC18: 238071.56 | AD18: 227082.54 | AE18: 236449.69 | AF18: 232792.52 | AG18: 224695.94 | AH18: 223616 | AI18: 234721.5 | AK18: =SUM(Y18:AJ18) -> 2646133.6 | AL18: =SUM(Y18:AD18) -> 1493858 | AM18: =SUM(AE18:AJ18) -> 1152275.6 | AN18: =SUM(Y18:AA18) -> 785899.79 | AO18: =SUM(AB18:AD18) -> 707958.21 | AP18: =SUM(AE18:AG18) -> 693938.15 | AQ18: =SUM(AH18:AJ18) -> 458337.5 | AR18: =IF(AK18-AR8<0,AK18-AR8,0) -> -1547715.3 | AS18: 1.12 | AT18: 私域第三方 | AU18: =IFERROR(Y18*1.12/C18,"") -> 0.12694867 | AV18: =IFERROR(Z18*1.12/D18,"") -> 0.1382855 | AW18: =IFERROR(AA18*1.12/E18,"") -> 0.13737067 | AX18: =IFERROR(AB18*1.12/F18,"") -> 0.11963015 | AY18: =IFERROR(AC18*1.12/G18,"") -> 0.12942897 | AZ18: =IFERROR(AD18*1.12/H18,"") -> 0.13093226 | BA18: =IFERROR(AE18*1.12/I18,"") -> 0.13133802 | BB18: =IFERROR(AF18*1.12/J18,"") -> 0.12963827 | ... BM18: =IFERROR(AQ18*1.12/U18,"") -> 0.12527675
X19: 电商商品 | Y19: =Y14-Y15 -> 2769275.6 | Z19: =Z14-Z15 -> 1936495.5 | AA19: =AA14-AA15 -> 2247015 | AB19: =AB14-AB15 -> 2050039 | AC19: =AC14-AC15 -> 1739690.9 | AD19: =AD14-AD15 -> 1876887.7 | AE19: =AE14-AE15 -> 1558920.4 | AF19: =AF14-AF15 -> 1430264.4 | ... AQ19: =AQ14-AQ15 -> 3935717.4 | AR19: =IF(AK19-AR9<0,AK19-AR9,0) -> -6580411.6
X20: 移动端 实际GMV | Y20: 19869985 | Z20: 18356031 | AA20: 22268977 | AB20: 36683170 | AC20: 31682217 | AD20: 42674514 | AE20: 40550181 | AF20: 49675432 | AG20: 35222909 | AH20: 33073320 | AI20: 53969000 | AK20: =SUM(Y20:AJ20) -> 384025736
B21: 2025年达成 | X21: 2025年达成
B22: 销售金额 | C22: 1月 | D22: 2月 | E22: 3月 | F22: 4月 | G22: 5月 | H22: 6月 | I22: 7月 | J22: 8月 | K22: 9月 | L22: 10月 | M22: 11月 | N22: 12月 | O22: 合计 | P22: H1 | Q22: H2 | R22: Q1 | S22: Q2 | T22: Q3 | U22: Q4 | X22: 销售利润 | Y22: 1月 | Z22: 2月 | AA22: 3月 | AB22: 4月 | AC22: 5月 | AD22: 6月 | AE22: 7月 | AF22: 8月 | AG22: 9月 | AH22: 10月 | AI22: 11月 | AJ22: 12月 | AK22: 合计 | AL22: H1 | AM22: H2 | AN22: Q1 | AO22: Q2 | AP22: Q3 | AQ22: Q4
B23: 存量合计 | C23: =IFERROR(C13/C3,"") -> 0.86524699 | D23: =IFERROR(D13/D3,"") -> 0.97749863 | E23: =IFERROR(E13/E3,"") -> 0.92104724 | F23: =IFERROR(F13/F3,"") -> 0.94645731 | G23: =IFERROR(G13/G3,"") -> 1.0168424 | H23: =IFERROR(H13/H3,"") -> 0.98665414 | I23: =IFERROR(I13/I3,"") -> 0.98417623 | J23: =IFERROR(J13/J3,"") -> 0.89293681 | ... U23: =IFERROR(U13/U3,"") -> 0.62507202 | X23: 存量合计 | Y23: =IFERROR(Y13/Y3,"") -> 0.9027048 | Z23: =IFERROR(Z13/Z3,"") -> 1.0104852 | AA23: =IFERROR(AA13/AA3,"") -> 1.029148 | AB23: =IFERROR(AB13/AB3,"") -> 0.97312655 | AC23: =IFERROR(AC13/AC3,"") -> 0.99259747 | AD23: =IFERROR(AD13/AD3,"") -> 1.0118917 | AE23: =IFERROR(AE13/AE3,"") -> 1.0195648 | AF23: =IFERROR(AF13/AF3,"") -> 0.93776675 | ... AQ23: =IFERROR(AQ13/AQ3,"") -> 0.59016246
B24: 电视端及APP业务 （含自营业务） | C24: =IFERROR(C14/C4,"") -> 0.86921844 | D24: =IFERROR(D14/D4,"") -> 0.98693483 | E24: =IFERROR(E14/E4,"") -> 0.92756292 | F24: =IFERROR(F14/F4,"") -> 0.95853589 | G24: =IFERROR(G14/G4,"") -> 1.0309413 | H24: =IFERROR(H14/H4,"") -> 1.0027294 | I24: =IFERROR(I14/I4,"") -> 0.99494571 | J24: =IFERROR(J14/J4,"") -> 0.9035191 | ... U24: =IFERROR(U14/U4,"") -> 0.63567962 | X24: 电视端及APP业务 （含自营业务） | Y24: =IFERROR(Y14/Y4,"") -> 0.90451688 | Z24: =IFERROR(Z14/Z4,"") -> 1.0140628 | AA24: =IFERROR(AA14/AA4,"") -> 1.0339232 | AB24: =IFERROR(AB14/AB4,"") -> 0.9797597 | AC24: =IFERROR(AC14/AC4,"") -> 0.99999342 | AD24: =IFERROR(AD14/AD4,"") -> 1.0185602 | AE24: =IFERROR(AE14/AE4,"") -> 1.0268617 | AF24: =IFERROR(AF14/AF4,"") -> 0.94538271 | ... AQ24: =IFERROR(AQ14/AQ4,"") -> 0.59506205
B25: 电视商品 （含自营业务） | C25: =IFERROR(C15/C5,"") -> 0.90702645 | D25: =IFERROR(D15/D5,"") -> 1.0600503 | E25: =IFERROR(E15/E5,"") -> 0.98641247 | F25: =IFERROR(F15/F5,"") -> 1.00712 | G25: =IFERROR(G15/G5,"") -> 1.0636568 | H25: =IFERROR(H15/H5,"") -> 1.033917 | I25: =IFERROR(I15/I5,"") -> 1.044932 | J25: =IFERROR(J15/J5,"") -> 0.96608362 | ... U25: =IFERROR(U15/U5,"") -> 0.67056674 | X25: 电视商品 （含自营业务） | Y25: =IFERROR(Y15/Y5,"") -> 0.92430655 | Z25: =IFERROR(Z15/Z5,"") -> 1.03897 | AA25: =IFERROR(AA15/AA5,"") -> 1.0548776 | AB25: =IFERROR(AB15/AB5,"") -> 1.0061397 | AC25: =IFERROR(AC15/AC5,"") -> 1.0372452 | AD25: =IFERROR(AD15/AD5,"") -> 1.0497993 | AE25: =IFERROR(AE15/AE5,"") -> 1.0749229 | AF25: =IFERROR(AF15/AF5,"") -> 0.99244025 | ... AQ25: =IFERROR(AQ15/AQ5,"") -> 0.61185201
B26: 数据库营销 | C26: =IFERROR(C16/C6,"") -> 1.0054067 | D26: =IFERROR(D16/D6,"") -> 1.3626193 | E26: =IFERROR(E16/E6,"") -> 0.83146412 | F26: =IFERROR(F16/F6,"") -> 1.0227266 | G26: =IFERROR(G16/G6,"") -> 1.0455592 | H26: =IFERROR(H16/H6,"") -> 0.91944881 | I26: =IFERROR(I16/I6,"") -> 1.7295385 | J26: =IFERROR(J16/J6,"") -> 1.3534545 | ... U26: =IFERROR(U16/U6,"") -> 1.1051599 | X26: 数据库营销 | Y26: =IFERROR(Y16/Y6,"") -> 1.187035 | Z26: =IFERROR(Z16/Z6,"") -> 1.3525768 | AA26: =IFERROR(AA16/AA6,"") -> 1.0255422 | AB26: =IFERROR(AB16/AB6,"") -> 1.1185117 | AC26: =IFERROR(AC16/AC6,"") -> 1.0950953 | AD26: =IFERROR(AD16/AD6,"") -> 0.98708914 | AE26: =IFERROR(AE16/AE6,"") -> 1.4880405 | AF26: =IFERROR(AF16/AF6,"") -> 1.3993055 | ... AQ26: =IFERROR(AQ16/AQ6,"") -> 0.95926867
B27: 私域 | C27: =IFERROR(C17/C7,"") -> 1.1470262 | D27: =IFERROR(D17/D7,"") -> 1.3681434 | E27: =IFERROR(E17/E7,"") -> 1.1225128 | F27: =IFERROR(F17/F7,"") -> 0.84154165 | G27: =IFERROR(G17/G7,"") -> 0.81579617 | H27: =IFERROR(H17/H7,"") -> 0.86238021 | I27: =IFERROR(I17/I7,"") -> 1.0489563 | J27: =IFERROR(J17/J7,"") -> 1.1836466 | ... U27: =IFERROR(U17/U7,"") -> 0.58991739 | X27: 私域 | Y27: =IFERROR(Y17/Y7,"") -> 1.147504 | Z27: =IFERROR(Z17/Z7,"") -> 1.4712122 | AA27: =IFERROR(AA17/AA7,"") -> 1.191759 | AB27: =IFERROR(AB17/AB7,"") -> 0.8758538 | AC27: =IFERROR(AC17/AC7,"") -> 0.85532491 | AD27: =IFERROR(AD17/AD7,"") -> 0.99965239 | AE27: =IFERROR(AE17/AE7,"") -> 1.1206842 | AF27: =IFERROR(AF17/AF7,"") -> 1.1371121 | ... AQ27: =IFERROR(AQ17/AQ7,"") -> 0.60153662
B28: 私域第三方 | C28: =IFERROR(C18/C8,"") -> 0.71836139 | D28: =IFERROR(D18/D8,"") -> 0.68847121 | E28: =IFERROR(E18/E8,"") -> 0.7325793 | F28: =IFERROR(F18/F8,"") -> 0.64418707 | G28: =IFERROR(G18/G8,"") -> 0.65428361 | H28: =IFERROR(H18/H8,"") -> 0.59877123 | I28: =IFERROR(I18/I8,"") -> 0.68668289 | J28: =IFERROR(J18/J8,"") -> 0.62170809 | ... U28: =IFERROR(U18/U8,"") -> 0.36111903 | X28: 私域第三方 | Y28: =IFERROR(Y18/Y8,"") -> 0.75851494 | Z28: =IFERROR(Z18/Z8,"") -> 0.78536229 | AA28: =IFERROR(AA18/AA8,"") -> 0.76739078 | AB28: =IFERROR(AB18/AB8,"") -> 0.62275931 | AC28: =IFERROR(AC18/AC8,"") -> 0.62674035 | AD28: =IFERROR(AD18/AD8,"") -> 0.65231855 | AE28: =IFERROR(AE18/AE8,"") -> 0.65374731 | AF28: =IFERROR(AF18/AF8,"") -> 0.5819813 | ... AQ28: =IFERROR(AQ18/AQ8,"") -> 0.34665712

Sheet 历史数据23
A1: 历年目标拟订逻辑
A2: 2023年，基于业务上报的预算目标，适当上浮调整；其中，购物零售版块（电视/电商）因OPG已限定目标，整体不动；旅游、本地生活、全球购、汽车等依据外部市场变化、历年业绩规模，有所上调。
B5: 年度 | C5: 销售额目标 | D5: 销售利润目标 | E5: 实际销售额 | F5: 实际销售利润 | G5: 利润目标同比目标 | H5: 利润目标同比实际 | I5: 备注
A6: 购物零售(含本地生活) | B6: 2025年 | D6: =SUM(C16:N16) -> 2.2853141e+08 | G6: =D6/D7-1 -> -0.37391558 | H6: =D6/F7-1 -> -0.23627939 | I6: 上报OPG版，日均利润额为62.6万;
B7: 2024年 | C7: 1.7944295e+09 | D7: =SUM(C17:N17) -> 3.6501692e+08 | E7: 1.3074093e+09 | F7: =SUM(C24:N24) -> 2.992343e+08 | G7: =D7/D8-1 -> -0.39519099 | H7: =D7/F8-1 -> -0.1014619 | I7: 框定：TV电视商品下降15%、IC电商商品增长10%，购物零售较2023年实际合计下降12%；
B8: 2023年 | C8: 2.8101841e+09 | D8: =SUM(C18:N18) -> 6.0352428e+08 | E8: 1.9235652e+09 | F8: =SUM(C25:N25) -> 4.0623422e+08 | G8: =D8/D9-1 -> -0.3264238 | H8: 剔除疫情影响天数，同比持平/同比增长5.5% | I8: 上报OPG版，日均利润额为147.8万；目标方案取高，日均170万，年中调整到165万（业务板块间调整），较财务底限上调11.6%-15%；
B9: 2022年 | C9: 4.1035663e+09 | D9: =SUM(C19:N19) -> 896000000 | E9: 2289870000 | F9: 489840000 | G9: =D9/D10-1 -> -0.088924433 | H9: =D9/F10-1 -> 0.17163406 | I9: =F8/D8 -> 0.67310336 | J9: 2023年达成情况
B10: 2021年 | C10: 4176781427 | D10: =SUM(C20:N20) -> 9.83453e+08 | E10: 3449498000 | F10: =SUM(C26:N26) -> 764743901
B11: 2020年
A12: 旅行路线代销 | B12: 2024年 | C12: 1.3490909e+08 | D12: 14000000 | E12: 1.2760947e+08 | F12: 15857979 | G12: =D12/D13-1 -> -0.076224101 | H12: =F12/F13-1 -> 0.17248221
B13: 2023年 | C13: 1.9255849e+08 | D13: 15155191 | E13: 103472155 | F13: 13525134
A14: 购物零售(含本地生活)
A15: 利润目标 | B15: 上年12月 | C15: 1月 | D15: 2月 | E15: 3月 | F15: 4月 | G15: 5月 | H15: 6月 | I15: 7月 | J15: 8月 | K15: 9月 | L15: 10月 | M15: 11月 | N15: 12月
A16: 25年目标底限 | B16: 34045559 | C16: 26173805 | D16: 17686050 | E16: 19048960 | F16: 19350240 | G16: 17292098 | H16: 17358990 | I16: 16452786 | J16: 16855074 | K16: 17312645 | L16: 17776477 | M16: 21990711 | N16: 21233571
A17: 24年目标 | B17: 56333846 | C17: 44747857 | D17: 29199126 | E17: 29378415 | F17: 32095025 | G17: 28744117 | H17: 27194925 | I17: 24260261 | J17: 25705711 | K17: 27796192 | L17: 26391657 | M17: 35458074 | N17: 34045559
A18: 23年目标 | B18: 86894556 | C18: 47378545 | D18: 45126193 | E18: 54136311 | F18: 56001174 | G18: 50966188 | H18: 49063521 | I18: 45903819 | J18: 46153688 | K18: 47003227 | L18: 47193680 | M18: 58264087 | N18: 56333846
A19: 22年目标 | B19: 99574701 | C19: 88504000 | D19: 55315000 | E19: 73317282 | F19: 76937888 | G19: 76937888 | H19: 73317282 | I19: 66076069 | J19: 70601827 | K19: 66981220 | L19: 71506978 | M19: 89610011 | N19: 86894556
A20: 21年目标 | B20: 1.0542734e+08 | C20: 89580981 | D20: 59114094 | E20: 63618869 | F20: 84540808 | G20: 83124036 | H20: 79579593 | I20: 78427766 | J20: 78023284 | K20: 87858917 | L20: 82285396 | M20: 97724555 | N20: 99574701
A21: 购物零售（含本地生活）
A22: 利润实际 | B22: 上年12月 | C22: 1月 | D22: 2月 | E22: 3月 | F22: 4月 | G22: 5月 | H22: 6月 | I22: 7月 | J22: 8月 | K22: 9月 | L22: 10月 | M22: 11月 | N22: 12月
A23: 25年目标底限 | B23: 27754349 | C23: 26173805 | D23: 17686050 | E23: 19048960 | F23: 19350240 | G23: 17292098 | H23: 17358990 | I23: 16452786 | J23: 16855074 | K23: 17312645 | L23: 17776477 | M23: 21990711 | N23: 21233571
A24: 24年实际 | B24: 37653592 | C24: 34006764 | D24: 23684768 | E24: 25054034 | F24: 24919117 | G24: 22040447 | H24: 22879456 | I24: 21936037 | J24: 21669839 | K24: 22210990 | L24: 23889521 | M24: 29188984 | N24: 27754349
A25: 23年实际 | B25: 52710000 | C25: 48124681 | D25: 30883670 | E25: 33760031 | F25: 34204404 | G25: 31976609 | H25: 31037674 | I25: 28669117 | J25: 30480858 | K25: 30993082 | L25: 30396484 | M25: 38054014 | N25: 37653592
A26: 21年实际 | B26: 93174000 | C26: 91162158 | D26: 60438349 | E26: 65649438 | F26: 59056154 | G26: 57947230 | H26: 59862586 | I26: 54090581 | J26: 57695733 | K26: 57445917 | L26: 58112582 | M26: 73618329 | N26: 69664844
A28: 购物零售同比(含本地生活)
A29: 利润目标 | B29: 上年12月 | C29: 1月 | D29: 2月 | E29: 3月 | F29: 4月 | G29: 5月 | H29: 6月 | I29: 7月 | J29: 8月 | K29: 9月 | L29: 10月 | M29: 11月 | N29: 12月
A30: 25年底限 | B30: =B17/B18-1 -> -0.35169879 | C30: =C17/C18-1 -> -0.055524884 | D30: =D17/D18-1 -> -0.35294505 | E30: =E17/E18-1 -> -0.45732515 | F30: =F17/F18-1 -> -0.42688657 | G30: =G17/G18-1 -> -0.43601595 | H30: =H17/H18-1 -> -0.44572008 | I30: =I17/I18-1 -> -0.47149797 | ... N30: =N17/N18-1 -> -0.39564646
A31: 24年 | B31: =B18/B19-1 -> -0.12734304 | C31: =C18/C19-1 -> -0.46467341 | D31: =D18/D19-1 -> -0.1841961 | E31: =E18/E19-1 -> -0.26161595 | F31: =F18/F19-1 -> -0.27212489 | G31: =G18/G19-1 -> -0.3375671 | H31: =H18/H19-1 -> -0.33080551 | I31: =I18/I19-1 -> -0.30528829 | ... N31: =N18/N19-1 -> -0.35169879
A32: 23年 | B32: =B19/B20-1 -> -0.05551347 | C32: =C19/C20-1 -> -0.012022429 | D32: =D19/D20-1 -> -0.064267144 | E32: =E19/E20-1 -> 0.15244554 | F32: =F19/F20-1 -> -0.089931954 | G32: =G19/G20-1 -> -0.074420693 | H32: =H19/H20-1 -> -0.07869243 | I32: =I19/I20-1 -> -0.15749138 | ... N32: =N19/N20-1 -> -0.12734304
A33: 购物零售（含本地生活）同比 | P33: * 25年春节：1.28-2.4
A34: 利润实际 | B34: 上年12月 | C34: 1月 | D34: 2月 | E34: 3月 | F34: 4月 | G34: 5月 | H34: 6月 | I34: 7月 | J34: 8月 | K34: 9月 | L34: 10月 | M34: 11月 | N34: 12月 | P34: * 24年春节：2.10-2.17
A35: 25年e | B35: =B23/B24-1 -> -0.26290304 | C35: =C23/C24-1 -> -0.23033532 | D35: =D23/D24-1 -> -0.25327325 | E35: =E23/E24-1 -> -0.23968491 | F35: =F23/F24-1 -> -0.22347809 | G35: =G23/G24-1 -> -0.21543794 | H35: =H23/H24-1 -> -0.24128481 | I35: =I23/I24-1 -> -0.24996546 | ... N35: =N23/N24-1 -> -0.23494617 | P35: * 23年春节：1.21-1.27
A36: 24年 | B36: =B24/B25-1 -> -0.28564613 | C36: =C24/C25-1 -> -0.29336126 | D36: =D24/D25-1 -> -0.23309736 | E36: =E24/E25-1 -> -0.25787883 | F36: =F24/F25-1 -> -0.27146467 | G36: =G24/G25-1 -> -0.31073219 | H36: =H24/H25-1 -> -0.2628489 | I36: =I24/I25-1 -> -0.23485481 | ... N36: =N24/N25-1 -> -0.26290304 | P36: * 22年春节：1.31-2.6，年度内因疫情管控，数据不做参考
A37: 23年 | B37: =B25/B26-1 -> -0.43428424 | C37: =C25/C26-1 -> -0.47209805 | D37: =D25/D26-1 -> -0.4890054 | E37: =E25/E26-1 -> -0.48575293 | F37: =F25/F26-1 -> -0.42081558 | G37: =G25/G26-1 -> -0.44817709 | H37: =H25/H26-1 -> -0.48151799 | I37: =I25/I26-1 -> -0.46997949 | ... N37: =N25/N26-1 -> -0.45950367 | P37: * 21年春节：2.11-2.17
A39: 实际利润（购物零售+本地生活） | E39: 购物零售+本地生活 | J39: 购物零售+本地生活
A40: 年月 | B40: 利润额 | C40: P1利润额 | E40: 利润实际 | F40: 25年方案二 | G40: 24年 | H40: 23年 | J40: 24年占比 | K40: 23年占比 | L40: 2025建议权重 | M40: 按季度
A41: 44896 | B41: 52710000 | E41: 1月 | F41: 27381363 | G41: 34006764 | H41: 48124681 | J41: =G41/$G$53 -> 0.11364594 | K41: =H41/$H$53 -> 0.11846536 | L41: =J41*0.6+K41*0.4 -> 0.11557371 | M41: =SUM(L41:L43) -> 0.27695239
A42: 44927 | B42: 48124681 | C42: 47445507 | E42: 2月 | F42: 18305519 | G42: 23684768 | H42: 30883670 | J42: =G42/$G$53 -> 0.079151245 | K42: =H42/$H$53 -> 0.076024295 | L42: =J42*0.6+K42*0.4 -> 0.077900465
A43: 44958 | B43: 30883670 | C43: 30961024 | E43: 3月 | F43: 19680590 | G43: 25054034 | H43: 33760031 | J43: =G43/$G$53 -> 0.083727143 | K43: =H43/$H$53 -> 0.083104843 | L43: =J43*0.6+K43*0.4 -> 0.083478223
A44: 44986 | B44: 33760031 | C44: 34659250 | E44: 4月 | F44: 19756444 | G44: 24919117 | H44: 34204404 | J44: =G44/$G$53 -> 0.083276271 | K44: =H44/$H$53 -> 0.084198728 | L44: =J44*0.6+K44*0.4 -> 0.083645254 | M44: =SUM(L44:L46) -> 0.23576219
A45: 45017 | B45: 34204404 | C45: 35372106 | E45: 5月 | F45: 17974661 | G45: 22040447 | H45: 31976609 | J45: =G45/$G$53 -> 0.073656151 | K45: =H45/$H$53 -> 0.078714711 | L45: =J45*0.6+K45*0.4 -> 0.075679575
A46: 45047 | B46: 31976609 | C46: 32771260 | E46: 6月 | F46: 18032764 | G46: 22879456 | H46: 31037674 | J46: =G46/$G$53 -> 0.076460002 | K46: =H46/$H$53 -> 0.076403396 | L46: =J46*0.6+K46*0.4 -> 0.07643736
A47: 45078 | B47: 31037674 | C47: 31097230 | E47: 7月 | F47: 16973036 | G47: 21936037 | H47: 28669117 | J47: =G47/$G$53 -> 0.073307228 | K47: =H47/$H$53 -> 0.070572877 | L47: =J47*0.6+K47*0.4 -> 0.072213487 | M47: =SUM(L47:L49) -> 0.22073025
A48: 45108 | B48: 28669117 | C48: 29598858 | E48: 8月 | F48: 17394206 | G48: 21669839 | H48: 30480858 | J48: =G48/$G$53 -> 0.072417629 | K48: =H48/$H$53 -> 0.07503272 | L48: =J48*0.6+K48*0.4 -> 0.073463665
A49: 45139 | B49: 30480858 | C49: 32163300 | E49: 9月 | F49: 17756288 | G49: 22210990 | H49: 30993082 | J49: =G49/$G$53 -> 0.074226084 | K49: =H49/$H$53 -> 0.076293629 | L49: =J49*0.6+K49*0.4 -> 0.075053102
A50: 45170 | B50: 30993082 | C50: 32167150 | E50: 10月 | F50: 18244765 | G50: 23889521 | H50: 30396484 | J50: =G50/$G$53 -> 0.079835502 | K50: =H50/$H$53 -> 0.074825022 | L50: =J50*0.6+K50*0.4 -> 0.07783131 | M50: =SUM(L50:L52) -> 0.26655516
A51: 45200 | B51: 30396484 | C51: 30891292 | E51: 11月 | F51: 22893790 | G51: 29188984 | H51: 38054014 | J51: =G51/$G$53 -> 0.097545581 | K51: =H51/$H$53 -> 0.093675057 | L51: =J51*0.6+K51*0.4 -> 0.095997371
A52: 45231 | B52: 38054014 | C52: 38617070 | E52: 12月 | F52: 22600144 | G52: 27754349 | H52: 37653592 | J52: =G52/$G$53 -> 0.092751226 | K52: =H52/$H$53 -> 0.092689367 | L52: =J52*0.6+K52*0.4 -> 0.092726482
A53: 45261 | B53: 37653592 | C53: 38159202 | E53: 全年 | F53: =SUM(F41:F52) -> 2.3699357e+08 | G53: =SUM(G41:G52) -> 2.992343e+08 | H53: =SUM(H41:H52) -> 4.0623422e+08
A54: 45292 | B54: 34006764 | C54: 35889628 | E54: 同比降幅 | F54: =F53/G53-1 -> -0.208 | G54: =G53/H53-1 -> -0.26339463
A55: 45323 | B55: 23684768 | C55: 25267100
A56: 45352 | B56: 25054034 | C56: 27020817
A57: 45383 | B57: 24919117 | C57: 26343392
A58: 45413 | B58: 22040447 | C58: 23793133 | E58: P1 | J58: P1
A59: 45444 | B59: 22879456 | C59: 24544679 | E59: 利润实际 | F59: 25年方案二 | G59: 24年 | H59: 23年 | J59: 24年占比 | K59: 23年占比 | L59: 2025建议权重 | M59: 按季度
A60: 45474 | B60: 21936037 | C60: 23924606 | E60: 1月 | F60: 28645816 | G60: 35889628 | H60: 47445507 | J60: =G60/$G$72 -> 0.11245865 | K60: =H60/$H$72 -> 0.11462946 | L60: =J60*0.6+K60*0.4 -> 0.11332698 | M60: =SUM(L60:L62) -> 0.27504823
A61: 45505 | B61: 21669839 | C61: 23745764 | E61: 2月 | F61: 19566257 | G61: 25267100 | H61: 30961024 | J61: =G61/$G$72 -> 0.079173404 | K61: =H61/$H$72 -> 0.074802563 | L61: =J61*0.6+K61*0.4 -> 0.077425068
A62: 45536 | B62: 22210990 | C62: 23627126 | E62: 3月 | F62: 21305059 | G62: 27020817 | H62: 34659250 | J62: =G62/$G$72 -> 0.084668603 | K62: =H62/$H$72 -> 0.083737564 | L62: =J62*0.6+K62*0.4 -> 0.084296187
A63: 45566 | B63: 23889521 | C63: 25282712 | E63: 4月 | F63: 21213682 | G63: 26343392 | H63: 35372106 | J63: =G63/$G$72 -> 0.08254592 | K63: =H63/$H$72 -> 0.085459841 | L63: =J63*0.6+K63*0.4 -> 0.083711488 | M63: =SUM(L63:L65) -> 0.23631331
A64: 45597 | B64: 29188984 | C64: 30659211 | E64: 5月 | F64: 19358406 | G64: 23793133 | H64: 32771260 | J64: =G64/$G$72 -> 0.07455479 | K64: =H64/$H$72 -> 0.079176136 | L64: =J64*0.6+K64*0.4 -> 0.076403328
A65: 45627 | B65: 27754349 | C65: 29038042 | E65: 6月 | F65: 19311980 | G65: 24544679 | H65: 31097230 | J65: =G65/$G$72 -> 0.076909728 | K65: =H65/$H$72 -> 0.07513164 | L65: =J65*0.6+K65*0.4 -> 0.076198493
A66: 45658 | E66: 7月 | F66: 18608729 | G66: 23924606 | H66: 29598858 | J66: =G66/$G$72 -> 0.074966755 | K66: =H66/$H$72 -> 0.071511538 | L66: =J66*0.6+K66*0.4 -> 0.073584668 | M66: =SUM(L66:L68) -> 0.22481881
A67: 45689 | E67: 8月 | F67: 19153660 | G67: 23745764 | H67: 32163300 | J67: =G67/$G$72 -> 0.074406361 | K67: =H67/$H$72 -> 0.07770729 | L67: =J67*0.6+K67*0.4 -> 0.075726733
A68: 45717 | E68: 9月 | F68: 19098406 | G68: 23627126 | H68: 32167150 | J68: =G68/$G$72 -> 0.074034614 | K68: =H68/$H$72 -> 0.077716592 | L68: =J68*0.6+K68*0.4 -> 0.075507405
A69: 45748 | E69: 10月 | F69: 19509787 | G69: 25282712 | H69: 30891292 | J69: =G69/$G$72 -> 0.079222323 | K69: =H69/$H$72 -> 0.074634089 | L69: =J69*0.6+K69*0.4 -> 0.07738703 | M69: =SUM(L69:L71) -> 0.26381965
A70: 45778 | E70: 11月 | F70: 24319004 | G70: 30659211 | H70: 38617070 | J70: =G70/$G$72 -> 0.096069359 | K70: =H70/$H$72 -> 0.093299751 | L70: =J70*0.6+K70*0.4 -> 0.094961516
A71: 45809 | E71: 12月 | F71: 23953661 | G71: 29038042 | H71: 38159202 | J71: =G71/$G$72 -> 0.090989493 | K71: =H71/$H$72 -> 0.092193531 | L71: =J71*0.6+K71*0.4 -> 0.091471108
A72: 45839 | E72: 全年 | F72: =SUM(F60:F71) -> 2.5404445e+08 | G72: =SUM(G60:G71) -> 3.1913621e+08 | H72: =SUM(H60:H71) -> 413903249
A73: 45870 | F73: =F72/G72-1 -> -0.20396232 | G73: =G72/H72-1 -> -0.2289594
A74: 45901
A75: 45931
A76: 45962
A77: 45992

Sheet 方案3预测
A1: 年月 | B1: 利润额 | C1: 趋势预测(利润额) | D1: 置信下限(利润额) | E1: 置信上限(利润额)
A2: 44896 | B2: 48308000
A3: 44927 | B3: 47418143 | G3: 706538 | H3: =G3+表1[[#This Row],[利润额]] -> 48124681
A4: 44958 | B4: 30642607 | G4: 241063 | H4: =G4+表1[[#This Row],[利润额]] -> 30883670
A5: 44986 | B5: 33392210 | G5: 367821 | H5: =G5+表1[[#This Row],[利润额]] -> 33760031
A6: 45017 | B6: 33852090 | G6: 352315 | H6: =G6+表1[[#This Row],[利润额]] -> 34204404
A7: 45047 | B7: 31498367 | G7: 478242 | H7: =G7+表1[[#This Row],[利润额]] -> 31976609
A8: 45078 | B8: 30298797 | G8: 738877 | H8: =G8+表1[[#This Row],[利润额]] -> 31037674
A9: 45108 | B9: 28220366 | G9: 448751 | H9: =G9+表1[[#This Row],[利润额]] -> 28669117
A10: 45139 | B10: 29898575 | G10: 582283 | H10: =G10+表1[[#This Row],[利润额]] -> 30480858
A11: 45170 | B11: 30053788 | G11: 939294 | H11: =G11+表1[[#This Row],[利润额]] -> 30993082
A12: 45200 | B12: 29436563 | G12: 959921 | H12: =G12+表1[[#This Row],[利润额]] -> 30396484
A13: 45231 | B13: 37262065 | G13: 791949 | H13: =G13+表1[[#This Row],[利润额]] -> 38054014
A14: 45261 | B14: 36649962 | F14: 本地生活（旅行社） | G14: 1003631 | H14: =G14+表1[[#This Row],[利润额]] -> 37653592 | I14: 购物公司+本地生活
A15: 45292 | B15: 33320359 | G15: 686405 | H15: =G15+表1[[#This Row],[利润额]] -> 34006764 | I15: =SUM(H15:H17)/SUM($H$15:$H$26) -> 0.27652433 | P15: 1046313 | Q15: 1046313 | R15: 1046313 | S15: 1046313 | T15: 1046313
A16: 45323 | B16: 23139465 | G16: 545303 | H16: =G16+表1[[#This Row],[利润额]] -> 23684768 | P16: 751501 | Q16: 751501 | R16: 751501 | S16: 751501 | T16: 751501
A17: 45352 | B17: 24789012 | G17: 265022 | H17: =G17+表1[[#This Row],[利润额]] -> 25054034 | P17: 592809.8 | Q17: 592809.8 | R17: 592809.8 | S17: 592809.8 | T17: 592809.8
A18: 45383 | B18: 24686292 | G18: 232825 | H18: =G18+表1[[#This Row],[利润额]] -> 24919117 | I18: =SUM(H18:H20)/SUM($H$15:$H$26) -> 0.23339242 | P18: 601844.3 | Q18: 601844.3 | R18: 601844.3 | S18: 601844.3 | T18: 601844.3
A19: 45413 | B19: 21738307 | G19: 302140 | H19: =G19+表1[[#This Row],[利润额]] -> 22040447 | P19: 726647 | Q19: 726647 | R19: 726647 | S19: 726647 | T19: 726647
A20: 45444 | B20: 22590734 | G20: 288721 | H20: =G20+表1[[#This Row],[利润额]] -> 22879456 | P20: 648327 | Q20: 648327 | R20: 648327 | S20: 648327 | T20: 648327
A21: 45474 | B21: 21807770 | G21: 128267 | H21: =G21+表1[[#This Row],[利润额]] -> 21936037 | I21: =SUM(H21:H23)/SUM($H$15:$H$26) -> 0.21995094 | P21: 543728.7 | Q21: 543728.7 | R21: 543728.7 | S21: 543728.7 | T21: 543728.7
A22: 45505 | B22: 21463665 | G22: 206174 | H22: =G22+表1[[#This Row],[利润额]] -> 21669839 | P22: 483678.5 | Q22: 483678.5 | R22: 483678.5 | S22: 483678.5 | T22: 483678.5
A23: 45536 | B23: 21792338 | G23: 418653 | H23: =G23+表1[[#This Row],[利润额]] -> 22210990 | P23: 623276.1 | Q23: 623276.1 | R23: 623276.1 | S23: 623276.1 | T23: 623276.1
A24: 45566 | B24: 23541594 | G24: 347927 | H24: =G24+表1[[#This Row],[利润额]] -> 23889521 | I24: =SUM(H24:H26)/SUM($H$15:$H$26) -> 0.27013231 | P24: 665681 | Q24: 665681 | R24: 665681 | S24: 665681 | T24: 665681
A25: 45597 | B25: 29061437 | G25: 127547 | H25: =G25+表1[[#This Row],[利润额]] -> 29188984 | P25: 387372 | Q25: 387372 | R25: 387372 | S25: 387372 | T25: 387372
A26: 45627 | B26: 28574382 | C26: 28574382 | D26: 28574382 | E26: 28574382 | F26: 1月取中、差额加到7月 | G26: 1月7月调整版 | H26: =35273/11*31+27654942.7777778 -> 27754349 | J26: =11931142/12*31 -> 30822117 | M26: 季度占比二次调整
A27: 45658 | C27: =_xlfn.FORECAST.ETS(A27,$B$2:$B$26,$A$2:$A$26,12,1) -> 25834585 | D27: =C27-_xlfn.FORECAST.ETS.CONFINT(A27,$B$2:$B$26,$A$2:$A$26,0.95,12,1) -> 22974354 | E27: =C27+_xlfn.FORECAST.ETS.CONFINT(A27,$B$2:$B$26,$A$2:$A$26,0.95,12,1) -> 28694815 | F27: =表1[[#This Row],[趋势预测(利润额)]]/C26-1 -> -0.095883011 | G27: 25834585 | H27: =SUM(G27:G29) -> 62461932 | I27: =H27/$G$42 -> 0.26745133 | K27: =G42*0.01 -> 2335450.4 | L27: =K27/3 -> 778483.46 | M27: =G27+L27 -> 26613068
A28: 45689 | C28: =_xlfn.FORECAST.ETS(A28,$B$2:$B$26,$A$2:$A$26,12,1) -> 14327880 | D28: =C28-_xlfn.FORECAST.ETS.CONFINT(A28,$B$2:$B$26,$A$2:$A$26,0.95,12,1) -> 11378230 | E28: =C28+_xlfn.FORECAST.ETS.CONFINT(A28,$B$2:$B$26,$A$2:$A$26,0.95,12,1) -> 17277531 | G28: 17277531 | L28: 778483.46 | M28: =G28+L28 -> 18056014
A29: 45717 | C29: =_xlfn.FORECAST.ETS(A29,$B$2:$B$26,$A$2:$A$26,12,1) -> 16312698 | D29: =C29-_xlfn.FORECAST.ETS.CONFINT(A29,$B$2:$B$26,$A$2:$A$26,0.95,12,1) -> 13275579 | E29: =C29+_xlfn.FORECAST.ETS.CONFINT(A29,$B$2:$B$26,$A$2:$A$26,0.95,12,1) -> 19349817 | G29: 19349817 | L29: 778483.46 | M29: =G29+L29 -> 20128300
A30: 45748 | C30: =_xlfn.FORECAST.ETS(A30,$B$2:$B$26,$A$2:$A$26,12,1) -> 16394847 | D30: =C30-_xlfn.FORECAST.ETS.CONFINT(A30,$B$2:$B$26,$A$2:$A$26,0.95,12,1) -> 13272045 | E30: =C30+_xlfn.FORECAST.ETS.CONFINT(A30,$B$2:$B$26,$A$2:$A$26,0.95,12,1) -> 19517649 | G30: 19517649 | H30: =SUM(G30:G32) -> 56606333 | I30: =H30/$G$42 -> 0.24237866 | K30: =-G42*0.01 -> -2335450.4 | L30: =-778483.461676023 -> -778483.46 | M30: =G30+L30 -> 18739165
A31: 45778 | C31: =_xlfn.FORECAST.ETS(A31,$B$2:$B$26,$A$2:$A$26,12,1) -> 13889561 | D31: =C31-_xlfn.FORECAST.ETS.CONFINT(A31,$B$2:$B$26,$A$2:$A$26,0.95,12,1) -> 10682716 | E31: =C31+_xlfn.FORECAST.ETS.CONFINT(A31,$B$2:$B$26,$A$2:$A$26,0.95,12,1) -> 17096406 | G31: 17096406 | L31: -778483.46 | M31: =G31+L31 -> 16317923
A32: 45809 | C32: =_xlfn.FORECAST.ETS(A32,$B$2:$B$26,$A$2:$A$26,12,1) -> 13842671 | D32: =C32-_xlfn.FORECAST.ETS.CONFINT(A32,$B$2:$B$26,$A$2:$A$26,0.95,12,1) -> 10553294 | E32: =C32+_xlfn.FORECAST.ETS.CONFINT(A32,$B$2:$B$26,$A$2:$A$26,0.95,12,1) -> 17132048 | G32: 19992278 | L32: -778483.46 | M32: =G32+L32 -> 19213794 | N32: =M32-1000000 -> 18213794
A33: 45839 | C33: =_xlfn.FORECAST.ETS(A33,$B$2:$B$26,$A$2:$A$26,12,1) -> 12409078 | D33: =C33-_xlfn.FORECAST.ETS.CONFINT(A33,$B$2:$B$26,$A$2:$A$26,0.95,12,1) -> 9038567.9 | E33: =C33+_xlfn.FORECAST.ETS.CONFINT(A33,$B$2:$B$26,$A$2:$A$26,0.95,12,1) -> 15779589 | G33: 15779589 | H33: =SUM(G33:G35) -> 49068979 | I33: =H33/$G$42 -> 0.210105 | K33: =G42*0.01 -> 2335450.4 | L33: 778483.46 | M33: =G33+L33 -> 16558072
A34: 45870 | C34: =_xlfn.FORECAST.ETS(A34,$B$2:$B$26,$A$2:$A$26,12,1) -> 13015469 | D34: =C34-_xlfn.FORECAST.ETS.CONFINT(A34,$B$2:$B$26,$A$2:$A$26,0.95,12,1) -> 9565121.8 | E34: =C34+_xlfn.FORECAST.ETS.CONFINT(A34,$B$2:$B$26,$A$2:$A$26,0.95,12,1) -> 16465816 | G34: 16465816 | L34: 778483.46 | M34: =G34+L34 -> 17244300
A35: 45901 | C35: =_xlfn.FORECAST.ETS(A35,$B$2:$B$26,$A$2:$A$26,12,1) -> 13294597 | D35: =C35-_xlfn.FORECAST.ETS.CONFINT(A35,$B$2:$B$26,$A$2:$A$26,0.95,12,1) -> 9765620.3 | E35: =C35+_xlfn.FORECAST.ETS.CONFINT(A35,$B$2:$B$26,$A$2:$A$26,0.95,12,1) -> 16823574 | G35: 16823574 | L35: 778483.46 | M35: =G35+L35 -> 17602058
A36: 45931 | C36: =_xlfn.FORECAST.ETS(A36,$B$2:$B$26,$A$2:$A$26,12,1) -> 13948975 | D36: =C36-_xlfn.FORECAST.ETS.CONFINT(A36,$B$2:$B$26,$A$2:$A$26,0.95,12,1) -> 10342493 | E36: =C36+_xlfn.FORECAST.ETS.CONFINT(A36,$B$2:$B$26,$A$2:$A$26,0.95,12,1) -> 17555456 | G36: 17555456 | H36: =SUM(G36:G38) -> 65407794 | I36: =H36/$G$42 -> 0.28006501 | K36: =-G42*0.01 -> -2335450.4 | L36: -778483.46 | M36: =G36+L36 -> 16776973 | N36: =M36+1000000 -> 17776973
A37: 45962 | C37: =_xlfn.FORECAST.ETS(A37,$B$2:$B$26,$A$2:$A$26,12,1) -> 20487854 | D37: =C37-_xlfn.FORECAST.ETS.CONFINT(A37,$B$2:$B$26,$A$2:$A$26,0.95,12,1) -> 16804920 | E37: =C37+_xlfn.FORECAST.ETS.CONFINT(A37,$B$2:$B$26,$A$2:$A$26,0.95,12,1) -> 24170788 | G37: 24170788 | L37: -778483.46 | M37: =G37+L37 -> 23392304
A38: 45992 | C38: =_xlfn.FORECAST.ETS(A38,$B$2:$B$26,$A$2:$A$26,12,1) -> 19923150 | D38: =C38-_xlfn.FORECAST.ETS.CONFINT(A38,$B$2:$B$26,$A$2:$A$26,0.95,12,1) -> 16164750 | E38: =C38+_xlfn.FORECAST.ETS.CONFINT(A38,$B$2:$B$26,$A$2:$A$26,0.95,12,1) -> 23681550 | G38: 23681550 | L38: -778483.46 | M38: =G38+L38 -> 22903067
M39: =SUM(M27:M38) -> 2.3354504e+08
K40: 27654943
A41: 2024年 | B41: =SUM(B15:B26) -> 2.9650535e+08
A42: 2025全年预测利润额 | C42: =SUM(C27:C38) -> 1.9368137e+08 | D42: =SUM(D27:D38) -> 1.5381769e+08 | E42: =SUM(E27:E38) -> 2.3354504e+08 | G42: =SUM(G27:G38) -> 2.3354504e+08 | J42: 2024年12月利润 | M42: 不要跟P1弄混
A43: 同比2024 | C43: =C42/$B$41-1 -> -0.34678628 | D43: =D42/$B$41-1 -> -0.48123132 | E43: =E42/$B$41-1 -> -0.21234125 | I43: 日期 | J43: P1 | K43: 购物零售 | L43: 旅行社本地生活 | M43: 购物零售+本地生活
I44: 45627 | J44: 694483 | K44: 682204
I45: 45628 | J45: 932599 | K45: 887892
I46: 45629 | J46: 916729 | K46: 844702
I47: 45630 | J47: 859773 | K47: 779390
I48: 45631 | J48: 917668 | K48: 805611
I49: 45632 | J49: 886008 | K49: 827132
I50: 45633 | J50: 683268 | K50: 666284
I51: 45634 | J51: 735906 | K51: 725421
I52: 45635 | J52: 1564160 | K52: 1548181
I53: 45636 | J53: 1375428 | K53: 1295403
I54: 45637 | J54: 1105410 | K54: 1077076
I55: 45638 | J55: 1259710 | K55: 1226271
... I58: 45641 | J58: 897720 | K58: 882905
I59: 12月预测 | J59: =AVERAGE(J58,J44:J51)*25+SUM(J52:J57) -> 29038042 | K59: =AVERAGE(K58,K44:K51)*25+SUM(K52:K57) -> 27654943 | L59: =35273/11*31 -> 99405.727 | M59: =L59+K59 -> 27754349
I60: 1-11月实际 | J60: =SUM(J62:J72) -> 290098168 | K60: =SUM(K62:K72) -> 267930969 | L60: =SUM(L62:L72) -> 3548984 | M60: =L60+K60 -> 271479953
I61: 2024年度实际 | J61: =J60+J59 -> 3.1913621e+08 | K61: =K60+K59 -> 2.9558591e+08 | L61: =L60+L59 -> 3648389.7 | M61: =L61+K61 -> 2.992343e+08
I62: 1月 | J62: 35889628 | K62: 33320357 | L62: 686405 | M62: =L62+K62 -> 34006762
I63: 2月 | J63: 25267100 | K63: 23139465 | L63: 545303 | M63: =L63+K63 -> 23684768
I64: 3月 | J64: 27020817 | K64: 24789013 | L64: 265022 | M64: =L64+K64 -> 25054035
I65: 4月 | J65: 26343392 | K65: 24686293 | L65: 232825 | M65: =L65+K65 -> 24919118
I66: 5月 | J66: 23793133 | K66: 21738306 | L66: 302140 | M66: =L66+K66 -> 22040446
I67: 6月 | J67: 24544679 | K67: 22590734 | L67: 288721 | M67: =L67+K67 -> 22879455
I68: 7月 | J68: 23924606 | K68: 21807771 | L68: 128267 | M68: =L68+K68 -> 21936038
I69: 8月 | J69: 23745764 | K69: 21463665 | L69: 206174 | M69: =L69+K69 -> 21669839
I70: 9月 | J70: 23627126 | K70: 21792336 | L70: 418653 | M70: =L70+K70 -> 22210989
I71: 10月 | J71: 25282712 | K71: 23541592 | L71: 347927 | M71: =L71+K71 -> 23889519
I72: 11月 | J72: 30659211 | K72: 29061437 | L72: 127547 | M72: =L72+K72 -> 29188984

Sheet Sheet1
A1: 年月 | B1: 利润额 | C1: 趋势预测(利润额) | D1: 置信下限(利润额) | E1: 置信上限(利润额)
A2: 44896 | B2: 52710000
A3: 44927 | B3: 48124681
A4: 44958 | B4: 30883670
A5: 44986 | B5: 33760031
A6: 45017 | B6: 34204404
A7: 45047 | B7: 31976609
A8: 45078 | B8: 31037674
A9: 45108 | B9: 28669117
A10: 45139 | B10: 30480858
A11: 45170 | B11: 30993082
A12: 45200 | B12: 30396484
A13: 45231 | B13: 38054014
... A25: 45597 | B25: 29188984
A26: 45627 | B26: 28673788 | C26: 28673788 | D26: 28673788 | E26: 28673788
A27: 45658 | C27: =_xlfn.FORECAST.ETS(A27,$B$2:$B$26,$A$2:$A$26,12,1) -> 25303105 | D27: =C27-_xlfn.FORECAST.ETS.CONFINT(A27,$B$2:$B$26,$A$2:$A$26,0.95,12,1) -> 21277763 | E27: =C27+_xlfn.FORECAST.ETS.CONFINT(A27,$B$2:$B$26,$A$2:$A$26,0.95,12,1) -> 29328446 | G27: =表2[[#This Row],[趋势预测(利润额)]]/$C$40 -> 0.135338 | H27: =表2[[#This Row],[置信下限(利润额)]]/$D$40 -> 0.16259918 | I27: =表2[[#This Row],[置信上限(利润额)]]/$E$40 -> 0.12066122
A28: 45689 | C28: =_xlfn.FORECAST.ETS(A28,$B$2:$B$26,$A$2:$A$26,12,1) -> 13691806 | D28: =C28-_xlfn.FORECAST.ETS.CONFINT(A28,$B$2:$B$26,$A$2:$A$26,0.95,12,1) -> 9540618.7 | E28: =C28+_xlfn.FORECAST.ETS.CONFINT(A28,$B$2:$B$26,$A$2:$A$26,0.95,12,1) -> 17842992 | G28: =表2[[#This Row],[趋势预测(利润额)]]/$C$40 -> 0.073232975 | H28: =表2[[#This Row],[置信下限(利润额)]]/$D$40 -> 0.072906949 | I28: =表2[[#This Row],[置信上限(利润额)]]/$E$40 -> 0.073408501
